{
  "type": "Feature",
  "properties": {
    "gn:admin1_code":"0",
    "gn:asciiname":"Sahil",
    "gn:country_code":"SA",
    "gn:dem":578,
    "gn:feature_class":"P",
    "gn:feature_code":"PPL",
    "gn:name":"S\u0101\u1e29il",
    "gn:population":0,
    "gn:timezone":"Asia/Riyadh",
    "iso:country":"SA",
    "name:ara_x_preferred":[
        "S\u0101\u1e29il"
    ],
    "name:ceb_x_preferred":[
        "Sahil"
    ],
    "name:fra_x_preferred":[
        "Sahil"
    ],
    "name:rus_x_preferred":[
        "\u0421\u0430\u0445\u0438\u043b"
    ],
    "name:swe_x_preferred":[
        "Sahil"
    ],
    "name:tur_x_preferred":[
        "Sahil"
    ],
    "wof:name":"Sahil",
    "wof:placetype":"locality"
},
  "geometry": {"coordinates":[41.84889,19.37845],"type":"Point"}
}