{
  "type": "Feature",
  "properties": {
    "gn:admin1_code":"10",
    "gn:asciiname":"Mishash as Suhul",
    "gn:country_code":"SA",
    "gn:dem":695,
    "gn:feature_class":"P",
    "gn:feature_code":"PPL",
    "gn:name":"Mish\u0101sh as Suh\u016bl",
    "gn:population":0,
    "gn:timezone":"Asia/Riyadh",
    "iso:country":"SA",
    "name:ara_x_preferred":[
        "\u0645\u0634\u0627\u0634 \u0627\u0644\u0633\u0647\u0648\u0644"
    ],
    "name:und_x_variant":[
        "Mish\u0101sh as Suh\u016bl"
    ],
    "wof:name":"Mishash as Suhul",
    "wof:placetype":"locality"
},
  "geometry": {"coordinates":[45.78557,25.29131],"type":"Point"}
}