{
  "type": "Feature",
  "properties": {
    "gn:admin1_code":"0",
    "gn:asciiname":"Makhshushah",
    "gn:country_code":"SA",
    "gn:dem":571,
    "gn:feature_class":"P",
    "gn:feature_code":"PPL",
    "gn:name":"Makhsh\u016bshah",
    "gn:population":0,
    "gn:timezone":"Asia/Riyadh",
    "iso:country":"SA",
    "name:und_x_variant":[
        "Makhsh\u016bshah"
    ],
    "wof:name":"Makhshushah",
    "wof:placetype":"locality"
},
  "geometry": {"coordinates":[41.79388,19.4428],"type":"Point"}
}