{
  "type": "Feature",
  "properties": {
    "gn:admin1_code":"13",
    "gn:asciiname":"Ash Shirthah",
    "gn:country_code":"SA",
    "gn:dem":1021,
    "gn:feature_class":"P",
    "gn:feature_code":"PPL",
    "gn:name":"Ash Shirthah",
    "gn:population":0,
    "gn:timezone":"Asia/Riyadh",
    "iso:country":"SA",
    "wof:name":"Ash Shirthah",
    "wof:placetype":"locality"
},
  "geometry": {"coordinates":[42.31667,26.61667000000001],"type":"Point"}
}