{
  "type": "Feature",
  "properties": {
    "gn:admin1_code":"0",
    "gn:asciiname":"Al `Amrah",
    "gn:country_code":"SA",
    "gn:dem":2236,
    "gn:feature_class":"P",
    "gn:feature_code":"PPL",
    "gn:name":"\u0100l \u2018Amrah",
    "gn:population":0,
    "gn:timezone":"Asia/Riyadh",
    "iso:country":"SA",
    "name:und_x_variant":[
        "Al Amarah",
        "\u0100l \u2018Amrah"
    ],
    "wof:name":"Al `Amrah",
    "wof:placetype":"locality"
},
  "geometry": {"coordinates":[42.97454000000001,18.12204],"type":"Point"}
}