{
  "type": "Feature",
  "properties": {
    "gn:admin1_code":"10",
    "gn:asciiname":"Al Wusta",
    "gn:country_code":"SA",
    "gn:dem":626,
    "gn:feature_class":"P",
    "gn:feature_code":"PPL",
    "gn:name":"Al Wus\u0163\u00e1",
    "gn:population":0,
    "gn:timezone":"Asia/Riyadh",
    "iso:country":"SA",
    "name:ara_x_preferred":[
        "Al Wus\u0163\u00e1"
    ],
    "name:ara_x_variant":[
        "\u0627\u0644\u0648\u0633\u0637\u0649"
    ],
    "name:deu_x_preferred":[
        "Al-Wusta"
    ],
    "name:eus_x_preferred":[
        "Al Wusta"
    ],
    "name:und_x_variant":[
        "Al Wust\u0101"
    ],
    "wof:name":"Al Wusta",
    "wof:placetype":"locality"
},
  "geometry": {"coordinates":[46.20799,24.58824],"type":"Point"}
}