{
  "type": "Feature",
  "properties": {
    "gn:admin1_code":"10",
    "gn:asciiname":"Al Qurayyah",
    "gn:country_code":"SA",
    "gn:dem":959,
    "gn:feature_class":"P",
    "gn:feature_code":"PPL",
    "gn:name":"Al Qurayyah",
    "gn:population":0,
    "gn:timezone":"Asia/Riyadh",
    "iso:country":"SA",
    "name:fas_x_preferred":[
        "\u0627\u0644\u0642\u0631\u06cc\u0627\u0647"
    ],
    "name:nno_x_preferred":[
        "Al Qurayyah"
    ],
    "wof:name":"Al Qurayyah",
    "wof:placetype":"locality"
},
  "geometry": {"coordinates":[43.26667,24.91667],"type":"Point"}
}