{
  "type": "Feature",
  "properties": {
    "gn:admin1_code":"13",
    "gn:asciiname":"An Nizim",
    "gn:country_code":"SA",
    "gn:dem":757,
    "gn:feature_class":"P",
    "gn:feature_code":"PPL",
    "gn:name":"An Niz\u0327\u012bm",
    "gn:population":0,
    "gn:timezone":"Asia/Riyadh",
    "iso:country":"SA",
    "name:ara_x_preferred":[
        "An Niz\u0327\u012bm"
    ],
    "name:ara_x_variant":[
        "\u0627\u0644\u0646\u0651\u0650\u0638\u064a\u0645"
    ],
    "wof:name":"An Nizim",
    "wof:placetype":"locality"
},
  "geometry": {"coordinates":[42.20054,27.94335],"type":"Point"}
}