{
  "type": "Feature",
  "properties": {
    "gn:admin1_code":"17",
    "gn:asciiname":"Al Hadrur",
    "gn:country_code":"SA",
    "gn:dem":35,
    "gn:feature_class":"P",
    "gn:feature_code":"PPL",
    "gn:name":"Al \u1e28a\u1e11r\u016br",
    "gn:population":0,
    "gn:timezone":"Asia/Riyadh",
    "iso:country":"SA",
    "name:ara_x_preferred":[
        "\u0627\u0644\u062d\u0636\u0631\u0648\u0631"
    ],
    "name:fas_x_preferred":[
        "\u0627\u0644\u062d\u0636\u0648\u0631"
    ],
    "name:nno_x_preferred":[
        "Al Hadrur"
    ],
    "name:und_x_variant":[
        "\u1e28uthr\u016br",
        "Al \u1e28a\u1e11r\u016br"
    ],
    "wof:name":"Al Hadrur",
    "wof:placetype":"locality"
},
  "geometry": {"coordinates":[42.86711,16.5437],"type":"Point"}
}