{
  "type": "Feature",
  "properties": {
    "gn:admin1_code":"14",
    "gn:asciiname":"Arya`",
    "gn:country_code":"SA",
    "gn:dem":1743,
    "gn:feature_class":"P",
    "gn:feature_code":"PPL",
    "gn:name":"Arya\u2018",
    "gn:population":0,
    "gn:timezone":"Asia/Riyadh",
    "iso:country":"SA",
    "name:nno_x_preferred":[
        "Arya`"
    ],
    "name:und_x_variant":[
        "D\u0101r ar R\u012b\u2018",
        "Arya\u2018"
    ],
    "wof:name":"Arya`",
    "wof:placetype":"locality"
},
  "geometry": {"coordinates":[40.62431,21.08497],"type":"Point"}
}