{
  "type": "Feature",
  "properties": {
    "gn:admin1_code":"0",
    "gn:asciiname":"Raghwan",
    "gn:cc2":"SA",
    "gn:country_code":"SA",
    "gn:dem":-9999,
    "gn:feature_class":"P",
    "gn:feature_code":"PPL",
    "gn:name":"Raghw\u0101n",
    "gn:population":0,
    "gn:timezone":"Asia/Riyadh",
    "iso:country":"SA",
    "name:und_x_variant":[
        "Rughw\u0101n",
        "Raghw\u0101n"
    ],
    "wof:name":"Raghwan",
    "wof:placetype":"locality"
},
  "geometry": {"coordinates":[39.51667,20.66667],"type":"Point"}
}