{
  "type": "Feature",
  "properties": {
    "gn:admin1_code":"10",
    "gn:asciiname":"Al Wusayyi`ah",
    "gn:country_code":"SA",
    "gn:dem":694,
    "gn:feature_class":"P",
    "gn:feature_code":"PPL",
    "gn:name":"Al Wusayyi\u2018ah",
    "gn:population":0,
    "gn:timezone":"Asia/Riyadh",
    "iso:country":"SA",
    "name:und_x_variant":[
        "Al Wusayyi\u2018ah"
    ],
    "wof:name":"Al Wusayyi`ah",
    "wof:placetype":"locality"
},
  "geometry": {"coordinates":[45.0198,26.00601],"type":"Point"}
}