{
  "type": "Feature",
  "properties": {
    "gn:admin1_code":"5",
    "gn:asciiname":"Wasitah",
    "gn:country_code":"SA",
    "gn:dem":186,
    "gn:feature_class":"P",
    "gn:feature_code":"PPL",
    "gn:name":"W\u0101si\u0163ah",
    "gn:population":0,
    "gn:timezone":"Asia/Riyadh",
    "iso:country":"SA",
    "name:ara_x_preferred":[
        "\u0627\u0644\u0648\u0627\u0633\u0637\u0629"
    ],
    "name:fas_x_preferred":[
        "\u0627\u0644\u0648\u0627\u0633\u0637\u0647"
    ],
    "name:nno_x_preferred":[
        "Wasitah"
    ],
    "name:und_x_variant":[
        "Wasta",
        "W\u0101si\u0163ah"
    ],
    "name:urd_x_preferred":[
        "\u0627\u0644\u0648\u0627\u0633\u0637\u06c1"
    ],
    "wof:name":"Wasitah",
    "wof:placetype":"locality"
},
  "geometry": {"coordinates":[38.90124,23.88255],"type":"Point"}
}