{
  "type": "Feature",
  "properties": {
    "gn:admin1_code":"0",
    "gn:asciiname":"Al Masha'ikh",
    "gn:country_code":"SA",
    "gn:dem":9,
    "gn:feature_class":"P",
    "gn:feature_code":"PPL",
    "gn:name":"Al Mash\u0101\u2019ikh",
    "gn:population":0,
    "gn:timezone":"Asia/Riyadh",
    "iso:country":"SA",
    "name:und_x_variant":[
        "El Mashaikh",
        "Al Mash\u0101\u2019ikh"
    ],
    "wof:name":"Al Masha'ikh",
    "wof:placetype":"locality"
},
  "geometry": {"coordinates":[41.08333,19.23333],"type":"Point"}
}