{
  "type": "Feature",
  "properties": {
    "gn:admin1_code":"10",
    "gn:asciiname":"Hafar al `Atk",
    "gn:country_code":"SA",
    "gn:dem":571,
    "gn:feature_class":"P",
    "gn:feature_code":"PPL",
    "gn:name":"\u1e28afar al \u2018Atk",
    "gn:population":0,
    "gn:timezone":"Asia/Riyadh",
    "iso:country":"SA",
    "name:ara_x_preferred":[
        "\u062d\u0641\u0631 \u0627\u0644\u0639\u062a\u0643"
    ],
    "name:ara_x_variant":[
        "\u062d\u064e\u0641\u064e\u0631 \u0627\u0644\u0639\u064e\u062a\u0652\u0634"
    ],
    "name:und_x_variant":[
        "\u1e28afar al \u2018Atsh",
        "\u1e28afar al \u2018Atk"
    ],
    "wof:name":"Hafar al `Atk",
    "wof:placetype":"locality"
},
  "geometry": {"coordinates":[46.49808,25.95581],"type":"Point"}
}