{
  "type": "Feature",
  "properties": {
    "gn:admin1_code":"0",
    "gn:asciiname":"Al Ghutamiyah",
    "gn:country_code":"SA",
    "gn:dem":1684,
    "gn:feature_class":"P",
    "gn:feature_code":"PPL",
    "gn:name":"Al Ghutam\u012byah",
    "gn:population":0,
    "gn:timezone":"Asia/Riyadh",
    "iso:country":"SA",
    "name:und_x_variant":[
        "Al Ghutam\u012byah"
    ],
    "wof:name":"Al Ghutamiyah",
    "wof:placetype":"locality"
},
  "geometry": {"coordinates":[41.40129,20.30612],"type":"Point"}
}