{
  "type": "Feature",
  "properties": {
    "gn:admin1_code":"13",
    "gn:asciiname":"Al Mabda`",
    "gn:country_code":"SA",
    "gn:dem":1311,
    "gn:feature_class":"P",
    "gn:feature_code":"PPL",
    "gn:name":"Al Mabda\u2018",
    "gn:population":0,
    "gn:timezone":"Asia/Riyadh",
    "iso:country":"SA",
    "name:ara_x_preferred":[
        "\u0627\u0644\u0645\u0628\u062f\u0639"
    ],
    "name:und_x_variant":[
        "Al Mabda\u2018"
    ],
    "wof:name":"Al Mabda`",
    "wof:placetype":"locality"
},
  "geometry": {"coordinates":[41.30804000000001,27.20341],"type":"Point"}
}