{
  "type": "Feature",
  "properties": {
    "gn:admin1_code":"0",
    "gn:asciiname":"Al Mulayh",
    "gn:country_code":"SA",
    "gn:dem":992,
    "gn:feature_class":"P",
    "gn:feature_code":"PPL",
    "gn:name":"Al Mulay\u1e29",
    "gn:population":0,
    "gn:timezone":"Asia/Riyadh",
    "iso:country":"SA",
    "name:ara_x_preferred":[
        "\u0627\u0644\u0645\u0644\u064a\u062d"
    ],
    "name:und_x_variant":[
        "Al Mulay\u1e29"
    ],
    "wof:name":"Al Mulayh",
    "wof:placetype":"locality"
},
  "geometry": {"coordinates":[40.88573,27.19275],"type":"Point"}
}