{
  "type": "Feature",
  "properties": {
    "gn:admin1_code":"13",
    "gn:asciiname":"Al Qawsah",
    "gn:country_code":"SA",
    "gn:dem":1294,
    "gn:feature_class":"P",
    "gn:feature_code":"PPL",
    "gn:name":"Al Qaw\u015fah",
    "gn:population":0,
    "gn:timezone":"Asia/Riyadh",
    "iso:country":"SA",
    "name:und_x_variant":[
        "Qussa",
        "Al Qaw\u015fah"
    ],
    "wof:name":"Al Qawsah",
    "wof:placetype":"locality"
},
  "geometry": {"coordinates":[41.18333,27.05],"type":"Point"}
}