{
  "type": "Feature",
  "properties": {
    "gn:admin1_code":"17",
    "gn:asciiname":"Sayr",
    "gn:country_code":"SA",
    "gn:dem":17,
    "gn:feature_class":"P",
    "gn:feature_code":"PPL",
    "gn:name":"Sayr",
    "gn:population":0,
    "gn:timezone":"Asia/Riyadh",
    "iso:country":"SA",
    "name:und_x_variant":[
        "Sayy\u0101l",
        "Sair",
        "Seir",
        "Sayr"
    ],
    "wof:name":"Sayr",
    "wof:placetype":"locality"
},
  "geometry": {"coordinates":[41.81491,16.85047999999999],"type":"Point"}
}