{
  "type": "Feature",
  "properties": {
    "gn:country":"SA",
    "gn:fcode":"PPLX",
    "gn:population":0,
    "iso:country":"SA",
    "name:ara_x_preferred":[
        "\u0627\u0644\u0646\u0632\u0647\u0629"
    ],
    "name:eng_x_preferred":[
        "An Nuzhah"
    ],
    "name:eng_x_variant":[
        "Al Nuzha",
        "An Nuzhah"
    ],
    "qs_pg:aaroncc":"SA",
    "qs_pg:gn_country":"SA",
    "qs_pg:gn_fcode":"PPLX",
    "qs_pg:gn_pop":0,
    "qs_pg:name":"\u0627\u0644\u0646\u0632\u0647\u0629",
    "qs_pg:name_adm0":"\u0627\u0644\u0633\u0639\u0648\u062f\u064a\u0629",
    "qs_pg:name_adm1":"\u0627\u0644\u0631\u064a\u0627\u0636",
    "qs_pg:photos":5,
    "qs_pg:photos_1k":1,
    "qs_pg:photos_9k":1,
    "qs_pg:photos_9r":1,
    "qs_pg:photos_all":5,
    "qs_pg:photos_sr":1,
    "qs_pg:pop_sr":0,
    "qs_pg:qs_pg_placetype":"neighbourhood",
    "qs_pg:qs_pg_placetype_gp":"Suburb",
    "qs_pg:woe_adm0":23424938,
    "woe:adm0_id":23424938,
    "woe:name_adm0":"\u0627\u0644\u0633\u0639\u0648\u062f\u064a\u0629",
    "woe:name_adm1":"\u0627\u0644\u0631\u064a\u0627\u0636",
    "woe:placetype":"Suburb",
    "wof:name":"\u0627\u0644\u0646\u0632\u0647\u0629",
    "wof:placetype":"neighbourhood"
},
  "geometry": {"coordinates":[46.7075,24.75694],"type":"Point"}
}