{
  "type": "Feature",
  "properties": {
    "gn:admin1_code":"10",
    "gn:asciiname":"Zumayqah",
    "gn:country_code":"SA",
    "gn:dem":451,
    "gn:feature_class":"P",
    "gn:feature_code":"PPL",
    "gn:name":"Zumayqah",
    "gn:population":0,
    "gn:timezone":"Asia/Riyadh",
    "iso:country":"SA",
    "name:und_x_variant":[
        "Az Zumayqah",
        "Zumaykah",
        "Zumaiqa",
        "Zumaygah",
        "Zamaijah",
        "Zumayqah"
    ],
    "wof:name":"Zumayqah",
    "wof:placetype":"locality"
},
  "geometry": {"coordinates":[47.16322,23.95754],"type":"Point"}
}