{
  "type": "Feature",
  "properties": {
    "gn:admin1_code":"20",
    "gn:asciiname":"Mughayra'",
    "gn:country_code":"SA",
    "gn:dem":600,
    "gn:feature_class":"P",
    "gn:feature_code":"PPL",
    "gn:name":"Mughayr\u0101\u2019",
    "gn:population":0,
    "gn:timezone":"Asia/Riyadh",
    "iso:country":"SA",
    "name:ara_x_preferred":[
        "\u0645\u063a\u064a\u0631\u0627\u0621"
    ],
    "name:und_x_variant":[
        "Mughayr\u0101\u2019"
    ],
    "wof:name":"Mughayra'",
    "wof:placetype":"locality"
},
  "geometry": {"coordinates":[40.41657,29.85758],"type":"Point"}
}