{
  "type": "Feature",
  "properties": {
    "gn:admin1_code":"6",
    "gn:asciiname":"Ghanwa",
    "gn:country_code":"SA",
    "gn:dem":84,
    "gn:feature_class":"P",
    "gn:feature_code":"PPL",
    "gn:name":"Ghanw\u00e1",
    "gn:population":0,
    "gn:timezone":"Asia/Riyadh",
    "iso:country":"SA",
    "name:und_x_variant":[
        "Ghunwa",
        "Ghanw\u0101",
        "Ghanw\u00e1"
    ],
    "wof:name":"Ghanwa",
    "wof:placetype":"locality"
},
  "geometry": {"coordinates":[48.45861,27.01667],"type":"Point"}
}