{
  "type": "Feature",
  "properties": {
    "gn:admin1_code":"20",
    "gn:asciiname":"Qiyal",
    "gn:country_code":"SA",
    "gn:dem":625,
    "gn:feature_class":"P",
    "gn:feature_code":"PPLL",
    "gn:name":"Qiy\u0101l",
    "gn:population":0,
    "gn:timezone":"Asia/Riyadh",
    "iso:country":"SA",
    "name:ara_x_preferred":[
        "Qiy\u0101l"
    ],
    "wof:name":"Qiyal",
    "wof:placetype":"locality"
},
  "geometry": {"coordinates":[40.10556,30.07389],"type":"Point"}
}