{
  "type": "Feature",
  "properties": {
    "gn:admin1_code":"11",
    "gn:admin2_code":"10972263.0",
    "gn:asciiname":"Ar Ruwayhan",
    "gn:country_code":"SA",
    "gn:dem":2037,
    "gn:feature_class":"P",
    "gn:feature_code":"PPL",
    "gn:name":"Ar Ruway\u1e29\u0101n",
    "gn:population":0,
    "gn:timezone":"Asia/Riyadh",
    "iso:country":"SA",
    "name:ara_x_preferred":[
        "\u0622\u0644 \u0631\u0648\u062d\u0627\u0646"
    ],
    "name:und_x_variant":[
        "Ar Ruway\u1e29\u0101n"
    ],
    "wof:name":"Ar Ruwayhan",
    "wof:placetype":"locality"
},
  "geometry": {"coordinates":[41.95,19.53333],"type":"Point"}
}