{
  "type": "Feature",
  "properties": {
    "gn:admin1_code":"5",
    "gn:asciiname":"Abu `Alaq",
    "gn:country_code":"SA",
    "gn:dem":1177,
    "gn:feature_class":"P",
    "gn:feature_code":"PPL",
    "gn:name":"Ab\u016b \u2018Alaq",
    "gn:population":0,
    "gn:timezone":"Asia/Riyadh",
    "iso:country":"SA",
    "name:und_x_variant":[
        "Ab\u016b \u2018Alaq"
    ],
    "wof:name":"Abu `Alaq",
    "wof:placetype":"locality"
},
  "geometry": {"coordinates":[38.78333,24.81667],"type":"Point"}
}