{
  "type": "Feature",
  "properties": {
    "gn:admin1_code":"0",
    "gn:asciiname":"Dulaym",
    "gn:country_code":"SA",
    "gn:dem":2274,
    "gn:feature_class":"P",
    "gn:feature_code":"PPL",
    "gn:name":"Dulaym",
    "gn:population":0,
    "gn:timezone":"Asia/Riyadh",
    "iso:country":"SA",
    "wof:name":"Dulaym",
    "wof:placetype":"locality"
},
  "geometry": {"coordinates":[43.35779,17.98869],"type":"Point"}
}