{
  "type": "Feature",
  "properties": {
    "gn:admin1_code":"0",
    "gn:asciiname":"Al Bikah",
    "gn:cc2":"SA",
    "gn:country_code":"SA",
    "gn:dem":291,
    "gn:feature_class":"P",
    "gn:feature_code":"PPL",
    "gn:name":"Al Bik\u0101\u1e29",
    "gn:population":0,
    "gn:timezone":"Asia/Riyadh",
    "iso:country":"SA",
    "name:ara_x_preferred":[
        "Al Bik\u0101\u1e29"
    ],
    "name:und_x_variant":[
        "Bika"
    ],
    "wof:name":"Al Bikah",
    "wof:placetype":"locality"
},
  "geometry": {"coordinates":[39.81667,20.96667],"type":"Point"}
}