{
  "type": "Feature",
  "properties": {
    "gn:admin1_code":"8",
    "gn:asciiname":"Khurayman",
    "gn:country_code":"SA",
    "gn:dem":704,
    "gn:feature_class":"P",
    "gn:feature_code":"PPL",
    "gn:name":"Khuraym\u0101n",
    "gn:population":0,
    "gn:timezone":"Asia/Riyadh",
    "iso:country":"SA",
    "name:ara_x_preferred":[
        "\u062e\u064f\u0631\u064a\u0645\u0627\u0646"
    ],
    "name:und_x_variant":[
        "Khuraym\u0101n"
    ],
    "wof:name":"Khurayman",
    "wof:placetype":"locality"
},
  "geometry": {"coordinates":[44.14442,25.53331],"type":"Point"}
}