{
  "type": "Feature",
  "properties": {
    "gn:admin1_code":"5",
    "gn:asciiname":"Jada`ah",
    "gn:country_code":"SA",
    "gn:dem":461,
    "gn:feature_class":"P",
    "gn:feature_code":"PPL",
    "gn:name":"Jad\u0101\u2018ah",
    "gn:population":0,
    "gn:timezone":"Asia/Riyadh",
    "iso:country":"SA",
    "name:und_x_variant":[
        "Jad\u0101\u2018ah"
    ],
    "wof:name":"Jada`ah",
    "wof:placetype":"locality"
},
  "geometry": {"coordinates":[38.8175,25.37889],"type":"Point"}
}