{
  "type": "Feature",
  "properties": {
    "gn:admin1_code":"0",
    "gn:asciiname":"Ash Shuqayq",
    "gn:country_code":"SA",
    "gn:dem":1022,
    "gn:feature_class":"P",
    "gn:feature_code":"PPL",
    "gn:name":"Ash Shuqayq",
    "gn:population":0,
    "gn:timezone":"Asia/Riyadh",
    "iso:country":"SA",
    "name:ara_x_preferred":[
        "\u0627\u0644\u0634\u0642\u064a\u0642"
    ],
    "wof:name":"Ash Shuqayq",
    "wof:placetype":"locality"
},
  "geometry": {"coordinates":[40.90493,27.1641],"type":"Point"}
}