{
  "type": "Feature",
  "properties": {
    "gn:admin1_code":"15",
    "gn:asciiname":"At Timyat",
    "gn:country_code":"SA",
    "gn:dem":423,
    "gn:feature_class":"P",
    "gn:feature_code":"PPL",
    "gn:name":"At Timy\u0101\u0163",
    "gn:population":0,
    "gn:timezone":"Asia/Riyadh",
    "iso:country":"SA",
    "name:ara_x_preferred":[
        "At Timy\u0101\u0163"
    ],
    "name:ara_x_variant":[
        "\u0627\u0644\u062a\u0651\u064e\u0645\u064a\u0627\u0637"
    ],
    "wof:name":"At Timyat",
    "wof:placetype":"locality"
},
  "geometry": {"coordinates":[43.1397,29.85758],"type":"Point"}
}