{
  "type": "Feature",
  "properties": {
    "gn:admin1_code":"14.0",
    "gn:asciiname":"Mahadid",
    "gn:country_code":"SA",
    "gn:dem":546,
    "gn:feature_class":"P",
    "gn:feature_code":"PPL",
    "gn:name":"Mah\u0101d\u012bd",
    "gn:population":0,
    "gn:timezone":"Asia/Riyadh",
    "iso:country":"SA",
    "name:und_x_variant":[
        "Mah\u0101d\u012bd"
    ],
    "wof:name":"Mahadid",
    "wof:placetype":"locality"
},
  "geometry": {"coordinates":[40.12118,21.23012],"type":"Point"}
}