{
  "type": "Feature",
  "properties": {
    "gn:admin1_code":"5",
    "gn:asciiname":"Al `Ays",
    "gn:country_code":"SA",
    "gn:dem":625,
    "gn:feature_class":"P",
    "gn:feature_code":"PPL",
    "gn:name":"Al \u2018Ays",
    "gn:population":0,
    "gn:timezone":"Asia/Riyadh",
    "iso:country":"SA",
    "name:ara_x_preferred":[
        "Al \u2018Ays"
    ],
    "wof:name":"Al `Ays",
    "wof:placetype":"locality"
},
  "geometry": {"coordinates":[38.10874,25.06349],"type":"Point"}
}