{
  "type": "Feature",
  "properties": {
    "gn:admin1_code":"14.0",
    "gn:asciiname":"Al Majarish",
    "gn:country_code":"SA",
    "gn:dem":1869,
    "gn:feature_class":"P",
    "gn:feature_code":"PPL",
    "gn:name":"Al Maj\u0101rish",
    "gn:population":0,
    "gn:timezone":"Asia/Riyadh",
    "iso:country":"SA",
    "name:und_x_variant":[
        "Al Maj\u0101rish"
    ],
    "wof:name":"Al Majarish",
    "wof:placetype":"locality"
},
  "geometry": {"coordinates":[40.34944,21.31639],"type":"Point"}
}