{
  "type": "Feature",
  "properties": {
    "iso:country":"SA",
    "name:und_x_variant":[
        "Jabrah"
    ],
    "qs:gn_country":"SA",
    "qs:gn_fcode":"PPLX",
    "qs:gn_pop":0,
    "qs:name":"\u062c\u0628\u0631\u0647",
    "qs:name_adm0":"\u0627\u0644\u0633\u0639\u0648\u062f\u064a\u0629",
    "qs:name_adm1":"\u0627\u0644\u0631\u064a\u0627\u0636",
    "qs:photos":3,
    "qs:photos_1k":1,
    "qs:photos_9k":1,
    "qs:photos_9r":1,
    "qs:photos_all":3,
    "qs:photos_sr":1,
    "qs:placetype":"Suburb",
    "qs:pop_sr":"0",
    "qs:woe_adm0":23424938,
    "wof:name":"\u062c\u0628\u0631\u0647",
    "wof:placetype":"neighbourhood"
},
  "geometry": {"coordinates":[46.71444,24.62111],"type":"Point"}
}