{
  "type": "Feature",
  "properties": {
    "gn:admin1_code":"10",
    "gn:asciiname":"`Ajaj",
    "gn:country_code":"SA",
    "gn:dem":686,
    "gn:feature_class":"P",
    "gn:feature_code":"PPL",
    "gn:name":"\u2018Aj\u0101j",
    "gn:population":0,
    "gn:timezone":"Asia/Riyadh",
    "iso:country":"SA",
    "name:ara_x_preferred":[
        "\u2018Aj\u0101j"
    ],
    "name:ara_x_variant":[
        "\u0639\u062c\u0627\u062c"
    ],
    "name:und_x_variant":[
        "\u2019Ajaj"
    ],
    "wof:name":"`Ajaj",
    "wof:placetype":"locality"
},
  "geometry": {"coordinates":[46.43925,24.16785],"type":"Point"}
}