{
  "type": "Feature",
  "properties": {
    "gn:admin1_code":"0",
    "gn:asciiname":"Sha`bah",
    "gn:country_code":"SA",
    "gn:dem":2121,
    "gn:feature_class":"P",
    "gn:feature_code":"PPL",
    "gn:name":"Sha\u2018bah",
    "gn:population":0,
    "gn:timezone":"Asia/Riyadh",
    "iso:country":"SA",
    "name:und_x_variant":[
        "Sha\u2018bah"
    ],
    "wof:name":"Sha`bah",
    "wof:placetype":"locality"
},
  "geometry": {"coordinates":[43.53333,17.73333],"type":"Point"}
}