{
  "type": "Feature",
  "properties": {
    "gn:admin1_code":"6",
    "gn:asciiname":"Al Lisafah",
    "gn:country_code":"SA",
    "gn:dem":269,
    "gn:feature_class":"P",
    "gn:feature_code":"PPL",
    "gn:name":"Al Li\u015f\u0101fah",
    "gn:population":0,
    "gn:timezone":"Asia/Riyadh",
    "iso:country":"SA",
    "name:ara_x_preferred":[
        "\u0627\u0644\u0644\u0635\u0627\u0641\u0629"
    ],
    "name:und_x_variant":[
        "Al Li\u015f\u0101fah"
    ],
    "wof:name":"Al Lisafah",
    "wof:placetype":"locality"
},
  "geometry": {"coordinates":[46.86444,27.61966],"type":"Point"}
}