{
  "type": "Feature",
  "properties": {
    "gn:admin1_code":"0",
    "gn:asciiname":"Al `Aqiq",
    "gn:country_code":"SA",
    "gn:dem":1395,
    "gn:feature_class":"P",
    "gn:feature_code":"PPL",
    "gn:name":"Al \u2018Aq\u012bq",
    "gn:population":0,
    "gn:timezone":"Asia/Riyadh",
    "iso:country":"SA",
    "name:ara_x_preferred":[
        "Al \u2018Aq\u012bq"
    ],
    "name:und_x_variant":[
        "Aqiq",
        "Umm ad Dam\u0101r"
    ],
    "wof:name":"Al `Aqiq",
    "wof:placetype":"locality"
},
  "geometry": {"coordinates":[41.41667,20.65],"type":"Point"}
}