{
  "type": "Feature",
  "properties": {
    "gn:admin1_code":"0",
    "gn:asciiname":"Ar Rabad",
    "gn:cc2":"SA",
    "gn:country_code":"SA",
    "gn:dem":388,
    "gn:feature_class":"P",
    "gn:feature_code":"PPL",
    "gn:name":"Ar Raba\u1e11",
    "gn:population":0,
    "gn:timezone":"Asia/Riyadh",
    "iso:country":"SA",
    "name:und_x_variant":[
        "Ar Ruba\u1e11",
        "Ar Raba\u1e11"
    ],
    "wof:name":"Ar Rabad",
    "wof:placetype":"locality"
},
  "geometry": {"coordinates":[39.53333,23.18333],"type":"Point"}
}