{
  "type": "Feature",
  "properties": {
    "gn:admin1_code":"14.0",
    "gn:asciiname":"Al Faydah",
    "gn:country_code":"SA",
    "gn:dem":112,
    "gn:feature_class":"P",
    "gn:feature_code":"PPL",
    "gn:name":"Al Fay\u1e11ah",
    "gn:population":0,
    "gn:timezone":"Asia/Riyadh",
    "iso:country":"SA",
    "name:fas_x_preferred":[
        "\u0627\u0644\u0641\u0627\u06cc\u062f\u0647"
    ],
    "name:nno_x_preferred":[
        "Al Faydah"
    ],
    "name:und_x_variant":[
        "Al Fay\u1e11ah"
    ],
    "wof:name":"Al Faydah",
    "wof:placetype":"locality"
},
  "geometry": {"coordinates":[39.38907,21.98047],"type":"Point"}
}