{
  "type": "Feature",
  "properties": {
    "gn:admin1_code":"10.0",
    "gn:asciiname":"Ash Sharikhiyah",
    "gn:country_code":"SA",
    "gn:dem":697,
    "gn:feature_class":"P",
    "gn:feature_code":"PPL",
    "gn:name":"Ash Sh\u0101rikh\u012byah",
    "gn:population":0,
    "gn:timezone":"Asia/Riyadh",
    "iso:country":"SA",
    "name:und_x_variant":[
        "Ash Sh\u0101rikh\u012byah"
    ],
    "wof:name":"Ash Sharikhiyah",
    "wof:placetype":"locality"
},
  "geometry": {"coordinates":[45.6475,25.56889],"type":"Point"}
}