{
  "type": "Feature",
  "properties": {
    "gn:admin1_code":"0",
    "gn:asciiname":"Dammari",
    "gn:cc2":"SA",
    "gn:country_code":"SA",
    "gn:dem":25,
    "gn:feature_class":"P",
    "gn:feature_code":"PPL",
    "gn:name":"Dammari",
    "gn:population":0,
    "gn:timezone":"Asia/Riyadh",
    "iso:country":"SA",
    "name:und_x_variant":[
        "Daumar\u012b",
        "Dammari"
    ],
    "wof:name":"Dammari",
    "wof:placetype":"locality"
},
  "geometry": {"coordinates":[42.58333,17.18333],"type":"Point"}
}