{
  "type": "Feature",
  "properties": {
    "gn:admin1_code":"17",
    "gn:asciiname":"Umm Hasan ar Rajhi",
    "gn:country_code":"SA",
    "gn:dem":44,
    "gn:feature_class":"P",
    "gn:feature_code":"PPL",
    "gn:name":"Umm \u1e28asan ar Raj\u1e29\u012b",
    "gn:population":0,
    "gn:timezone":"Asia/Riyadh",
    "iso:country":"SA",
    "name:und_x_variant":[
        "Umm \u1e28asan ar Raj\u1e29\u012b"
    ],
    "wof:name":"Umm Hasan ar Rajhi",
    "wof:placetype":"locality"
},
  "geometry": {"coordinates":[42.80444,16.87972],"type":"Point"}
}