{
  "type": "Feature",
  "properties": {
    "gn:admin1_code":"0",
    "gn:asciiname":"Shimas",
    "gn:cc2":"SA",
    "gn:country_code":"SA",
    "gn:dem":596,
    "gn:feature_class":"P",
    "gn:feature_code":"PPL",
    "gn:name":"Shim\u0101s",
    "gn:population":0,
    "gn:timezone":"Asia/Riyadh",
    "iso:country":"SA",
    "name:ara_x_preferred":[
        "Shim\u0101s"
    ],
    "name:und_x_variant":[
        "Shamas"
    ],
    "wof:name":"Shimas",
    "wof:placetype":"neighbourhood"
},
  "geometry": {"coordinates":[43.98333,26.35],"type":"Point"}
}