{
  "type": "Feature",
  "properties": {
    "gn:admin1_code":"14.0",
    "gn:asciiname":"Za`faran",
    "gn:country_code":"SA",
    "gn:dem":1470,
    "gn:feature_class":"P",
    "gn:feature_code":"PPL",
    "gn:name":"Za\u2018far\u0101n",
    "gn:population":0,
    "gn:timezone":"Asia/Riyadh",
    "iso:country":"SA",
    "name:und_x_variant":[
        "Za\u2018far\u0101n"
    ],
    "wof:name":"Za`faran",
    "wof:placetype":"locality"
},
  "geometry": {"coordinates":[40.7348,21.22203],"type":"Point"}
}