{
  "type": "Feature",
  "properties": {
    "gn:admin1_code":"6",
    "gn:asciiname":"Al Kahafah",
    "gn:country_code":"SA",
    "gn:dem":76,
    "gn:feature_class":"P",
    "gn:feature_code":"PPL",
    "gn:name":"Al Kahafah",
    "gn:population":0,
    "gn:timezone":"Asia/Riyadh",
    "iso:country":"SA",
    "name:und_x_variant":[
        "Kahafa",
        "Al Kahfah",
        "Al Kahafah"
    ],
    "wof:name":"Al Kahafah",
    "wof:placetype":"locality"
},
  "geometry": {"coordinates":[48.33519,27.37881],"type":"Point"}
}