{
  "type": "Feature",
  "properties": {
    "gn:admin1_code":"20",
    "gn:asciiname":"`Ayn al Hawwasi",
    "gn:country_code":"SA",
    "gn:dem":513,
    "gn:feature_class":"P",
    "gn:feature_code":"PPL",
    "gn:name":"\u2018Ayn al \u1e28aww\u0101s\u012b",
    "gn:population":0,
    "gn:timezone":"Asia/Riyadh",
    "iso:country":"SA",
    "name:und_x_variant":[
        "\u2018Ayn al \u1e28aww\u0101s\u012b"
    ],
    "wof:name":"`Ayn al Hawwasi",
    "wof:placetype":"locality"
},
  "geometry": {"coordinates":[37.58164,31.36361],"type":"Point"}
}