{
  "type": "Feature",
  "properties": {
    "gn:admin1_code":"10",
    "gn:asciiname":"Ash Shukayyirah",
    "gn:country_code":"SA",
    "gn:dem":692,
    "gn:feature_class":"P",
    "gn:feature_code":"PPL",
    "gn:name":"Ash Shukayyirah",
    "gn:population":0,
    "gn:timezone":"Asia/Riyadh",
    "iso:country":"SA",
    "name:ara_x_preferred":[
        "\u0627\u0644\u0634\u0643\u064a\u0631\u0629"
    ],
    "wof:name":"Ash Shukayyirah",
    "wof:placetype":"locality"
},
  "geometry": {"coordinates":[45.26328,25.34117],"type":"Point"}
}