{
  "type": "Feature",
  "properties": {
    "gn:admin1_code":"17.0",
    "gn:asciiname":"Al Asamilah",
    "gn:country_code":"SA",
    "gn:dem":32,
    "gn:feature_class":"P",
    "gn:feature_code":"PPL",
    "gn:name":"Al As\u0101milah",
    "gn:population":0,
    "gn:timezone":"Asia/Riyadh",
    "iso:country":"SA",
    "name:ara_x_preferred":[
        "\u0627\u0644\u0627\u0633\u0627\u0645\u0644\u0629"
    ],
    "name:und_x_variant":[
        "Al As\u0101milah"
    ],
    "wof:name":"Al Asamilah",
    "wof:placetype":"locality"
},
  "geometry": {"coordinates":[42.7575,16.86778],"type":"Point"}
}