{
  "type": "Feature",
  "properties": {
    "gn:admin1_code":"0",
    "gn:asciiname":"Al an Nanisah",
    "gn:country_code":"SA",
    "gn:dem":2313,
    "gn:feature_class":"P",
    "gn:feature_code":"PPL",
    "gn:name":"Al an Nanisah",
    "gn:population":0,
    "gn:timezone":"Asia/Riyadh",
    "iso:country":"SA",
    "wof:name":"Al an Nanisah",
    "wof:placetype":"locality"
},
  "geometry": {"coordinates":[42.94348,18.05937],"type":"Point"}
}