{
  "type": "Feature",
  "properties": {
    "gn:admin1_code":"10",
    "gn:asciiname":"Sudus",
    "gn:country_code":"SA",
    "gn:dem":796,
    "gn:feature_class":"P",
    "gn:feature_code":"PPL",
    "gn:name":"Sud\u016bs",
    "gn:population":0,
    "gn:timezone":"Asia/Riyadh",
    "iso:country":"SA",
    "name:ara_x_preferred":[
        "Sud\u016bs"
    ],
    "name:ara_x_variant":[
        "\u0633\u062f\u0648\u0633"
    ],
    "name:und_x_variant":[
        "Sadus",
        "Sid\u016bs"
    ],
    "wof:name":"Sudus",
    "wof:placetype":"locality"
},
  "geometry": {"coordinates":[46.20788,24.99374],"type":"Point"}
}