{
  "type": "Feature",
  "properties": {
    "gn:admin1_code":"10",
    "gn:asciiname":"Al Khalidiyah",
    "gn:country_code":"SA",
    "gn:dem":666,
    "gn:feature_class":"P",
    "gn:feature_code":"PPL",
    "gn:name":"Al Kh\u0101lid\u012byah",
    "gn:population":0,
    "gn:timezone":"Asia/Riyadh",
    "iso:country":"SA",
    "name:ara_x_preferred":[
        "\u0627\u0644\u062e\u0627\u0644\u062f\u064a\u0629"
    ],
    "name:eng_x_preferred":[
        "Al Khalidiyah"
    ],
    "name:und_x_variant":[
        "Al Kh\u0101lid\u012byah"
    ],
    "wof:name":"Al Khalidiyah",
    "wof:placetype":"locality"
},
  "geometry": {"coordinates":[45.88319,25.69804],"type":"Point"}
}