{
  "type": "Feature",
  "properties": {
    "gn:admin1_code":"6",
    "gn:asciiname":"Al `Uthmaniyah",
    "gn:country_code":"SA",
    "gn:dem":262,
    "gn:feature_class":"P",
    "gn:feature_code":"PPLL",
    "gn:name":"Al \u2018Uthm\u0101n\u012byah",
    "gn:population":0,
    "gn:timezone":"Asia/Riyadh",
    "iso:country":"SA",
    "name:ara_x_preferred":[
        "\u0627\u0644\u0639\u062b\u0645\u0627\u0646\u064a\u0629"
    ],
    "name:und_x_variant":[
        "Ithmaniya",
        "Al \u2018Uthm\u0101n\u012byah"
    ],
    "wof:name":"Al `Uthmaniyah",
    "wof:placetype":"locality"
},
  "geometry": {"coordinates":[49.31683,25.18951],"type":"Point"}
}