{
  "type": "Feature",
  "properties": {
    "gn:admin1_code":"5",
    "gn:asciiname":"Al Hufrah",
    "gn:country_code":"SA",
    "gn:dem":593,
    "gn:feature_class":"P",
    "gn:feature_code":"PPL",
    "gn:name":"Al \u1e28ufrah",
    "gn:population":0,
    "gn:timezone":"Asia/Riyadh",
    "iso:country":"SA",
    "name:und_x_variant":[
        "Al \u1e28ufrah"
    ],
    "wof:name":"Al Hufrah",
    "wof:placetype":"locality"
},
  "geometry": {"coordinates":[39.18306,24.60889],"type":"Point"}
}