{
  "type": "Feature",
  "properties": {
    "gn:admin1_code":"13",
    "gn:asciiname":"Murayfiq",
    "gn:country_code":"SA",
    "gn:dem":1040,
    "gn:feature_class":"P",
    "gn:feature_code":"PPL",
    "gn:name":"Murayfiq",
    "gn:population":0,
    "gn:timezone":"Asia/Riyadh",
    "iso:country":"SA",
    "name:ara_x_preferred":[
        "\u0645\u0631\u064a\u0641\u0642"
    ],
    "wof:name":"Murayfiq",
    "wof:placetype":"locality"
},
  "geometry": {"coordinates":[41.64436,27.36237],"type":"Point"}
}