{
  "type": "Feature",
  "properties": {
    "gn:admin1_code":"11.0",
    "gn:asciiname":"Al Qarn",
    "gn:country_code":"SA",
    "gn:dem":2478,
    "gn:feature_class":"P",
    "gn:feature_code":"PPL",
    "gn:name":"Al Qarn",
    "gn:population":0,
    "gn:timezone":"Asia/Riyadh",
    "iso:country":"SA",
    "name:ara_x_preferred":[
        "\u0627\u0644\u0642\u0631\u0646"
    ],
    "name:nno_x_preferred":[
        "Al Qarn"
    ],
    "wof:name":"Al Qarn",
    "wof:placetype":"locality"
},
  "geometry": {"coordinates":[42.77819,17.98939],"type":"Point"}
}