{
  "type": "Feature",
  "properties": {
    "gn:admin1_code":"6",
    "gn:asciiname":"Umm Tali`",
    "gn:country_code":"SA",
    "gn:dem":147,
    "gn:feature_class":"P",
    "gn:feature_code":"PPL",
    "gn:name":"Umm T\u0101li\u2018",
    "gn:population":0,
    "gn:timezone":"Asia/Riyadh",
    "iso:country":"SA",
    "name:ara_x_preferred":[
        "Umm T\u0101li\u2018"
    ],
    "name:ara_x_variant":[
        "\u0623\u0645 \u062a\u0627\u0644\u0639"
    ],
    "wof:name":"Umm Tali`",
    "wof:placetype":"locality"
},
  "geometry": {"coordinates":[48.86337,25.97532],"type":"Point"}
}