{
  "type": "Feature",
  "properties": {
    "gn:admin1_code":"13",
    "gn:asciiname":"Bada'i` al Makhul",
    "gn:country_code":"SA",
    "gn:dem":927,
    "gn:feature_class":"P",
    "gn:feature_code":"PPL",
    "gn:name":"Bad\u0101\u2019i\u2018 al Mak\u1e29\u016bl",
    "gn:population":0,
    "gn:timezone":"Asia/Riyadh",
    "iso:country":"SA",
    "name:ara_x_preferred":[
        "\u0628\u062f\u0627\u0626\u0639 \u0627\u0644\u0645\u0643\u062d\u0648\u0644"
    ],
    "name:und_x_variant":[
        "Bad\u0101\u2019i\u2018 al Mak\u1e29\u016bl"
    ],
    "wof:name":"Bada'i` al Makhul",
    "wof:placetype":"locality"
},
  "geometry": {"coordinates":[42.56153,26.588],"type":"Point"}
}