{
  "type": "Feature",
  "properties": {
    "gn:admin1_code":"13",
    "gn:asciiname":"Al Mukhtalif",
    "gn:country_code":"SA",
    "gn:dem":1159,
    "gn:feature_class":"P",
    "gn:feature_code":"PPL",
    "gn:name":"Al Mukhtalif",
    "gn:population":0,
    "gn:timezone":"Asia/Riyadh",
    "iso:country":"SA",
    "name:ara_x_preferred":[
        "\u0627\u0644\u0645\u062e\u062a\u0644\u0641"
    ],
    "wof:name":"Al Mukhtalif",
    "wof:placetype":"locality"
},
  "geometry": {"coordinates":[41.20933,27.18491],"type":"Point"}
}