{
  "type": "Feature",
  "properties": {
    "gn:admin1_code":"6",
    "gn:asciiname":"Jarudiyah",
    "gn:cc2":"SA",
    "gn:country_code":"SA",
    "gn:dem":16,
    "gn:feature_class":"P",
    "gn:feature_code":"PPL",
    "gn:name":"Jar\u016bd\u012byah",
    "gn:population":0,
    "gn:timezone":"Asia/Riyadh",
    "iso:country":"SA",
    "name:und_x_variant":[
        "Jurudiya",
        "Jarudiya",
        "Jar\u016bd\u012byah"
    ],
    "wof:name":"Jarudiyah",
    "wof:placetype":"neighbourhood"
},
  "geometry": {"coordinates":[49.98472,26.54139],"type":"Point"}
}