{
  "type": "Feature",
  "properties": {
    "gn:admin1_code":"6",
    "gn:asciiname":"Jarudiyah",
    "gn:cc2":"SA",
    "gn:country_code":"SA",
    "gn:dem":16,
    "gn:feature_class":"P",
    "gn:feature_code":"PPL",
    "gn:name":"Jar\u016bd\u012byah",
    "gn:population":0,
    "gn:timezone":"Asia/Riyadh",
    "iso:country":"SA",
    "name:ara_x_preferred":[
        "\u0627\u0644\u062c\u0627\u0631\u0648\u062f\u064a\u0629"
    ],
    "name:fas_x_preferred":[
        "\u0632\u06cc\u062f\u06cc\u0647 \u062c\u0627\u0631\u0648\u062f\u06cc\u0647"
    ],
    "name:ind_x_preferred":[
        "Jarudiyah"
    ],
    "name:rus_x_preferred":[
        "\u0414\u0436\u0430\u0440\u0443\u0434\u0438\u0442\u044b"
    ],
    "name:und_x_variant":[
        "Jurudiya",
        "Jarudiya",
        "Jar\u016bd\u012byah"
    ],
    "wof:name":"Jarudiyah",
    "wof:placetype":"neighbourhood"
},
  "geometry": {"coordinates":[49.98472,26.54139],"type":"Point"}
}