{
  "type": "Feature",
  "properties": {
    "gn:admin1_code":"5.0",
    "gn:asciiname":"Al Biqa`",
    "gn:country_code":"SA",
    "gn:dem":227,
    "gn:feature_class":"P",
    "gn:feature_code":"PPL",
    "gn:name":"Al Biq\u0101\u2018",
    "gn:population":0,
    "gn:timezone":"Asia/Riyadh",
    "iso:country":"SA",
    "name:ara_x_preferred":[
        "Al Biq\u0101\u2018"
    ],
    "name:ara_x_variant":[
        "\u0627\u0644\u0628\u0642\u0627\u0639"
    ],
    "name:fas_x_preferred":[
        "\u0627\u0644\u0628\u06cc\u063a"
    ],
    "name:nno_x_preferred":[
        "Al Biqa"
    ],
    "name:urd_x_preferred":[
        "\u0627\u0644\u0628\u0642\u0627\u0639"
    ],
    "wof:name":"Al Biqa`",
    "wof:placetype":"locality"
},
  "geometry": {"coordinates":[38.59884,24.38862],"type":"Point"}
}