{
  "type": "Feature",
  "properties": {
    "gn:admin1_code":"0",
    "gn:asciiname":"Ash Shara'i`",
    "gn:country_code":"SA",
    "gn:dem":2300,
    "gn:feature_class":"P",
    "gn:feature_code":"PPL",
    "gn:name":"Ash Shar\u0101\u2019i\u2018",
    "gn:population":0,
    "gn:timezone":"Asia/Riyadh",
    "iso:country":"SA",
    "name:ara_x_preferred":[
        "\u062d\u064a \u0627\u0644\u0634\u0631\u0627\u0626\u0639"
    ],
    "name:nno_x_preferred":[
        "Ash Shara'i`"
    ],
    "name:und_x_variant":[
        "Ash Shar\u0101yi\u2018",
        "Ash Shar\u0101\u2019i\u2018"
    ],
    "name:urd_x_preferred":[
        "\u0627\u0644\u0634\u0631\u0627\u0626\u0639"
    ],
    "wof:name":"Ash Shara'i`",
    "wof:placetype":"locality"
},
  "geometry": {"coordinates":[43.3382,18.02203],"type":"Point"}
}