{
  "type": "Feature",
  "properties": {
    "gn:admin1_code":"17",
    "gn:asciiname":"Adaya",
    "gn:country_code":"SA",
    "gn:dem":28,
    "gn:feature_class":"P",
    "gn:feature_code":"PPL",
    "gn:name":"Adaya",
    "gn:population":0,
    "gn:timezone":"Asia/Riyadh",
    "iso:country":"SA",
    "name:ara_x_preferred":[
        "Al \u2018A\u0163\u0101y\u0101"
    ],
    "wof:name":"Adaya",
    "wof:placetype":"locality"
},
  "geometry": {"coordinates":[42.55013,17.16519],"type":"Point"}
}