{
  "type": "Feature",
  "properties": {
    "gn:admin1_code":"10",
    "gn:asciiname":"Ruwayqah",
    "gn:country_code":"SA",
    "gn:dem":709,
    "gn:feature_class":"P",
    "gn:feature_code":"PPL",
    "gn:name":"Ruwayqah",
    "gn:population":0,
    "gn:timezone":"Asia/Riyadh",
    "iso:country":"SA",
    "name:und_x_variant":[
        "Rawaiqa",
        "Ruwayqah"
    ],
    "wof:name":"Ruwayqah",
    "wof:placetype":"locality"
},
  "geometry": {"coordinates":[46.28333,25.15],"type":"Point"}
}