{
  "type": "Feature",
  "properties": {
    "gn:admin1_code":"13",
    "gn:asciiname":"Al Bir",
    "gn:country_code":"SA",
    "gn:dem":1032,
    "gn:feature_class":"P",
    "gn:feature_code":"PPL",
    "gn:name":"Al B\u012br",
    "gn:population":0,
    "gn:timezone":"Asia/Riyadh",
    "iso:country":"SA",
    "name:ara_x_preferred":[
        "Al B\u012br"
    ],
    "name:ara_x_variant":[
        "\u0627\u0644\u0628\u064a\u0631"
    ],
    "wof:name":"Al Bir",
    "wof:placetype":"locality"
},
  "geometry": {"coordinates":[42.17444,26.91887],"type":"Point"}
}