{
  "type": "Feature",
  "properties": {
    "gn:admin1_code":"14.0",
    "gn:asciiname":"Ad Dihasiyah",
    "gn:country_code":"SA",
    "gn:dem":1484,
    "gn:feature_class":"P",
    "gn:feature_code":"PPL",
    "gn:name":"Ad Dih\u0101s\u012byah",
    "gn:population":0,
    "gn:timezone":"Asia/Riyadh",
    "iso:country":"SA",
    "name:und_x_variant":[
        "Ad Dih\u0101s\u012byah"
    ],
    "wof:name":"Ad Dihasiyah",
    "wof:placetype":"locality"
},
  "geometry": {"coordinates":[40.53294,21.43577],"type":"Point"}
}