{
  "type": "Feature",
  "properties": {
    "gn:admin1_code":"5",
    "gn:asciiname":"Hasa",
    "gn:country_code":"SA",
    "gn:dem":386,
    "gn:feature_class":"P",
    "gn:feature_code":"PPL",
    "gn:name":"Hasa",
    "gn:population":0,
    "gn:timezone":"Asia/Riyadh",
    "iso:country":"SA",
    "name:nno_x_preferred":[
        "Hasa"
    ],
    "name:und_x_variant":[
        "\u1e28as\u0101"
    ],
    "name:urd_x_preferred":[
        "\u062d\u0627\u0633\u0627"
    ],
    "wof:name":"Hasa",
    "wof:placetype":"locality"
},
  "geometry": {"coordinates":[38.58333,24.28333],"type":"Point"}
}