{
  "type": "Feature",
  "properties": {
    "gn:admin1_code":"14.0",
    "gn:asciiname":"Ar Rudaymah",
    "gn:country_code":"SA",
    "gn:dem":216,
    "gn:feature_class":"P",
    "gn:feature_code":"PPL",
    "gn:name":"Ar Rudaymah",
    "gn:population":0,
    "gn:timezone":"Asia/Riyadh",
    "iso:country":"SA",
    "name:nno_x_preferred":[
        "Ar Rudaymah"
    ],
    "wof:name":"Ar Rudaymah",
    "wof:placetype":"locality"
},
  "geometry": {"coordinates":[39.68611,21.76667],"type":"Point"}
}