{
  "type": "Feature",
  "properties": {
    "gn:admin1_code":"17",
    "gn:asciiname":"Ka`lul",
    "gn:country_code":"SA",
    "gn:dem":57,
    "gn:feature_class":"P",
    "gn:feature_code":"PPL",
    "gn:name":"Ka\u2018l\u016bl",
    "gn:population":0,
    "gn:timezone":"Asia/Riyadh",
    "iso:country":"SA",
    "name:nno_x_preferred":[
        "Ka`lul"
    ],
    "name:und_x_variant":[
        "Ka\u2018l\u016bl"
    ],
    "wof:name":"Ka`lul",
    "wof:placetype":"locality"
},
  "geometry": {"coordinates":[42.84672,16.8976],"type":"Point"}
}