{
  "type": "Feature",
  "properties": {
    "iso:country":"SA",
    "name:ara_x_preferred":[
        "\u0627\u0644\u0645\u0635\u0627\u0646\u0639"
    ],
    "name:und_x_variant":[
        "Ma\u015f\u0101ni\u2018"
    ],
    "qs:gn_country":"SA",
    "qs:gn_fcode":"PPLX",
    "qs:gn_pop":0,
    "qs:name":"\u0627\u0644\u0645\u0648\u0646\u0633\u064a\u0647",
    "qs:name_adm0":"\u0627\u0644\u0633\u0639\u0648\u062f\u064a\u0629",
    "qs:name_adm1":"\u0627\u0644\u0631\u064a\u0627\u0636",
    "qs:photos":2,
    "qs:photos_1k":1,
    "qs:photos_9k":1,
    "qs:photos_9r":1,
    "qs:photos_all":2,
    "qs:photos_sr":1,
    "qs:placetype":"Suburb",
    "qs:pop_sr":"0",
    "qs:woe_adm0":23424938,
    "wof:name":"\u0627\u0644\u0645\u0648\u0646\u0633\u064a\u0647",
    "wof:placetype":"neighbourhood"
},
  "geometry": {"coordinates":[46.72035,24.57812],"type":"Point"}
}