{
  "type": "Feature",
  "properties": {
    "gn:admin1_code":"0",
    "gn:asciiname":"Umm `Irq",
    "gn:country_code":"SA",
    "gn:dem":572,
    "gn:feature_class":"P",
    "gn:feature_code":"PPL",
    "gn:name":"Umm \u2018Irq",
    "gn:population":0,
    "gn:timezone":"Asia/Riyadh",
    "iso:country":"SA",
    "name:ara_x_preferred":[
        "Umm \u2018Irq"
    ],
    "wof:name":"Umm `Irq",
    "wof:placetype":"locality"
},
  "geometry": {"coordinates":[41.85,19.38333],"type":"Point"}
}