{
  "type": "Feature",
  "properties": {
    "gn:admin1_code":"10",
    "gn:asciiname":"Al Khufayfah",
    "gn:country_code":"SA",
    "gn:dem":769,
    "gn:feature_class":"P",
    "gn:feature_code":"PPL",
    "gn:name":"Al Khufayfah",
    "gn:population":0,
    "gn:timezone":"Asia/Riyadh",
    "iso:country":"SA",
    "name:und_x_variant":[
        "Khufaifiya",
        "Al Khufayf\u012byah",
        "Al Khufayfah"
    ],
    "wof:name":"Al Khufayfah",
    "wof:placetype":"locality"
},
  "geometry": {"coordinates":[44.71996,24.90663],"type":"Point"}
}