{
  "type": "Feature",
  "properties": {
    "gn:admin1_code":"13",
    "gn:asciiname":"Raynibah",
    "gn:country_code":"SA",
    "gn:dem":1124,
    "gn:feature_class":"P",
    "gn:feature_code":"PPL",
    "gn:name":"Raynibah",
    "gn:population":0,
    "gn:timezone":"Asia/Riyadh",
    "iso:country":"SA",
    "name:ara_x_preferred":[
        "\u0631\u064a\u0646\u0628\u0629"
    ],
    "wof:name":"Raynibah",
    "wof:placetype":"locality"
},
  "geometry": {"coordinates":[41.52084,27.27878],"type":"Point"}
}