{
  "type": "Feature",
  "properties": {
    "gn:admin1_code":"0",
    "gn:asciiname":"Jazirah",
    "gn:country_code":"SA",
    "gn:dem":1551,
    "gn:feature_class":"P",
    "gn:feature_code":"PPL",
    "gn:name":"Jaz\u012brah",
    "gn:population":0,
    "gn:timezone":"Asia/Riyadh",
    "iso:country":"SA",
    "name:und_x_variant":[
        "Jazira",
        "Jaz\u012brah"
    ],
    "wof:name":"Jazirah",
    "wof:placetype":"locality"
},
  "geometry": {"coordinates":[42.98532,19.06385],"type":"Point"}
}