{
  "type": "Feature",
  "properties": {
    "gn:admin1_code":"0",
    "gn:asciiname":"Al `Ushayr",
    "gn:country_code":"SA",
    "gn:dem":2438,
    "gn:feature_class":"P",
    "gn:feature_code":"PPL",
    "gn:name":"Al \u2018Ushayr",
    "gn:population":0,
    "gn:timezone":"Asia/Riyadh",
    "iso:country":"SA",
    "name:und_x_variant":[
        "Al \u2018Ashayr",
        "Al \u2018Ushayr"
    ],
    "wof:name":"Al `Ushayr",
    "wof:placetype":"locality"
},
  "geometry": {"coordinates":[42.05,19.33333],"type":"Point"}
}