{
  "type": "Feature",
  "properties": {
    "gn:admin1_code":"14",
    "gn:asciiname":"Bi'r ad Dibba",
    "gn:country_code":"SA",
    "gn:dem":9,
    "gn:feature_class":"P",
    "gn:feature_code":"PPL",
    "gn:name":"Bi\u2019r ad Dibba",
    "gn:population":0,
    "gn:timezone":"Asia/Riyadh",
    "iso:country":"SA",
    "name:und_x_variant":[
        "Bir El Dibba",
        "Bi\u2019r ad Dibba"
    ],
    "wof:name":"Bi'r ad Dibba",
    "wof:placetype":"locality"
},
  "geometry": {"coordinates":[41.18333,18.98333],"type":"Point"}
}