{
  "type": "Feature",
  "properties": {
    "gn:admin1_code":"8",
    "gn:asciiname":"`Uqlat as Suqur",
    "gn:country_code":"SA",
    "gn:dem":785,
    "gn:feature_class":"P",
    "gn:feature_code":"PPL",
    "gn:name":"\u2018Uqlat a\u015f \u015euq\u016br",
    "gn:population":0,
    "gn:timezone":"Asia/Riyadh",
    "iso:country":"SA",
    "name:ara_x_preferred":[
        "\u0639\u0642\u0644\u0629 \u0627\u0644\u0635\u0651\u064f\u0642\u0648\u0631"
    ],
    "name:und_x_variant":[
        "Aqlat al Suqur",
        "\u2018Uglat a\u015f \u015euq\u016br",
        "\u2018Aqlat a\u015f \u015euq\u016br",
        "\u2018Uqlat al Qu\u015fur",
        "\u2018Uqlat a\u015f \u015euq\u016br"
    ],
    "wof:name":"`Uqlat as Suqur",
    "wof:placetype":"locality"
},
  "geometry": {"coordinates":[42.20119,25.82916],"type":"Point"}
}