{
  "type": "Feature",
  "properties": {
    "gn:admin1_code":"17.0",
    "gn:asciiname":"Al Wahlah",
    "gn:country_code":"SA",
    "gn:dem":7,
    "gn:feature_class":"P",
    "gn:feature_code":"PPL",
    "gn:name":"Al Wa\u1e29lah",
    "gn:population":0,
    "gn:timezone":"Asia/Riyadh",
    "iso:country":"SA",
    "name:und_x_variant":[
        "Al Wa\u1e29lah"
    ],
    "wof:name":"Al Wahlah",
    "wof:placetype":"locality"
},
  "geometry": {"coordinates":[42.71444,16.79194],"type":"Point"}
}