{
  "type": "Feature",
  "properties": {
    "gn:admin1_code":"0",
    "gn:asciiname":"Al Wasitah",
    "gn:country_code":"SA",
    "gn:dem":64,
    "gn:feature_class":"P",
    "gn:feature_code":"PPL",
    "gn:name":"Al W\u0101si\u0163ah",
    "gn:population":0,
    "gn:timezone":"Asia/Riyadh",
    "iso:country":"SA",
    "name:und_x_variant":[
        "Al W\u0101si\u0163ah"
    ],
    "wof:name":"Al Wasitah",
    "wof:placetype":"locality"
},
  "geometry": {"coordinates":[42.76125,17.04272000000001],"type":"Point"}
}