{
  "type": "Feature",
  "properties": {
    "gn:admin1_code":"8",
    "gn:asciiname":"Ash Shibibiyah",
    "gn:country_code":"SA",
    "gn:dem":654,
    "gn:feature_class":"P",
    "gn:feature_code":"PPL",
    "gn:name":"Ash Shib\u012bb\u012byah",
    "gn:population":0,
    "gn:timezone":"Asia/Riyadh",
    "iso:country":"SA",
    "name:ara_x_preferred":[
        "\u0627\u0644\u0634\u0651\u0650\u0628\u064a\u0628\u064a\u0651\u064e\u0629"
    ],
    "name:und_x_variant":[
        "Ash Shab\u012bb\u012bya",
        "Shabibiya",
        "Shab\u012bb\u012byah",
        "Ash Shib\u012bb\u012byah"
    ],
    "wof:name":"Ash Shibibiyah",
    "wof:placetype":"locality"
},
  "geometry": {"coordinates":[43.75871,26.02205],"type":"Point"}
}