{
  "type": "Feature",
  "properties": {
    "gn:admin1_code":"17",
    "gn:asciiname":"Ghawiyah",
    "gn:country_code":"SA",
    "gn:dem":125,
    "gn:feature_class":"P",
    "gn:feature_code":"PPL",
    "gn:name":"Gh\u0101wiyah",
    "gn:population":0,
    "gn:timezone":"Asia/Riyadh",
    "iso:country":"SA",
    "name:und_x_variant":[
        "Ghawiya",
        "Gh\u0101wiyah"
    ],
    "wof:name":"Ghawiyah",
    "wof:placetype":"locality"
},
  "geometry": {"coordinates":[43.11096,16.56506],"type":"Point"}
}