{
  "type": "Feature",
  "properties": {
    "gn:admin1_code":"0",
    "gn:asciiname":"Sahra'",
    "gn:country_code":"SA",
    "gn:dem":2339,
    "gn:feature_class":"P",
    "gn:feature_code":"PPL",
    "gn:name":"\u015ea\u1e29r\u0101\u2019",
    "gn:population":0,
    "gn:timezone":"Asia/Riyadh",
    "iso:country":"SA",
    "name:und_x_variant":[
        "\u015ea\u1e29r\u0101\u2019"
    ],
    "wof:name":"Sahra'",
    "wof:placetype":"locality"
},
  "geometry": {"coordinates":[42.47138,18.26065],"type":"Point"}
}