{
  "type": "Feature",
  "properties": {
    "gn:admin1_code":"14.0",
    "gn:asciiname":"`Arafat",
    "gn:country_code":"SA",
    "gn:dem":310,
    "gn:feature_class":"P",
    "gn:feature_code":"PPL",
    "gn:name":"\u2018Araf\u0101t",
    "gn:population":0,
    "gn:timezone":"Asia/Riyadh",
    "iso:country":"SA",
    "name:und_x_variant":[
        "\u2018Araf\u0101t"
    ],
    "wof:name":"`Arafat",
    "wof:placetype":"neighbourhood"
},
  "geometry": {"coordinates":[39.94526,21.36361],"type":"Point"}
}