{
  "type": "Feature",
  "properties": {
    "gn:admin1_code":"0",
    "gn:asciiname":"Ya`ud",
    "gn:country_code":"SA",
    "gn:dem":2289,
    "gn:feature_class":"P",
    "gn:feature_code":"PPL",
    "gn:name":"Ya\u2018u\u1e11",
    "gn:population":0,
    "gn:timezone":"Asia/Riyadh",
    "iso:country":"SA",
    "name:und_x_variant":[
        "Ya\u2018udh",
        "Ya\u2018u\u1e11"
    ],
    "wof:name":"Ya`ud",
    "wof:placetype":"locality"
},
  "geometry": {"coordinates":[43.35,17.98333],"type":"Point"}
}