{
  "type": "Feature",
  "properties": {
    "gn:admin1_code":"10",
    "gn:asciiname":"Al `Idwah",
    "gn:country_code":"SA",
    "gn:dem":687,
    "gn:feature_class":"P",
    "gn:feature_code":"PPL",
    "gn:name":"Al \u2018Idwah",
    "gn:population":0,
    "gn:timezone":"Asia/Riyadh",
    "iso:country":"SA",
    "name:ara_x_preferred":[
        "\u0627\u0644\u0639\u062f\u0648\u0629"
    ],
    "name:und_x_variant":[
        "Al \u2018Idwah"
    ],
    "wof:name":"Al `Idwah",
    "wof:placetype":"locality"
},
  "geometry": {"coordinates":[45.92862,24.23835],"type":"Point"}
}