{
  "type": "Feature",
  "properties": {
    "gn:admin1_code":"10",
    "gn:asciiname":"Bin Shefefani",
    "gn:country_code":"SA",
    "gn:dem":765,
    "gn:feature_class":"P",
    "gn:feature_code":"PPL",
    "gn:name":"Bin Shefefani",
    "gn:population":0,
    "gn:timezone":"Asia/Riyadh",
    "iso:country":"SA",
    "name:und_x_variant":[
        "Ben Shefefani",
        "Bin Shefefani"
    ],
    "wof:name":"Bin Shefefani",
    "wof:placetype":"locality"
},
  "geometry": {"coordinates":[45.43333,23.56667],"type":"Point"}
}