{
  "type": "Feature",
  "properties": {
    "gn:admin1_code":"14",
    "gn:asciiname":"Manjamah",
    "gn:country_code":"SA",
    "gn:dem":34,
    "gn:feature_class":"P",
    "gn:feature_code":"PPL",
    "gn:name":"Manjamah",
    "gn:population":0,
    "gn:timezone":"Asia/Riyadh",
    "iso:country":"SA",
    "name:und_x_variant":[
        "Munjiye",
        "Mumjiye",
        "Manjamah"
    ],
    "wof:name":"Manjamah",
    "wof:placetype":"locality"
},
  "geometry": {"coordinates":[41.36639,18.74083],"type":"Point"}
}