{
  "type": "Feature",
  "properties": {
    "gn:admin1_code":"17.0",
    "gn:asciiname":"`Antutah",
    "gn:country_code":"SA",
    "gn:dem":59,
    "gn:feature_class":"P",
    "gn:feature_code":"PPL",
    "gn:name":"\u2018An\u0163\u016b\u0163ah",
    "gn:population":0,
    "gn:timezone":"Asia/Riyadh",
    "iso:country":"SA",
    "name:und_x_variant":[
        "\u2018An\u0163\u016b\u0163ah"
    ],
    "wof:name":"`Antutah",
    "wof:placetype":"locality"
},
  "geometry": {"coordinates":[42.94306,16.53444],"type":"Point"}
}