{
  "type": "Feature",
  "properties": {
    "gn:admin1_code":"6",
    "gn:asciiname":"Ma`aqla",
    "gn:country_code":"SA",
    "gn:dem":421,
    "gn:feature_class":"P",
    "gn:feature_code":"PPL",
    "gn:name":"Ma\u2018aql\u0101",
    "gn:population":0,
    "gn:timezone":"Asia/Riyadh",
    "iso:country":"SA",
    "name:ara_x_preferred":[
        "\u0645\u0639\u0642\u0644\u0627"
    ],
    "name:ara_x_variant":[
        "\u0627\u0644\u0634\u0645\u0644\u0648\u0644"
    ],
    "name:und_x_variant":[
        "Umm \u2018Aql\u0101",
        "Ma\u2018aqala",
        "Ash Shuml\u016bl",
        "Ma\u2018aql\u0101",
        "Ma\u2018aqalah",
        "Ma\u2018qal\u0101",
        "Ash Shaml\u016bl"
    ],
    "wof:name":"Ma`aqla",
    "wof:placetype":"locality"
},
  "geometry": {"coordinates":[47.33385,26.51818],"type":"Point"}
}