{
  "type": "Feature",
  "properties": {
    "gn:admin1_code":"0",
    "gn:asciiname":"Al Ashram",
    "gn:country_code":"SA",
    "gn:dem":2138,
    "gn:feature_class":"P",
    "gn:feature_code":"PPL",
    "gn:name":"Al Ashram",
    "gn:population":0,
    "gn:timezone":"Asia/Riyadh",
    "iso:country":"SA",
    "name:und_x_variant":[
        "Lashram",
        "Al Ashram"
    ],
    "wof:name":"Al Ashram",
    "wof:placetype":"neighbourhood"
},
  "geometry": {"coordinates":[42.57362,18.26268],"type":"Point"}
}