{
  "type": "Feature",
  "properties": {
    "gn:admin1_code":"11.0",
    "gn:asciiname":"Al Wadiyayn",
    "gn:country_code":"SA",
    "gn:dem":2244,
    "gn:feature_class":"P",
    "gn:feature_code":"PPL",
    "gn:name":"Al W\u0101diyayn",
    "gn:population":0,
    "gn:timezone":"Asia/Riyadh",
    "iso:country":"SA",
    "name:ara_x_preferred":[
        "\u0627\u0644\u0648\u0627\u062f\u064a\u064a\u0646"
    ],
    "name:und_x_variant":[
        "Al W\u0101diyayn"
    ],
    "wof:name":"Al Wadiyayn",
    "wof:placetype":"locality"
},
  "geometry": {"coordinates":[42.80254,18.08557],"type":"Point"}
}