{
  "type": "Feature",
  "properties": {
    "gn:admin1_code":"0",
    "gn:asciiname":"Al Khurmah",
    "gn:country_code":"SA",
    "gn:dem":1025,
    "gn:feature_class":"P",
    "gn:feature_code":"PPL",
    "gn:name":"Al Khurmah",
    "gn:population":0,
    "gn:timezone":"Asia/Riyadh",
    "iso:country":"SA",
    "name:und_x_variant":[
        "Khurmah",
        "Khurma",
        "Al Khurmah"
    ],
    "wof:name":"Al Khurmah",
    "wof:placetype":"locality"
},
  "geometry": {"coordinates":[42.03092,21.91149],"type":"Point"}
}