{
  "type": "Feature",
  "properties": {
    "gn:admin1_code":"6",
    "gn:asciiname":"Ra's al Khafji",
    "gn:country_code":"SA",
    "gn:dem":11,
    "gn:feature_class":"P",
    "gn:feature_code":"PPL",
    "gn:name":"Ra\u2019s al Khafj\u012b",
    "gn:population":0,
    "gn:timezone":"Asia/Riyadh",
    "iso:country":"SA",
    "name:ara_x_preferred":[
        "\u0631\u0623\u0633 \u0627\u0644\u062e\u0641\u062c\u064a"
    ],
    "name:ara_x_variant":[
        "\u0627\u0644\u062e\u0641\u062c\u064a"
    ],
    "name:arz_x_preferred":[
        "\u0627\u0644\u062e\u0641\u062c\u0649"
    ],
    "name:bul_x_preferred":[
        "\u0425\u0430\u0444\u0434\u0436\u0438"
    ],
    "name:ceb_x_preferred":[
        "Ra's al Khafj\u012b"
    ],
    "name:ces_x_preferred":[
        "Chafd\u017e\u00ed"
    ],
    "name:dan_x_preferred":[
        "Khafji"
    ],
    "name:fas_x_preferred":[
        "\u0627\u0644\u062e\u0641\u062c\u06cc"
    ],
    "name:fra_x_preferred":[
        "Ras al-Khafji"
    ],
    "name:ind_x_preferred":[
        "Khafji"
    ],
    "name:ita_x_preferred":[
        "Khafji"
    ],
    "name:jpn_x_preferred":[
        "\u30ab\u30d5\u30b8"
    ],
    "name:kor_x_preferred":[
        "\uce74\ud504\uc9c0"
    ],
    "name:mal_x_preferred":[
        "\u0d16\u0d2b\u0d4d\u0d1c\u0d3f"
    ],
    "name:mzn_x_preferred":[
        "\u0627\u0644\u062e\u0641\u062c\u06cc"
    ],
    "name:nno_x_preferred":[
        "Khafji"
    ],
    "name:nor_x_preferred":[
        "Khafji"
    ],
    "name:pol_x_preferred":[
        "Al-Chafd\u017ci"
    ],
    "name:por_x_preferred":[
        "Khafji"
    ],
    "name:rus_x_preferred":[
        "\u0420\u0430\u0441-\u044d\u043b\u044c-\u0425\u0430\u0444\u0434\u0436\u0438"
    ],
    "name:spa_x_preferred":[
        "Khafji"
    ],
    "name:swe_x_preferred":[
        "Khafji"
    ],
    "name:tgl_x_preferred":[
        "Khafji"
    ],
    "name:tur_x_preferred":[
        "Hafci"
    ],
    "name:und_x_variant":[
        "Ra\u2019s al Khafj\u012b"
    ],
    "name:urd_x_preferred":[
        "\u062e\u0641\u062c\u06cc"
    ],
    "wof:name":"Ra's al Khafji",
    "wof:placetype":"locality"
},
  "geometry": {"coordinates":[48.50906,28.42371],"type":"Point"}
}