{
  "type": "Feature",
  "properties": {
    "gn:admin1_code":"6",
    "gn:asciiname":"Ra's al Khafji",
    "gn:country_code":"SA",
    "gn:dem":11,
    "gn:feature_class":"P",
    "gn:feature_code":"PPL",
    "gn:name":"Ra\u2019s al Khafj\u012b",
    "gn:population":0,
    "gn:timezone":"Asia/Riyadh",
    "iso:country":"SA",
    "name:und_x_variant":[
        "Khafji",
        "Ra\u2019s al Khafj\u012b"
    ],
    "wof:name":"Ra's al Khafji",
    "wof:placetype":"locality"
},
  "geometry": {"coordinates":[48.50906,28.42371],"type":"Point"}
}