{
  "type": "Feature",
  "properties": {
    "gn:admin1_code":"10",
    "gn:asciiname":"Hazmiyah",
    "gn:country_code":"SA",
    "gn:dem":993,
    "gn:feature_class":"P",
    "gn:feature_code":"PPL",
    "gn:name":"Hazm\u012byah",
    "gn:population":0,
    "gn:timezone":"Asia/Riyadh",
    "iso:country":"SA",
    "name:und_x_variant":[
        "Hazm\u012byah"
    ],
    "wof:name":"Hazmiyah",
    "wof:placetype":"locality"
},
  "geometry": {"coordinates":[43.51167,24.63694],"type":"Point"}
}