{
  "type": "Feature",
  "properties": {
    "gn:admin1_code":"14.0",
    "gn:asciiname":"Al Khulasah",
    "gn:country_code":"SA",
    "gn:dem":358,
    "gn:feature_class":"P",
    "gn:feature_code":"PPL",
    "gn:name":"Al Khul\u0101\u015fah",
    "gn:population":0,
    "gn:timezone":"Asia/Riyadh",
    "iso:country":"SA",
    "name:und_x_variant":[
        "Al Khul\u0101\u015fah"
    ],
    "wof:name":"Al Khulasah",
    "wof:placetype":"locality"
},
  "geometry": {"coordinates":[39.919,21.69499],"type":"Point"}
}