{
  "type": "Feature",
  "properties": {
    "gn:admin1_code":"0",
    "gn:asciiname":"Al Mustajiddah",
    "gn:country_code":"SA",
    "gn:dem":1019,
    "gn:feature_class":"P",
    "gn:feature_code":"PPL",
    "gn:name":"Al Mustajiddah",
    "gn:population":0,
    "gn:timezone":"Asia/Riyadh",
    "iso:country":"SA",
    "name:und_x_variant":[
        "Mustagidda",
        "Mustajidda",
        "Mustajiddah",
        "Al Mustajiddah"
    ],
    "wof:name":"Al Mustajiddah",
    "wof:placetype":"locality"
},
  "geometry": {"coordinates":[41.53987,26.66606],"type":"Point"}
}