{
  "type": "Feature",
  "properties": {
    "gn:admin1_code":"17",
    "gn:asciiname":"Abu ar Radif",
    "gn:country_code":"SA",
    "gn:dem":150,
    "gn:feature_class":"P",
    "gn:feature_code":"PPL",
    "gn:name":"Ab\u016b ar Rad\u012bf",
    "gn:population":0,
    "gn:timezone":"Asia/Riyadh",
    "iso:country":"SA",
    "name:ara_x_preferred":[
        "\u0623\u0628\u0648 \u0627\u0644\u0631\u062f\u064a\u0641"
    ],
    "name:und_x_variant":[
        "Ab\u016b ar Rad\u012bf",
        "Ab\u016b Rad\u012bf"
    ],
    "wof:name":"Abu ar Radif",
    "wof:placetype":"locality"
},
  "geometry": {"coordinates":[43.1312,16.61855],"type":"Point"}
}