{
  "type": "Feature",
  "properties": {
    "gn:admin1_code":"14.0",
    "gn:asciiname":"Faydat al Mislah",
    "gn:country_code":"SA",
    "gn:dem":919,
    "gn:feature_class":"P",
    "gn:feature_code":"PPL",
    "gn:name":"Fay\u1e11at al Misla\u1e29",
    "gn:population":0,
    "gn:timezone":"Asia/Riyadh",
    "iso:country":"SA",
    "name:und_x_variant":[
        "Fay\u1e11at al Misla\u1e29"
    ],
    "wof:name":"Faydat al Mislah",
    "wof:placetype":"locality"
},
  "geometry": {"coordinates":[40.76694000000001,22.5025],"type":"Point"}
}