{
  "type": "Feature",
  "properties": {
    "gn:admin1_code":"10",
    "gn:asciiname":"Ghasibah",
    "gn:country_code":"SA",
    "gn:dem":540,
    "gn:feature_class":"P",
    "gn:feature_code":"PPL",
    "gn:name":"Gha\u015f\u012bbah",
    "gn:population":0,
    "gn:timezone":"Asia/Riyadh",
    "iso:country":"SA",
    "name:und_x_variant":[
        "Gha\u1e63\u012bba",
        "Gha\u015f\u012bbah"
    ],
    "wof:name":"Ghasibah",
    "wof:placetype":"locality"
},
  "geometry": {"coordinates":[46.71654,22.27312],"type":"Point"}
}