{
  "type": "Feature",
  "properties": {
    "gn:admin1_code":"8",
    "gn:asciiname":"Qusur Mayy",
    "gn:country_code":"SA",
    "gn:dem":599,
    "gn:feature_class":"P",
    "gn:feature_code":"PPL",
    "gn:name":"Qu\u015f\u016br Mayy",
    "gn:population":0,
    "gn:timezone":"Asia/Riyadh",
    "iso:country":"SA",
    "name:und_x_variant":[
        "Qusur Mai",
        "Qu\u015f\u016br Mayy"
    ],
    "wof:name":"Qusur Mayy",
    "wof:placetype":"locality"
},
  "geometry": {"coordinates":[44.15,26.05],"type":"Point"}
}