{
  "type": "Feature",
  "properties": {
    "iso:country":"SA",
    "name:ara_x_preferred":[
        "\u062f\u0631\u0647 \u0627\u0644\u0639\u0631\u0648\u0633"
    ],
    "name:eng_x_preferred":[
        "Durrat Al Arous"
    ],
    "qs:gn_pop":0,
    "qs:name":"\u062f\u0631\u0647 \u0627\u0644\u0639\u0631\u0648\u0633",
    "qs:name_adm0":"\u0627\u0644\u0633\u0639\u0648\u062f\u064a\u0629",
    "qs:name_adm1":"\u0645\u0643\u0629",
    "qs:photos":59,
    "qs:photos_1k":12,
    "qs:photos_9k":1,
    "qs:photos_9r":2,
    "qs:photos_all":59,
    "qs:photos_sr":2,
    "qs:placetype":"Town",
    "qs:pop_sr":"0",
    "qs:woe_adm0":23424938,
    "wof:name":"Durrat Al Arous",
    "wof:placetype":"locality"
},
  "geometry": {"coordinates":[38.952476,21.935641],"type":"Point"}
}