{
  "type": "Feature",
  "properties": {
    "gn:admin1_code":"0",
    "gn:asciiname":"Ar Ruwanah",
    "gn:country_code":"SA",
    "gn:dem":2051,
    "gn:feature_class":"P",
    "gn:feature_code":"PPL",
    "gn:name":"Ar Ruwanah",
    "gn:population":0,
    "gn:timezone":"Asia/Riyadh",
    "iso:country":"SA",
    "name:und_x_variant":[
        "Ar Rownah",
        "Ar Ruwanah"
    ],
    "wof:name":"Ar Ruwanah",
    "wof:placetype":"locality"
},
  "geometry": {"coordinates":[42.80606,18.21984],"type":"Point"}
}