{
  "type": "Feature",
  "properties": {
    "gn:admin1_code":"14",
    "gn:asciiname":"Rakah",
    "gn:country_code":"SA",
    "gn:dem":7,
    "gn:feature_class":"P",
    "gn:feature_code":"PPL",
    "gn:name":"R\u0101kah",
    "gn:population":0,
    "gn:timezone":"Asia/Riyadh",
    "iso:country":"SA",
    "name:und_x_variant":[
        "Raka",
        "R\u0101kah"
    ],
    "wof:name":"Rakah",
    "wof:placetype":"locality"
},
  "geometry": {"coordinates":[40.43333,20.03333],"type":"Point"}
}