{
  "type": "Feature",
  "properties": {
    "gn:admin1_code":"10",
    "gn:asciiname":"Al Hinnah",
    "gn:country_code":"SA",
    "gn:dem":862,
    "gn:feature_class":"P",
    "gn:feature_code":"PPL",
    "gn:name":"Al \u1e28innah",
    "gn:population":0,
    "gn:timezone":"Asia/Riyadh",
    "iso:country":"SA",
    "name:und_x_variant":[
        "Al \u1e28innah"
    ],
    "wof:name":"Al Hinnah",
    "wof:placetype":"locality"
},
  "geometry": {"coordinates":[43.90444,24.49056],"type":"Point"}
}