{
  "type": "Feature",
  "properties": {
    "gn:admin1_code":"13",
    "gn:asciiname":"As Sulubiyah",
    "gn:country_code":"SA",
    "gn:dem":1080,
    "gn:feature_class":"P",
    "gn:feature_code":"PPL",
    "gn:name":"A\u015f \u015eulub\u012byah",
    "gn:population":0,
    "gn:timezone":"Asia/Riyadh",
    "iso:country":"SA",
    "name:ara_x_preferred":[
        "\u0627\u0644\u0635\u0644\u0628\u064a\u0629"
    ],
    "name:und_x_variant":[
        "A\u015f \u015eulub\u012byah"
    ],
    "wof:name":"As Sulubiyah",
    "wof:placetype":"locality"
},
  "geometry": {"coordinates":[42.07716,26.80013],"type":"Point"}
}