{
  "type": "Feature",
  "properties": {
    "gn:admin1_code":"8",
    "gn:asciiname":"Al Mushash",
    "gn:country_code":"SA",
    "gn:dem":790,
    "gn:feature_class":"P",
    "gn:feature_code":"PPL",
    "gn:name":"Al Mush\u0101sh",
    "gn:population":0,
    "gn:timezone":"Asia/Riyadh",
    "iso:country":"SA",
    "name:ara_x_preferred":[
        "Al Mush\u0101sh"
    ],
    "name:und_x_variant":[
        "Al Mish\u0101sh"
    ],
    "wof:name":"Al Mushash",
    "wof:placetype":"locality"
},
  "geometry": {"coordinates":[42.56667,25.38333],"type":"Point"}
}