{
  "type": "Feature",
  "properties": {
    "gn:admin1_code":"14.0",
    "gn:asciiname":"Al Uqlah",
    "gn:country_code":"SA",
    "gn:dem":183,
    "gn:feature_class":"P",
    "gn:feature_code":"PPL",
    "gn:name":"Al Uqlah",
    "gn:population":0,
    "gn:timezone":"Asia/Riyadh",
    "iso:country":"SA",
    "wof:name":"Al Uqlah",
    "wof:placetype":"locality"
},
  "geometry": {"coordinates":[39.46389,22.82961],"type":"Point"}
}