{
  "type": "Feature",
  "properties": {
    "gn:admin1_code":"8",
    "gn:asciiname":"Duhayma'",
    "gn:country_code":"SA",
    "gn:dem":771,
    "gn:feature_class":"P",
    "gn:feature_code":"PPL",
    "gn:name":"Duhaym\u0101\u2019",
    "gn:population":0,
    "gn:timezone":"Asia/Riyadh",
    "iso:country":"SA",
    "name:ara_x_preferred":[
        "\u062f\u064f\u0647\u064e\u064a\u0645\u0627\u0621"
    ],
    "name:und_x_variant":[
        "Duhaym\u0101\u2019"
    ],
    "wof:name":"Duhayma'",
    "wof:placetype":"locality"
},
  "geometry": {"coordinates":[43.83698,25.52837],"type":"Point"}
}