{
  "type": "Feature",
  "properties": {
    "gn:admin1_code":"8",
    "gn:asciiname":"Al Qaw`i",
    "gn:country_code":"SA",
    "gn:dem":696,
    "gn:feature_class":"P",
    "gn:feature_code":"PPL",
    "gn:name":"Al Qaw\u2018\u012b",
    "gn:population":0,
    "gn:timezone":"Asia/Riyadh",
    "iso:country":"SA",
    "name:ara_x_preferred":[
        "\u0627\u0644\u0642\u0648\u0639\u064a"
    ],
    "name:und_x_variant":[
        "Al Qaw\u2018\u012b"
    ],
    "wof:name":"Al Qaw`i",
    "wof:placetype":"locality"
},
  "geometry": {"coordinates":[43.36089000000001,25.77336],"type":"Point"}
}