{
  "type": "Feature",
  "properties": {
    "gn:admin1_code":"6",
    "gn:asciiname":"Al Waziyah",
    "gn:country_code":"SA",
    "gn:dem":145,
    "gn:feature_class":"P",
    "gn:feature_code":"PPL",
    "gn:name":"Al Waz\u012byah",
    "gn:population":0,
    "gn:timezone":"Asia/Riyadh",
    "iso:country":"SA",
    "name:ara_x_preferred":[
        "\u0627\u0644\u0648\u0632\u064a\u0629"
    ],
    "name:und_x_variant":[
        "Al Waz\u012byah"
    ],
    "wof:name":"Al Waziyah",
    "wof:placetype":"locality"
},
  "geometry": {"coordinates":[49.54781,25.50321],"type":"Point"}
}