{
  "type": "Feature",
  "properties": {
    "gn:admin1_code":"20",
    "gn:asciiname":"Al Faysaliyah",
    "gn:country_code":"SA",
    "gn:dem":573,
    "gn:feature_class":"P",
    "gn:feature_code":"PPL",
    "gn:name":"Al Fay\u015fal\u012byah",
    "gn:population":0,
    "gn:timezone":"Asia/Riyadh",
    "iso:country":"SA",
    "name:ara_x_preferred":[
        "\u0627\u0644\u0641\u064a\u0635\u0644\u064a\u0629"
    ],
    "name:eng_x_preferred":[
        "Al Faysaliyah"
    ],
    "name:und_x_variant":[
        "Al Fay\u015fal\u012byah"
    ],
    "wof:name":"Al Faysaliyah",
    "wof:placetype":"locality"
},
  "geometry": {"coordinates":[40.20244,29.94102],"type":"Point"}
}