{
  "type": "Feature",
  "properties": {
    "gn:admin1_code":"10",
    "gn:asciiname":"As Sayhad",
    "gn:country_code":"SA",
    "gn:dem":703,
    "gn:feature_class":"P",
    "gn:feature_code":"PPL",
    "gn:name":"A\u015f \u015eayhad",
    "gn:population":0,
    "gn:timezone":"Asia/Riyadh",
    "iso:country":"SA",
    "name:ara_x_preferred":[
        "\u0627\u0644\u0635\u064a\u0647\u062f"
    ],
    "name:und_x_variant":[
        "A\u015f \u015eayhad"
    ],
    "wof:name":"As Sayhad",
    "wof:placetype":"locality"
},
  "geometry": {"coordinates":[45.79878,24.48742],"type":"Point"}
}