{
  "type": "Feature",
  "properties": {
    "gn:admin1_code":"14",
    "gn:asciiname":"Umm as Salam",
    "gn:country_code":"SA",
    "gn:dem":140,
    "gn:feature_class":"P",
    "gn:feature_code":"PPL",
    "gn:name":"Umm as Sal\u0101m",
    "gn:population":0,
    "gn:timezone":"Asia/Riyadh",
    "iso:country":"SA",
    "name:und_x_variant":[
        "Umm Salam",
        "Umm el Salam",
        "Umm as Sal\u0101m"
    ],
    "wof:name":"Umm as Salam",
    "wof:placetype":"neighbourhood"
},
  "geometry": {"coordinates":[39.39124,21.44886],"type":"Point"}
}