{
  "type": "Feature",
  "properties": {
    "gn:admin1_code":"14",
    "gn:asciiname":"Dabyah",
    "gn:cc2":"SA",
    "gn:country_code":"SA",
    "gn:dem":155,
    "gn:feature_class":"P",
    "gn:feature_code":"PPL",
    "gn:name":"\u1e10abyah",
    "gn:population":0,
    "gn:timezone":"Asia/Riyadh",
    "iso:country":"SA",
    "name:nno_x_preferred":[
        "Dabyah"
    ],
    "name:und_x_variant":[
        "A\u1e11 \u1e10ubayyah",
        "Z\u0327abyah",
        "\u1e10abyah"
    ],
    "wof:name":"Dabyah",
    "wof:placetype":"locality"
},
  "geometry": {"coordinates":[39.44611,22.42472],"type":"Point"}
}