{
  "type": "Feature",
  "properties": {
    "gn:admin1_code":"6",
    "gn:asciiname":"`Ayn Dar al Qadimah",
    "gn:country_code":"SA",
    "gn:dem":146,
    "gn:feature_class":"P",
    "gn:feature_code":"PPL",
    "gn:name":"\u2018Ayn D\u0101r al Qad\u012bmah",
    "gn:population":0,
    "gn:timezone":"Asia/Riyadh",
    "iso:country":"SA",
    "name:ara_x_preferred":[
        "\u0639\u064a\u0646 \u062f\u0627\u0631 \u0627\u0644\u0642\u062f\u064a\u0645\u0629"
    ],
    "name:und_x_variant":[
        "\u2018Ayn D\u0101r al Qad\u012bmah"
    ],
    "wof:name":"`Ayn Dar al Qadimah",
    "wof:placetype":"locality"
},
  "geometry": {"coordinates":[49.38947,25.98915],"type":"Point"}
}