{
  "type": "Feature",
  "properties": {
    "gn:admin1_code":"10",
    "gn:asciiname":"Al Khafaq al Jadid",
    "gn:country_code":"SA",
    "gn:dem":710,
    "gn:feature_class":"P",
    "gn:feature_code":"PPL",
    "gn:name":"Al Khafaq al Jad\u012bd",
    "gn:population":0,
    "gn:timezone":"Asia/Riyadh",
    "iso:country":"SA",
    "name:ara_x_preferred":[
        "\u0627\u0644\u062e\u0641\u0642 \u0627\u0644\u062c\u062f\u064a\u062f"
    ],
    "name:und_x_variant":[
        "Al Khafaq al Jad\u012bd"
    ],
    "wof:name":"Al Khafaq al Jadid",
    "wof:placetype":"locality"
},
  "geometry": {"coordinates":[45.71186,24.42376],"type":"Point"}
}