{
  "type": "Feature",
  "properties": {
    "gn:admin1_code":"5",
    "gn:asciiname":"Abu Dhiba",
    "gn:country_code":"SA",
    "gn:dem":401,
    "gn:feature_class":"P",
    "gn:feature_code":"PPL",
    "gn:name":"Abu Dhiba",
    "gn:population":0,
    "gn:timezone":"Asia/Riyadh",
    "iso:country":"SA",
    "name:ara_x_preferred":[
        "Ab\u016b \u1e10ib\u0101\u2018"
    ],
    "name:ara_x_variant":[
        "\u0623\u0628\u0648 \u0636\u0628\u0627\u0639"
    ],
    "name:fas_x_preferred":[
        "\u0627\u0628\u0648 \u062f\u0647\u06cc\u0628\u0627"
    ],
    "name:nno_x_preferred":[
        "Abu Dhiba"
    ],
    "name:und_x_variant":[
        "Ab\u016b \u1e10ub\u0101\u2018",
        "Abu Dhiba",
        "Ab\u016b \u1e10ih\u0101\u2018"
    ],
    "name:urd_x_preferred":[
        "\u0627\u0628\u0648 \u0636\u0628\u0627"
    ],
    "wof:name":"Abu Dhiba",
    "wof:placetype":"locality"
},
  "geometry": {"coordinates":[39.55367,23.19887],"type":"Point"}
}