{
  "type": "Feature",
  "properties": {
    "gn:admin1_code":"0",
    "gn:asciiname":"Sahl Sha`irah",
    "gn:country_code":"SA",
    "gn:dem":7,
    "gn:feature_class":"P",
    "gn:feature_code":"PPL",
    "gn:name":"Sahl Sha\u2018\u012brah",
    "gn:population":0,
    "gn:timezone":"Asia/Riyadh",
    "iso:country":"SA",
    "name:und_x_variant":[
        "Sahl Sha\u2018\u012brah"
    ],
    "wof:name":"Sahl Sha`irah",
    "wof:placetype":"locality"
},
  "geometry": {"coordinates":[40.96667,19.43333],"type":"Point"}
}