{
  "type": "Feature",
  "properties": {
    "gn:admin1_code":"8",
    "gn:asciiname":"Al Ghammas",
    "gn:country_code":"SA",
    "gn:dem":633,
    "gn:feature_class":"P",
    "gn:feature_code":"PPL",
    "gn:name":"Al Ghamm\u0101s",
    "gn:population":0,
    "gn:timezone":"Asia/Riyadh",
    "iso:country":"SA",
    "name:ara_x_preferred":[
        "\u0627\u0644\u063a\u064e\u0645\u0651\u064e\u0627\u0633"
    ],
    "name:und_x_variant":[
        "Ghamm\u0101s",
        "Ghamm\u0101sh",
        "Al Ghamm\u0101s"
    ],
    "wof:name":"Al Ghammas",
    "wof:placetype":"neighbourhood"
},
  "geometry": {"coordinates":[43.88926,26.23262],"type":"Point"}
}