{
  "type": "Feature",
  "properties": {
    "gn:admin1_code":"10.0",
    "gn:asciiname":"Quwaybil",
    "gn:country_code":"SA",
    "gn:dem":728,
    "gn:feature_class":"P",
    "gn:feature_code":"PPL",
    "gn:name":"Quwayb\u012bl",
    "gn:population":0,
    "gn:timezone":"Asia/Riyadh",
    "iso:country":"SA",
    "name:und_x_variant":[
        "Quwayb\u012bl"
    ],
    "wof:name":"Quwaybil",
    "wof:placetype":"locality"
},
  "geometry": {"coordinates":[45.57028,25.60472],"type":"Point"}
}