{
  "type": "Feature",
  "properties": {
    "gn:admin1_code":"5",
    "gn:asciiname":"`Alya'",
    "gn:country_code":"SA",
    "gn:dem":154,
    "gn:feature_class":"P",
    "gn:feature_code":"PPL",
    "gn:name":"\u2018Aly\u0101\u2019",
    "gn:population":0,
    "gn:timezone":"Asia/Riyadh",
    "iso:country":"SA",
    "name:ara_x_preferred":[
        "\u2018Aly\u0101\u2019"
    ],
    "name:ara_x_variant":[
        "\u0627\u0644\u0639\u0627\u0644\u064a\u0629"
    ],
    "name:fas_x_preferred":[
        "\u0627\u0644\u0639\u0627\u0644\u06cc\u0647"
    ],
    "name:nno_x_preferred":[
        "`Alya'"
    ],
    "name:urd_x_preferred":[
        "\u0639\u0644\u06cc\u0627"
    ],
    "wof:name":"`Alya'",
    "wof:placetype":"locality"
},
  "geometry": {"coordinates":[38.8832,23.82365],"type":"Point"}
}