{
  "type": "Feature",
  "properties": {
    "gn:admin1_code":"10.0",
    "gn:asciiname":"Dirab",
    "gn:country_code":"SA",
    "gn:dem":576,
    "gn:feature_class":"P",
    "gn:feature_code":"PPL",
    "gn:name":"Dirab",
    "gn:population":0,
    "gn:timezone":"Asia/Riyadh",
    "iso:country":"SA",
    "name:ara_x_preferred":[
        "D\u012br\u0101b"
    ],
    "name:ara_x_variant":[
        "\u062f\u064a\u0631\u0627\u0628"
    ],
    "wof:name":"Dirab",
    "wof:placetype":"neighbourhood"
},
  "geometry": {"coordinates":[46.66294,24.39376],"type":"Point"}
}