{
  "type": "Feature",
  "properties": {
    "gn:admin1_code":"14",
    "gn:asciiname":"Al Yaqutiyah",
    "gn:country_code":"SA",
    "gn:dem":166,
    "gn:feature_class":"P",
    "gn:feature_code":"PPL",
    "gn:name":"Al Y\u0101q\u016bt\u012byah",
    "gn:population":0,
    "gn:timezone":"Asia/Riyadh",
    "iso:country":"SA",
    "name:und_x_variant":[
        "Al Y\u0101q\u016bt\u012byah"
    ],
    "wof:name":"Al Yaqutiyah",
    "wof:placetype":"locality"
},
  "geometry": {"coordinates":[39.65,21.55],"type":"Point"}
}