{
  "type": "Feature",
  "properties": {
    "gn:admin1_code":"14.0",
    "gn:asciiname":"Al Muqayti`",
    "gn:country_code":"SA",
    "gn:dem":117,
    "gn:feature_class":"P",
    "gn:feature_code":"PPL",
    "gn:name":"Al Muqay\u0163\u012b\u2018",
    "gn:population":0,
    "gn:timezone":"Asia/Riyadh",
    "iso:country":"SA",
    "name:fas_x_preferred":[
        "\u0627\u0644\u0645\u0642\u06cc\u062a\u06cc"
    ],
    "name:nno_x_preferred":[
        "Al Muqayti`"
    ],
    "name:und_x_variant":[
        "Al Muqay\u0163\u012b\u2018"
    ],
    "wof:name":"Al Muqayti`",
    "wof:placetype":"locality"
},
  "geometry": {"coordinates":[39.4757,21.85007],"type":"Point"}
}