{
  "type": "Feature",
  "properties": {
    "gn:admin1_code":"0",
    "gn:asciiname":"Jilhayah",
    "gn:country_code":"SA",
    "gn:dem":2033,
    "gn:feature_class":"P",
    "gn:feature_code":"PPL",
    "gn:name":"Jilhayah",
    "gn:population":0,
    "gn:timezone":"Asia/Riyadh",
    "iso:country":"SA",
    "wof:name":"Jilhayah",
    "wof:placetype":"locality"
},
  "geometry": {"coordinates":[41.56667,19.85],"type":"Point"}
}