{
  "type": "Feature",
  "properties": {
    "gn:admin1_code":"5.0",
    "gn:asciiname":"Ash Shuwamin",
    "gn:country_code":"SA",
    "gn:dem":781,
    "gn:feature_class":"P",
    "gn:feature_code":"PPL",
    "gn:name":"Ash Shuw\u0101m\u012bn",
    "gn:population":0,
    "gn:timezone":"Asia/Riyadh",
    "iso:country":"SA",
    "name:ara_x_preferred":[
        "Ash Shuw\u0101m\u012bn"
    ],
    "wof:name":"Ash Shuwamin",
    "wof:placetype":"locality"
},
  "geometry": {"coordinates":[39.7077,23.51977],"type":"Point"}
}