{
  "type": "Feature",
  "properties": {
    "gn:admin1_code":"20",
    "gn:asciiname":"Jimajim",
    "gn:country_code":"SA",
    "gn:dem":535,
    "gn:feature_class":"P",
    "gn:feature_code":"PPL",
    "gn:name":"Jim\u0101jim",
    "gn:population":0,
    "gn:timezone":"Asia/Riyadh",
    "iso:country":"SA",
    "name:ara_x_preferred":[
        "\u062c\u0645\u0627\u062c\u0645"
    ],
    "name:ara_x_variant":[
        "Jim\u0101jim"
    ],
    "wof:name":"Jimajim",
    "wof:placetype":"locality"
},
  "geometry": {"coordinates":[37.67823,31.00618],"type":"Point"}
}