{
  "type": "Feature",
  "properties": {
    "gn:admin1_code":"0",
    "gn:asciiname":"Al Qa`",
    "gn:country_code":"SA",
    "gn:dem":14,
    "gn:feature_class":"P",
    "gn:feature_code":"PPL",
    "gn:name":"Al Q\u0101\u2018",
    "gn:population":0,
    "gn:timezone":"Asia/Riyadh",
    "iso:country":"SA",
    "name:ara_x_preferred":[
        "Al Q\u0101\u2018"
    ],
    "name:und_x_variant":[
        "El Kaa"
    ],
    "wof:name":"Al Qa`",
    "wof:placetype":"locality"
},
  "geometry": {"coordinates":[41.14217,19.13527],"type":"Point"}
}