{
  "type": "Feature",
  "properties": {
    "gn:admin1_code":"5",
    "gn:asciiname":"Al Malbanah",
    "gn:country_code":"SA",
    "gn:dem":371,
    "gn:feature_class":"P",
    "gn:feature_code":"PPL",
    "gn:name":"Al Malbanah",
    "gn:population":0,
    "gn:timezone":"Asia/Riyadh",
    "iso:country":"SA",
    "wof:name":"Al Malbanah",
    "wof:placetype":"locality"
},
  "geometry": {"coordinates":[39.51861,23.17487],"type":"Point"}
}