{
  "type": "Feature",
  "properties": {
    "gn:admin1_code":"13",
    "gn:asciiname":"Dubay`ah",
    "gn:country_code":"SA",
    "gn:dem":745,
    "gn:feature_class":"P",
    "gn:feature_code":"PPL",
    "gn:name":"\u1e10ubay\u2018ah",
    "gn:population":0,
    "gn:timezone":"Asia/Riyadh",
    "iso:country":"SA",
    "name:ara_x_preferred":[
        "\u0636\u064f\u0628\u064e\u064a\u0639\u0629"
    ],
    "name:und_x_variant":[
        "\u1e10ubay\u2018ah"
    ],
    "wof:name":"Dubay`ah",
    "wof:placetype":"locality"
},
  "geometry": {"coordinates":[42.17657,27.9689],"type":"Point"}
}