{
  "type": "Feature",
  "properties": {
    "gn:admin1_code":"10",
    "gn:asciiname":"Banban",
    "gn:country_code":"SA",
    "gn:dem":652,
    "gn:feature_class":"P",
    "gn:feature_code":"PPL",
    "gn:name":"Banb\u0101n",
    "gn:population":0,
    "gn:timezone":"Asia/Riyadh",
    "iso:country":"SA",
    "name:ara_x_preferred":[
        "\u0628\u0646\u0628\u0627\u0646"
    ],
    "name:und_x_variant":[
        "Binb\u0101n",
        "Banb\u0101n",
        "Banban"
    ],
    "wof:name":"Banban",
    "wof:placetype":"neighbourhood"
},
  "geometry": {"coordinates":[46.57288,25.01518],"type":"Point"}
}