{
  "type": "Feature",
  "properties": {
    "gn:admin1_code":"10",
    "gn:asciiname":"Dalqan",
    "gn:country_code":"SA",
    "gn:dem":957,
    "gn:feature_class":"P",
    "gn:feature_code":"PPL",
    "gn:name":"Dalq\u0101n",
    "gn:population":0,
    "gn:timezone":"Asia/Riyadh",
    "iso:country":"SA",
    "name:und_x_variant":[
        "Dalq\u0101n"
    ],
    "wof:name":"Dalqan",
    "wof:placetype":"locality"
},
  "geometry": {"coordinates":[42.61667,24.25],"type":"Point"}
}