{
  "type": "Feature",
  "properties": {
    "gn:admin1_code":"6",
    "gn:asciiname":"Umm Qulayb",
    "gn:country_code":"SA",
    "gn:dem":385,
    "gn:feature_class":"P",
    "gn:feature_code":"PPL",
    "gn:name":"Umm Qulayb",
    "gn:population":0,
    "gn:timezone":"Asia/Riyadh",
    "iso:country":"SA",
    "name:ara_x_preferred":[
        "\u0627\u0645 \u0642\u0644\u064a\u0628"
    ],
    "wof:name":"Umm Qulayb",
    "wof:placetype":"locality"
},
  "geometry": {"coordinates":[45.98019,27.83886],"type":"Point"}
}