{
  "type": "Feature",
  "properties": {
    "iso:country":"SA",
    "name:ara_x_preferred":[
        "\u0627\u0644\u062c\u0632\u064a\u0631\u0629"
    ],
    "name:unk_x_variant":[
        "Al Jaz\u012brah"
    ],
    "qs:gn_country":"SA",
    "qs:gn_fcode":"PPLX",
    "qs:gn_pop":0,
    "qs:name":"\u0627\u0644\u062c\u0632\u064a\u0631\u0629",
    "qs:name_adm0":"\u0627\u0644\u0633\u0639\u0648\u062f\u064a\u0629",
    "qs:name_adm1":"\u0627\u0644\u0631\u064a\u0627\u0636",
    "qs:photos":58,
    "qs:photos_1k":12,
    "qs:photos_9k":1,
    "qs:photos_9r":2,
    "qs:photos_all":58,
    "qs:photos_sr":2,
    "qs:placetype":"Suburb",
    "qs:pop_sr":"0",
    "qs:woe_adm0":23424938,
    "wof:name":"\u0627\u0644\u062c\u0632\u064a\u0631\u0629",
    "wof:placetype":"neighbourhood"
},
  "geometry": {"coordinates":[46.79667,24.66694],"type":"Point"}
}