{
  "type": "Feature",
  "properties": {
    "iso:country":"SA",
    "name:ara_x_preferred":[
        "\u0645\u0637\u0627\u0631 \u0634\u0631\u0648\u0631\u0629 \u0627\u0644\u0645\u062d\u0644\u064a"
    ],
    "name:ckb_x_preferred":[
        "\u0641\u0695\u06c6\u06a9\u06d5\u062e\u0627\u0646\u06d5\u06cc \u0646\u0627\u0648\u062e\u06c6\u06cc\u06cc\u06cc \u0634\u06d5\u0631\u0648\u0648\u0631\u06d5"
    ],
    "name:fas_x_preferred":[
        "\u0641\u0631\u0648\u062f\u06af\u0627\u0647 \u0628\u0648\u0645\u06cc \u0634\u0631\u0648\u0631\u0647"
    ],
    "name:fra_x_preferred":[
        "A\u00e9roport domestique de Sharurah"
    ],
    "name:msa_x_preferred":[
        "Lapangan Terbang Sharurah"
    ],
    "name:pol_x_preferred":[
        "Port lotniczy Szarura"
    ],
    "name:tgk_x_preferred":[
        "\u0424\u0443\u0440\u0443\u0434\u0433\u043e\u04b3\u0438 \u0431\u0443\u043c \u0448\u0440\u0443\u0440\u04b3"
    ],
    "oa:elevation_ft":"2363",
    "oa:type":"medium_airport",
    "wd:wordcount":150,
    "woe:hierarchy":{
        "country_id":23424938,
        "county_id":56120126,
        "planet_id":1,
        "state_id":2346960
    },
    "wof:name":"Sharurah Airport",
    "wof:placetype":"campus"
},
  "geometry": {"coordinates":[47.121111111111,17.466944444444],"type":"Point"}
}