{
  "type": "Feature",
  "properties": {
    "gn:admin1_code":"15",
    "gn:asciiname":"Al Kasib",
    "gn:country_code":"SA",
    "gn:dem":423,
    "gn:feature_class":"P",
    "gn:feature_code":"PPL",
    "gn:name":"Al K\u0101sib",
    "gn:population":0,
    "gn:timezone":"Asia/Riyadh",
    "iso:country":"SA",
    "name:ara_x_preferred":[
        "Al K\u0101sib"
    ],
    "name:ara_x_variant":[
        "\u0627\u0644\u0643\u0627\u0633\u0628"
    ],
    "wof:name":"Al Kasib",
    "wof:placetype":"locality"
},
  "geometry": {"coordinates":[41.93495,30.50294],"type":"Point"}
}