{
  "type": "Feature",
  "properties": {
    "gn:admin1_code":"0",
    "gn:asciiname":"Al `Orosh",
    "gn:country_code":"SA",
    "gn:dem":2440,
    "gn:feature_class":"P",
    "gn:feature_code":"PPL",
    "gn:name":"Al \u2018Orosh",
    "gn:population":0,
    "gn:timezone":"Asia/Riyadh",
    "iso:country":"SA",
    "name:ara_x_preferred":[
        "Al \u2018Orosh"
    ],
    "wof:name":"Al `Orosh",
    "wof:placetype":"locality"
},
  "geometry": {"coordinates":[42.06667,19.31667],"type":"Point"}
}