{
  "type": "Feature",
  "properties": {
    "iso:country":"SA",
    "name:ara_x_preferred":[
        "\u0627\u0644\u0645\u0631\u0648\u062c"
    ],
    "name:eng_x_colloquial":[
        "Al Muroej",
        "Al Muroj",
        "Al Muruj"
    ],
    "name:eng_x_preferred":[
        "Al Marooj"
    ],
    "name:eng_x_variant":[
        "Al Mur\u00f8j",
        "Al Marooj"
    ],
    "name:unk_x_variant":[
        "\u0627\u0644\u0645\u0631\u0648\u062c"
    ],
    "qs:gn_adm0_cc":"SA",
    "qs:gn_local":108410,
    "qs:gn_nam_loc":"\u0627\u0644\u0631\u064a\u0627\u0636, \u0627\u0644\u0631\u064a\u0627\u0636, \u0627\u0644\u0631\u064a\u0627\u0636, SA",
    "qs:gn_namadm1":"10",
    "qs:local_max":655,
    "qs:local_sum":5321,
    "qs:localhoods":54,
    "qs:name":"\u0627\u0644\u0645\u0631\u0648\u062c",
    "qs:name_adm0":"\u0627\u0644\u0633\u0639\u0648\u062f\u064a\u0629",
    "qs:name_adm1":"\u0627\u0644\u0631\u064a\u0627\u0636",
    "qs:name_adm2":"\u0627\u0644\u0631\u064a\u0627\u0636",
    "qs:name_en":"Al Marooj",
    "qs:name_local":"\u0627\u0644\u0631\u064a\u0627\u0636",
    "qs:photo_max":10,
    "qs:photo_sum":44,
    "qs:placetype":"Suburb",
    "qs:quad_count":16,
    "qs:woe_adm0":23424938,
    "qs:woe_adm1":2346951,
    "qs:woe_adm2":56120189,
    "qs:woe_lau":0,
    "qs:woe_local":1939753,
    "qs:woe_ver":"7.10.0",
    "wof:lang":[
        "ara"
    ],
    "wof:name":"\u0627\u0644\u0645\u0631\u0648\u062c",
    "wof:placetype":"neighbourhood"
},
  "geometry": {"coordinates":[46.661255,24.764123],"type":"Point"}
}