{
  "type": "Feature",
  "properties": {
    "gn:admin1_code":"14",
    "gn:asciiname":"Halb",
    "gn:country_code":"SA",
    "gn:dem":16,
    "gn:feature_class":"P",
    "gn:feature_code":"PPL",
    "gn:name":"\u1e28alb",
    "gn:population":0,
    "gn:timezone":"Asia/Riyadh",
    "iso:country":"SA",
    "name:und_x_variant":[
        "\u1e28alb"
    ],
    "wof:name":"Halb",
    "wof:placetype":"locality"
},
  "geometry": {"coordinates":[41.36667,18.66667],"type":"Point"}
}