{
  "type": "Feature",
  "properties": {
    "gn:admin1_code":"10",
    "gn:asciiname":"Bulaydah",
    "gn:cc2":"SA",
    "gn:country_code":"SA",
    "gn:dem":621,
    "gn:feature_class":"P",
    "gn:feature_code":"PPL",
    "gn:name":"Bulaydah",
    "gn:population":0,
    "gn:timezone":"Asia/Riyadh",
    "iso:country":"SA",
    "name:und_x_variant":[
        "Bulaida",
        "Bulaydah"
    ],
    "wof:name":"Bulaydah",
    "wof:placetype":"locality"
},
  "geometry": {"coordinates":[46.23333,24.56667],"type":"Point"}
}