{
  "type": "Feature",
  "properties": {
    "gn:admin1_code":"8",
    "gn:asciiname":"Namasiyah",
    "gn:country_code":"SA",
    "gn:dem":661,
    "gn:feature_class":"P",
    "gn:feature_code":"PPL",
    "gn:name":"Namas\u012byah",
    "gn:population":0,
    "gn:timezone":"Asia/Riyadh",
    "iso:country":"SA",
    "name:und_x_variant":[
        "Namasiya",
        "Namas\u012byah"
    ],
    "wof:name":"Namasiyah",
    "wof:placetype":"locality"
},
  "geometry": {"coordinates":[44.26667,25.83333],"type":"Point"}
}