{
  "type": "Feature",
  "properties": {
    "gn:admin1_code":"17.0",
    "gn:asciiname":"Al Jawwah",
    "gn:country_code":"SA",
    "gn:dem":203,
    "gn:feature_class":"P",
    "gn:feature_code":"PPL",
    "gn:name":"Al Jawwah",
    "gn:population":0,
    "gn:timezone":"Asia/Riyadh",
    "iso:country":"SA",
    "name:ara_x_preferred":[
        "\u0627\u0644\u062c\u0648\u0629"
    ],
    "name:fas_x_preferred":[
        "\u0627\u0644\u062c\u0648\u0647"
    ],
    "name:nno_x_preferred":[
        "Al Jawah"
    ],
    "wof:name":"Al Jawwah",
    "wof:placetype":"locality"
},
  "geometry": {"coordinates":[43.02978,16.95665],"type":"Point"}
}