{
  "type": "Feature",
  "properties": {
    "gn:admin1_code":"14.0",
    "gn:asciiname":"Murshidiyah",
    "gn:country_code":"SA",
    "gn:dem":273,
    "gn:feature_class":"P",
    "gn:feature_code":"PPL",
    "gn:name":"Murshid\u012byah",
    "gn:population":0,
    "gn:timezone":"Asia/Riyadh",
    "iso:country":"SA",
    "name:ara_x_preferred":[
        "\u0645\u0631\u0634\u062f\u064a\u0629"
    ],
    "name:nno_x_preferred":[
        "Murshidiyah"
    ],
    "name:und_x_variant":[
        "Murshid\u012byah"
    ],
    "wof:name":"Murshidiyah",
    "wof:placetype":"neighbourhood"
},
  "geometry": {"coordinates":[39.79288,21.49157],"type":"Point"}
}