{
  "type": "Feature",
  "properties": {
    "gn:admin1_code":"0",
    "gn:asciiname":"Jurumah",
    "gn:country_code":"SA",
    "gn:dem":1081,
    "gn:feature_class":"P",
    "gn:feature_code":"PPL",
    "gn:name":"Jurumah",
    "gn:population":0,
    "gn:timezone":"Asia/Riyadh",
    "iso:country":"SA",
    "name:ara_x_preferred":[
        "\u062c\u0631\u0645\u0629"
    ],
    "wof:name":"Jurumah",
    "wof:placetype":"locality"
},
  "geometry": {"coordinates":[40.91302,27.05332000000001],"type":"Point"}
}