{
  "type": "Feature",
  "properties": {
    "gn:country":"SA",
    "gn:fcode":"PPL",
    "gn:population":11813,
    "iso:country":"SA",
    "name:und_x_variant":[
        "Umm es Sahich"
    ],
    "qs:name":"Umm as S\u0101hik",
    "qs:photos_9r":0,
    "qs:photos_sr":0,
    "qs:pop_sr":"6",
    "wof:name":"Umm as S\u0101hik",
    "wof:placetype":"locality",
    "wof:population":11813
},
  "geometry": {"coordinates":[49.91639,26.65361],"type":"Point"}
}