{
  "type": "Feature",
  "properties": {
    "gn:admin1_code":"10",
    "gn:asciiname":"Al Khala'iq al Gharbiyah",
    "gn:country_code":"SA",
    "gn:dem":716,
    "gn:feature_class":"P",
    "gn:feature_code":"PPL",
    "gn:name":"Al Khal\u0101\u2019iq al Gharb\u012byah",
    "gn:population":0,
    "gn:timezone":"Asia/Riyadh",
    "iso:country":"SA",
    "name:ara_x_preferred":[
        "\u0627\u0644\u062e\u0644\u0627\u0626\u0642 \u0627\u0644\u063a\u0631\u0628\u064a\u0629"
    ],
    "name:und_x_variant":[
        "Al Khal\u0101\u2019iq al Gharb\u012byah"
    ],
    "wof:name":"Al Khala'iq al Gharbiyah",
    "wof:placetype":"locality"
},
  "geometry": {"coordinates":[45.59792,24.52024],"type":"Point"}
}