{
  "type": "Feature",
  "properties": {
    "gn:admin1_code":"14.0",
    "gn:asciiname":"Al Yamaniyah",
    "gn:country_code":"SA",
    "gn:dem":116,
    "gn:feature_class":"P",
    "gn:feature_code":"PPL",
    "gn:name":"Al Yam\u0101n\u012byah",
    "gn:population":0,
    "gn:timezone":"Asia/Riyadh",
    "iso:country":"SA",
    "name:fas_x_preferred":[
        "\u0627\u0644\u06cc\u0645\u0627\u0646\u06cc\u0647"
    ],
    "name:nno_x_preferred":[
        "Al Yamaniyah"
    ],
    "name:und_x_variant":[
        "Al Yam\u0101n\u012byah"
    ],
    "wof:name":"Al Yamaniyah",
    "wof:placetype":"locality"
},
  "geometry": {"coordinates":[39.39,21.96558],"type":"Point"}
}