{
  "type": "Feature",
  "properties": {
    "gn:admin1_code":"10",
    "gn:asciiname":"Rawdat Sudayr",
    "gn:country_code":"SA",
    "gn:dem":735,
    "gn:feature_class":"P",
    "gn:feature_code":"PPL",
    "gn:name":"Raw\u1e11at Sudayr",
    "gn:population":0,
    "gn:timezone":"Asia/Riyadh",
    "iso:country":"SA",
    "name:ara_x_preferred":[
        "\u0631\u0648\u0636\u0629 \u0633\u062f\u064a\u0631"
    ],
    "name:und_x_variant":[
        "Raw\u1e11at Sudayr"
    ],
    "wof:name":"Rawdat Sudayr",
    "wof:placetype":"locality"
},
  "geometry": {"coordinates":[45.5527,25.61327],"type":"Point"}
}