{
  "type": "Feature",
  "properties": {
    "gn:admin1_code":"8",
    "gn:asciiname":"Ash Shayhiyah",
    "gn:country_code":"SA",
    "gn:dem":679,
    "gn:feature_class":"P",
    "gn:feature_code":"PPL",
    "gn:name":"Ash Shay\u1e29\u012byah",
    "gn:population":0,
    "gn:timezone":"Asia/Riyadh",
    "iso:country":"SA",
    "name:ara_x_preferred":[
        "\u0627\u0644\u0634\u062d\u0627\u0646\u064a\u0629"
    ],
    "name:und_x_variant":[
        "Shaihiya",
        "Shay\u1e29\u012byah",
        "Shaih\u012byah",
        "Ash Shay\u1e29\u012byah"
    ],
    "wof:name":"Ash Shayhiyah",
    "wof:placetype":"locality"
},
  "geometry": {"coordinates":[43.46667,25.86667],"type":"Point"}
}