{
  "type": "Feature",
  "properties": {
    "gn:admin1_code":"8",
    "gn:asciiname":"Malqa",
    "gn:country_code":"SA",
    "gn:dem":645,
    "gn:feature_class":"P",
    "gn:feature_code":"PPL",
    "gn:name":"Malq\u00e1",
    "gn:population":0,
    "gn:timezone":"Asia/Riyadh",
    "iso:country":"SA",
    "name:und_x_variant":[
        "Malq\u00e1"
    ],
    "wof:name":"Malqa",
    "wof:placetype":"locality"
},
  "geometry": {"coordinates":[43.95,26.11667000000001],"type":"Point"}
}