{
  "type": "Feature",
  "properties": {
    "gn:country":"SA",
    "gn:fcode":"PPL",
    "gn:pop":5205,
    "iso:country":"SA",
    "qs:name":"Al Fuwayliq",
    "qs:photos_9r":0,
    "qs:photos_sr":0,
    "qs:pop_sr":"5",
    "wof:name":"Al Fuwayliq",
    "wof:placetype":"locality",
    "wof:population":5205
},
  "geometry": {"coordinates":[43.2534,26.44322],"type":"Point"}
}