{
  "type": "Feature",
  "properties": {
    "gn:admin1_code":"14.0",
    "gn:asciiname":"Al `Awajiyah",
    "gn:country_code":"SA",
    "gn:dem":1470,
    "gn:feature_class":"P",
    "gn:feature_code":"PPL",
    "gn:name":"Al \u2018Aw\u0101j\u012byah",
    "gn:population":0,
    "gn:timezone":"Asia/Riyadh",
    "iso:country":"SA",
    "name:und_x_variant":[
        "Al \u2018Aw\u0101j\u012byah"
    ],
    "wof:name":"Al `Awajiyah",
    "wof:placetype":"locality"
},
  "geometry": {"coordinates":[40.54842,21.44769],"type":"Point"}
}