{
  "type": "Feature",
  "properties": {
    "iso:country":"SA",
    "name:ara_x_preferred":[
        "\u0627\u0644\u0645\u0631\u062c\u0627\u0646"
    ],
    "name:eng_x_preferred":[
        "Al Murjan"
    ],
    "name:eng_x_variant":[
        "Al Murjan"
    ],
    "name:unk_x_variant":[
        "\u0627\u0644\u0645\u0631\u062c\u0627\u0646"
    ],
    "qs:gn_local":0,
    "qs:local_max":49,
    "qs:local_sum":102,
    "qs:localhoods":5,
    "qs:name":"\u0627\u0644\u0645\u0631\u062c\u0627\u0646",
    "qs:name_adm0":"\u0627\u0644\u0633\u0639\u0648\u062f\u064a\u0629",
    "qs:name_adm1":"\u0627\u0644\u0634\u0631\u0642\u064a\u0629",
    "qs:name_adm2":"\u0627\u0644\u0642\u0637\u064a\u0641",
    "qs:name_en":"Al Murjan",
    "qs:name_local":"\u0627\u0644\u0642\u0637\u064a\u0641",
    "qs:photo_max":20,
    "qs:photo_sum":26,
    "qs:placetype":"Suburb",
    "qs:quad_count":5,
    "qs:woe_adm0":23424938,
    "qs:woe_adm1":2346954,
    "qs:woe_adm2":56120202,
    "qs:woe_lau":0,
    "qs:woe_local":1939673,
    "qs:woe_ver":"7.10.0",
    "wof:lang":[
        "ara"
    ],
    "wof:name":"\u0627\u0644\u0645\u0631\u062c\u0627\u0646",
    "wof:placetype":"neighbourhood"
},
  "geometry": {"coordinates":[50.042092,26.585883],"type":"Point"}
}