{
  "type": "Feature",
  "properties": {
    "gn:admin1_code":"10",
    "gn:asciiname":"Al Hamjah",
    "gn:country_code":"SA",
    "gn:dem":923,
    "gn:feature_class":"P",
    "gn:feature_code":"PPL",
    "gn:name":"Al Hamjah",
    "gn:population":0,
    "gn:timezone":"Asia/Riyadh",
    "iso:country":"SA",
    "wof:name":"Al Hamjah",
    "wof:placetype":"locality"
},
  "geometry": {"coordinates":[43.74005,24.29656],"type":"Point"}
}