{
  "type": "Feature",
  "properties": {
    "gn:country":"SA",
    "gn:fcode":"PPLX",
    "gn:population":0,
    "iso:country":"SA",
    "name:ara_x_preferred":[
        "\u0627\u0644\u0631\u062d\u0645\u0627\u0646\u064a\u0629"
    ],
    "name:eng_x_preferred":[
        "Ar Rahmaniyah"
    ],
    "name:eng_x_variant":[
        "Ar Rahmaniyah",
        "Al Rahmaniyah"
    ],
    "name:und_x_variant":[
        "Ar Ra\u1e29m\u0101n\u012byah"
    ],
    "qs:gn_adm0_cc":"SA",
    "qs:gn_fcode":"PPLX",
    "qs:gn_local":108410,
    "qs:gn_nam_loc":"\u0627\u0644\u0631\u064a\u0627\u0636, \u0627\u0644\u0631\u064a\u0627\u0636, \u0627\u0644\u0631\u064a\u0627\u0636, SA",
    "qs:gn_namadm1":"10",
    "qs:gn_name":"Ar Ra\u1e29m\u0101n\u012byah",
    "qs:local_max":655,
    "qs:local_sum":5321,
    "qs:localhoods":54,
    "qs:name":"\u0627\u0644\u0631\u062d\u0645\u0627\u0646\u064a\u0629",
    "qs:name_adm0":"\u0627\u0644\u0633\u0639\u0648\u062f\u064a\u0629",
    "qs:name_adm1":"\u0627\u0644\u0631\u064a\u0627\u0636",
    "qs:name_adm2":"\u0627\u0644\u0631\u064a\u0627\u0636",
    "qs:name_en":"Ar Rahmaniyah",
    "qs:name_local":"\u0627\u0644\u0631\u064a\u0627\u0636",
    "qs:photo_max":15,
    "qs:photo_sum":108,
    "qs:placetype":"Suburb",
    "qs:quad_count":18,
    "qs:woe_adm0":23424938,
    "qs:woe_adm1":2346951,
    "qs:woe_adm2":56120189,
    "qs:woe_lau":0,
    "qs:woe_local":1939753,
    "qs:woe_ver":"7.10.0",
    "qs_pg:aaroncc":"SA",
    "qs_pg:gn_country":"SA",
    "qs_pg:gn_fcode":"PPLX",
    "qs_pg:gn_pop":0,
    "qs_pg:name":"\u0627\u0644\u0631\u062d\u0645\u0627\u0646\u064a\u0629",
    "qs_pg:name_adm0":"\u0627\u0644\u0633\u0639\u0648\u062f\u064a\u0629",
    "qs_pg:name_adm1":"\u0627\u0644\u0631\u064a\u0627\u0636",
    "qs_pg:photos":491,
    "qs_pg:photos_1k":99,
    "qs_pg:photos_9k":2,
    "qs_pg:photos_9r":5,
    "qs_pg:photos_all":491,
    "qs_pg:photos_sr":7,
    "qs_pg:pop_sr":0,
    "qs_pg:qs_pg_placetype":"neighbourhood",
    "qs_pg:qs_pg_placetype_gp":"Suburb",
    "qs_pg:woe_adm0":23424938,
    "wof:lang":[
        "ara"
    ],
    "wof:name":"\u0627\u0644\u0631\u062d\u0645\u0627\u0646\u064a\u0629",
    "wof:placetype":"neighbourhood"
},
  "geometry": {"coordinates":[46.666062,24.71885],"type":"Point"}
}