{
  "type": "Feature",
  "properties": {
    "gn:admin1_code":"5",
    "gn:asciiname":"Abyar `Ali",
    "gn:country_code":"SA",
    "gn:dem":639,
    "gn:feature_class":"P",
    "gn:feature_code":"PPL",
    "gn:name":"Aby\u0101r \u2018Al\u012b",
    "gn:population":0,
    "gn:timezone":"Asia/Riyadh",
    "iso:country":"SA",
    "name:ara_x_preferred":[
        "Aby\u0101r \u2018Al\u012b"
    ],
    "wof:name":"Abyar `Ali",
    "wof:placetype":"neighbourhood"
},
  "geometry": {"coordinates":[39.53831,24.41328],"type":"Point"}
}