{
  "type": "Feature",
  "properties": {
    "gn:admin1_code":"5",
    "gn:asciiname":"Abyar `Ali",
    "gn:country_code":"SA",
    "gn:dem":639,
    "gn:feature_class":"P",
    "gn:feature_code":"PPL",
    "gn:name":"Aby\u0101r \u2018Al\u012b",
    "gn:population":0,
    "gn:timezone":"Asia/Riyadh",
    "iso:country":"SA",
    "name:ara_x_preferred":[
        "Aby\u0101r \u2018Al\u012b"
    ],
    "name:ara_x_variant":[
        "\u0623\u0628\u064a\u0627\u0631 \u0639\u0644\u064a,\u0627\u0644\u0645\u062f\u064a\u0646\u0629 \u0627\u0644\u0645\u0646\u0648\u0631\u0629"
    ],
    "name:fas_x_preferred":[
        "\u0627\u0628\u06cc\u0627\u0631 \u0639\u0644\u06cc"
    ],
    "name:ind_x_preferred":[
        "Abyar 'Ali"
    ],
    "name:nno_x_preferred":[
        "Abyar 'Ali"
    ],
    "name:urd_x_preferred":[
        "\u0627\u0628\u06cc\u0627\u0631 \u0639\u0644\u06cc"
    ],
    "wof:name":"Abyar `Ali",
    "wof:placetype":"neighbourhood"
},
  "geometry": {"coordinates":[39.53831,24.41328],"type":"Point"}
}