{
  "type": "Feature",
  "properties": {
    "gn:admin1_code":"10",
    "gn:asciiname":"Al `Ammariyah",
    "gn:country_code":"SA",
    "gn:dem":710,
    "gn:feature_class":"P",
    "gn:feature_code":"PPL",
    "gn:name":"Al \u2018Amm\u0101r\u012byah",
    "gn:population":0,
    "gn:timezone":"Asia/Riyadh",
    "iso:country":"SA",
    "name:ara_x_preferred":[
        "\u0627\u0644\u0639\u0645\u0627\u0631\u064a\u0629"
    ],
    "name:und_x_variant":[
        "\u2018Amm\u0101r\u012byah",
        "Al \u2018Amm\u0101r\u012bya",
        "\u2018Ammariya",
        "Al \u2018Amm\u0101r\u012byah",
        "Al \u2019Ammariyah"
    ],
    "wof:name":"Al `Ammariyah",
    "wof:placetype":"locality"
},
  "geometry": {"coordinates":[46.42268,24.80333],"type":"Point"}
}