{
  "type": "Feature",
  "properties": {
    "gn:admin1_code":"10",
    "gn:asciiname":"Al Fuwayliq",
    "gn:country_code":"SA",
    "gn:dem":722,
    "gn:feature_class":"P",
    "gn:feature_code":"PPL",
    "gn:name":"Al Fuwayliq",
    "gn:population":0,
    "gn:timezone":"Asia/Riyadh",
    "iso:country":"SA",
    "name:ara_x_preferred":[
        "\u0627\u0644\u0641\u0648\u064a\u0644\u0642"
    ],
    "wof:name":"Al Fuwayliq",
    "wof:placetype":"locality"
},
  "geometry": {"coordinates":[45.32925,24.36507000000001],"type":"Point"}
}