{
  "type": "Feature",
  "properties": {
    "gn:admin1_code":"6",
    "gn:asciiname":"Manfadh al Khafji",
    "gn:country_code":"SA",
    "gn:dem":11,
    "gn:feature_class":"P",
    "gn:feature_code":"PPL",
    "gn:name":"Manfadh al Khafj\u012b",
    "gn:population":0,
    "gn:timezone":"Asia/Riyadh",
    "iso:country":"SA",
    "name:und_x_variant":[
        "Manfadh al Khafj\u012b"
    ],
    "wof:name":"Manfadh al Khafji",
    "wof:placetype":"locality"
},
  "geometry": {"coordinates":[48.41078,28.52051],"type":"Point"}
}