{
  "type": "Feature",
  "properties": {
    "gn:gn_country":"SA",
    "gn:gn_fcode":"PPL",
    "gn:gn_pop":7396,
    "gn:population":7396,
    "iso:country":"SA",
    "name:ara_x_preferred":[
        "\u0627\u0644\u062c\u0631\u0627\u062f\u064a\u0629"
    ],
    "name:eng_x_preferred":[
        "Al Jaradiyah"
    ],
    "name:fas_x_preferred":[
        "\u0627\u0644\u062c\u0631\u0627\u062f\u06cc\u0629"
    ],
    "name:nld_x_preferred":[
        "Al Jaradiyah"
    ],
    "name:nno_x_preferred":[
        "Al Jaradiyah"
    ],
    "name:rus_x_preferred":[
        "\u042d\u043b\u044c-\u0414\u0436\u0430\u0440\u0430\u0434\u0438\u044f"
    ],
    "name:urd_x_preferred":[
        "\u062c\u0631\u0627\u062f\u06cc\u06c1"
    ],
    "qs_pg:aaroncc":"SA",
    "qs_pg:gn_country":"SA",
    "qs_pg:gn_fcode":"PPL",
    "qs_pg:gn_pop":7396,
    "qs_pg:name":"Al Jar\u0101d\u012byah",
    "qs_pg:photos_9r":0,
    "qs_pg:photos_sr":0,
    "qs_pg:pop_sr":5,
    "qs_pg:qs_pg_placetype":"locality",
    "wof:name":"Al Jar\u0101d\u012byah",
    "wof:placetype":"locality",
    "wof:population":7396
},
  "geometry": {"coordinates":[42.9124,16.57946],"type":"Point"}
}