{
  "type": "Feature",
  "properties": {
    "iso:country":"SA",
    "ne:ADM0CAP":0.0,
    "ne:ADM0NAME":"Saudi Arabia",
    "ne:ADM0_A3":"SAU",
    "ne:ADM1NAME":"Ar Riyad",
    "ne:ADMIN1_COD":0,
    "ne:CAPALT":0,
    "ne:CHANGED":0,
    "ne:CHECKME":0,
    "ne:COMPARE":0,
    "ne:DIFFASCII":0,
    "ne:ELEVATION":0.0,
    "ne:FEATURECLA":"Populated place",
    "ne:GEONAMEID":-1,
    "ne:GEONAMESNO":"No GeoNames match due to small population, not in GeoNames, or poor NEV placement.",
    "ne:GN_POP":0,
    "ne:GTOPO30":0.0,
    "ne:ISO_A2":"SA",
    "ne:LABELRANK":5,
    "ne:LATITUDE":23.489456,
    "ne:LONGITUDE":46.75636,
    "ne:LS_MATCH":1,
    "ne:LS_NAME":"Al Hillah",
    "ne:MAX_AREAKM":109.0,
    "ne:MAX_AREAMI":42.0,
    "ne:MAX_BBXMAX":44.475,
    "ne:MAX_BBXMIN":44.316667,
    "ne:MAX_BBYMAX":32.558333,
    "ne:MAX_BBYMIN":32.391667,
    "ne:MAX_NATSCA":20.0,
    "ne:MAX_PERKM":113.0,
    "ne:MAX_PERMI":70.0,
    "ne:MAX_POP10":594605,
    "ne:MAX_POP20":594605,
    "ne:MAX_POP300":0,
    "ne:MAX_POP310":0,
    "ne:MAX_POP50":0,
    "ne:MEAN_BBXC":44.408637,
    "ne:MEAN_BBYC":32.481595,
    "ne:MEGACITY":0,
    "ne:MIN_AREAKM":109.0,
    "ne:MIN_AREAMI":42.0,
    "ne:MIN_BBXMAX":44.475,
    "ne:MIN_BBXMIN":44.316667,
    "ne:MIN_BBYMAX":32.558333,
    "ne:MIN_BBYMIN":32.391667,
    "ne:MIN_PERKM":113.0,
    "ne:MIN_PERMI":70.0,
    "ne:NAME":"Al Hillah",
    "ne:NAMEASCII":"Al Hillah",
    "ne:NAMEDIFF":0,
    "ne:NATSCALE":10,
    "ne:POP1950":0,
    "ne:POP1955":0,
    "ne:POP1960":0,
    "ne:POP1965":0,
    "ne:POP1970":0,
    "ne:POP1975":0,
    "ne:POP1980":0,
    "ne:POP1985":0,
    "ne:POP1990":0,
    "ne:POP1995":0,
    "ne:POP2000":0,
    "ne:POP2005":0,
    "ne:POP2010":0,
    "ne:POP2015":0,
    "ne:POP2020":0,
    "ne:POP2025":0,
    "ne:POP2050":0,
    "ne:POP_MAX":594605,
    "ne:POP_MIN":594605,
    "ne:POP_OTHER":584856,
    "ne:RANK_MAX":11,
    "ne:RANK_MIN":11,
    "ne:SCALERANK":8,
    "ne:SOV0NAME":"Saudi Arabia",
    "ne:SOV_A3":"SAU",
    "ne:UN_FID":0,
    "ne:UN_LAT":0.0,
    "ne:UN_LONG":0.0,
    "ne:WORLDCITY":0,
    "ne:min_zoom":7.0,
    "wof:name":"Al Hillah",
    "wof:placetype":"locality"
},
  "geometry": {"coordinates":[46.75636022826461,23.4894563995245],"type":"Point"}
}