{
  "type": "Feature",
  "properties": {
    "gn:admin1_code":"0",
    "gn:asciiname":"Al Khuwayjiyah",
    "gn:cc2":"SA",
    "gn:country_code":"SA",
    "gn:dem":332,
    "gn:feature_class":"P",
    "gn:feature_code":"PPL",
    "gn:name":"Al Khuwayj\u012byah",
    "gn:population":0,
    "gn:timezone":"Asia/Riyadh",
    "iso:country":"SA",
    "name:und_x_variant":[
        "Al Khuwayj\u012bah",
        "Al Khuwayj\u012byah"
    ],
    "wof:name":"Al Khuwayjiyah",
    "wof:placetype":"locality"
},
  "geometry": {"coordinates":[39.51667,23.13333],"type":"Point"}
}