{
  "type": "Feature",
  "properties": {
    "gn:admin1_code":"8",
    "gn:asciiname":"As Sulaybi",
    "gn:country_code":"SA",
    "gn:dem":731,
    "gn:feature_class":"P",
    "gn:feature_code":"PPL",
    "gn:name":"A\u015f \u015eulayb\u012b",
    "gn:population":0,
    "gn:timezone":"Asia/Riyadh",
    "iso:country":"SA",
    "name:ara_x_preferred":[
        "\u0627\u0644\u0635\u0651\u064f\u0644\u064a\u0628\u064a"
    ],
    "name:und_x_variant":[
        "A\u015f \u015eulayb\u012b"
    ],
    "wof:name":"As Sulaybi",
    "wof:placetype":"locality"
},
  "geometry": {"coordinates":[43.04373,25.62603],"type":"Point"}
}