{
  "type": "Feature",
  "properties": {
    "gn:admin1_code":"8",
    "gn:asciiname":"At Tiraq",
    "gn:country_code":"SA",
    "gn:dem":736,
    "gn:feature_class":"P",
    "gn:feature_code":"PPL",
    "gn:name":"A\u0163 \u0162ir\u0101q",
    "gn:population":0,
    "gn:timezone":"Asia/Riyadh",
    "iso:country":"SA",
    "name:ara_x_preferred":[
        "A\u0163 \u0162ir\u0101q"
    ],
    "name:ara_x_variant":[
        "\u0627\u0644\u0637\u0631\u0627\u0642"
    ],
    "wof:name":"At Tiraq",
    "wof:placetype":"locality"
},
  "geometry": {"coordinates":[43.30763,26.67771],"type":"Point"}
}