{
  "type": "Feature",
  "properties": {
    "iso:country":"SA",
    "name:ara_x_preferred":[
        "\u0627\u0644\u062f\u0644\u0645"
    ],
    "name:eng_x_preferred":[
        "Ad Dilam"
    ],
    "qs:gn_pop":0,
    "qs:name":"\u0627\u0644\u062f\u0644\u0645",
    "qs:name_adm0":"\u0627\u0644\u0633\u0639\u0648\u062f\u064a\u0629",
    "qs:name_adm1":"\u0627\u0644\u0631\u064a\u0627\u0636",
    "qs:photos":2,
    "qs:photos_1k":1,
    "qs:photos_9k":1,
    "qs:photos_9r":1,
    "qs:photos_all":2,
    "qs:photos_sr":1,
    "qs:placetype":"Town",
    "qs:pop_sr":"0",
    "qs:woe_adm0":23424938,
    "wof:name":"Ad Dilam",
    "wof:placetype":"locality"
},
  "geometry": {"coordinates":[47.1534915,24.004991],"type":"Point"}
}