{
  "type": "Feature",
  "properties": {
    "gn:admin1_code":"0",
    "gn:asciiname":"Al `Uqdah",
    "gn:country_code":"SA",
    "gn:dem":109,
    "gn:feature_class":"P",
    "gn:feature_code":"PPL",
    "gn:name":"Al \u2018Uqdah",
    "gn:population":0,
    "gn:timezone":"Asia/Riyadh",
    "iso:country":"SA",
    "name:und_x_variant":[
        "Ar Rukbah",
        "Al \u2018Uqdah"
    ],
    "wof:name":"Al `Uqdah",
    "wof:placetype":"locality"
},
  "geometry": {"coordinates":[41.16926,19.5424],"type":"Point"}
}