{
  "type": "Feature",
  "properties": {
    "gn:admin1_code":"14",
    "gn:asciiname":"`Ushayrah",
    "gn:country_code":"SA",
    "gn:dem":1209,
    "gn:feature_class":"P",
    "gn:feature_code":"PPL",
    "gn:name":"\u2018Ushayrah",
    "gn:population":0,
    "gn:timezone":"Asia/Riyadh",
    "iso:country":"SA",
    "name:ara_x_preferred":[
        "\u0639\u0634\u064a\u0631\u0629"
    ],
    "name:fas_x_preferred":[
        "\u0639\u0634\u06cc\u0631\u0629"
    ],
    "name:nno_x_preferred":[
        "`Ushayrah"
    ],
    "name:und_x_variant":[
        "Ashaira",
        "\u2018Ashayrah",
        "\u2018Ushayrah"
    ],
    "name:urd_x_preferred":[
        "\u0639\u0634\u06cc\u0631\u06c1"
    ],
    "wof:name":"`Ushayrah",
    "wof:placetype":"locality"
},
  "geometry": {"coordinates":[40.6506,21.75393],"type":"Point"}
}