{
  "type": "Feature",
  "properties": {
    "gn:admin1_code":"0",
    "gn:asciiname":"Darb Bani Sha`bah",
    "gn:country_code":"SA",
    "gn:dem":1588,
    "gn:feature_class":"P",
    "gn:feature_code":"PPL",
    "gn:name":"Darb Ban\u012b Sha\u2018bah",
    "gn:population":0,
    "gn:timezone":"Asia/Riyadh",
    "iso:country":"SA",
    "name:und_x_variant":[
        "Darb Bani Sha\u2018ba",
        "Darb Ban\u012b Sha\u2018bah"
    ],
    "wof:name":"Darb Bani Sha`bah",
    "wof:placetype":"locality"
},
  "geometry": {"coordinates":[42.45,18.06667],"type":"Point"}
}