{
  "type": "Feature",
  "properties": {
    "iso:country":"SA",
    "qs:gn_pop":0,
    "qs:name":"\u0628\u062d\u0631\u0647",
    "qs:name_adm0":"\u0627\u0644\u0633\u0639\u0648\u062f\u064a\u0629",
    "qs:name_adm1":"\u0645\u0643\u0629",
    "qs:photos":229,
    "qs:photos_1k":46,
    "qs:photos_9k":1,
    "qs:photos_9r":4,
    "qs:photos_all":229,
    "qs:photos_sr":4,
    "qs:placetype":"Town",
    "qs:pop_sr":"0",
    "qs:woe_adm0":23424938,
    "wof:name":"\u0628\u062d\u0631\u0647",
    "wof:placetype":"locality"
},
  "geometry": {"coordinates":[39.497576,21.419673],"type":"Point"}
}