{
  "type": "Feature",
  "properties": {
    "gn:admin1_code":"20",
    "gn:asciiname":"Al Qunaytirah",
    "gn:country_code":"SA",
    "gn:dem":590,
    "gn:feature_class":"P",
    "gn:feature_code":"PPL",
    "gn:name":"Al Qunay\u0163irah",
    "gn:population":0,
    "gn:timezone":"Asia/Riyadh",
    "iso:country":"SA",
    "name:ara_x_preferred":[
        "\u0627\u0644\u0642\u0646\u064a\u0637\u0631\u0629"
    ],
    "name:sco_x_preferred":[
        "Al Qunaytirah"
    ],
    "name:und_x_variant":[
        "Al Qunay\u0163irah"
    ],
    "wof:name":"Al Qunaytirah",
    "wof:placetype":"locality"
},
  "geometry": {"coordinates":[40.09467,29.97468],"type":"Point"}
}