{
  "type": "Feature",
  "properties": {
    "iso:country":"SA",
    "name:ara_x_preferred":[
        "\u0627\u0644\u062f\u0648\u062d\u0629 \u0627\u0644\u0634\u0645\u0627\u0644\u064a\u0629"
    ],
    "name:eng_x_preferred":[
        "Northern Al Dohah"
    ],
    "name:eng_x_variant":[
        "Northern Al Dohah"
    ],
    "name:unk_x_variant":[
        "\u0627\u0644\u062f\u0648\u062d\u0629 \u0627\u0644\u0634\u0645\u0627\u0644\u064a\u0629"
    ],
    "qs:gn_adm0_cc":"SA",
    "qs:gn_local":110336,
    "qs:local_max":174,
    "qs:local_sum":650,
    "qs:localhoods":9,
    "qs:name":"\u0627\u0644\u062f\u0648\u062d\u0629 \u0627\u0644\u0634\u0645\u0627\u0644\u064a\u0629",
    "qs:name_adm0":"\u0627\u0644\u0633\u0639\u0648\u062f\u064a\u0629",
    "qs:name_adm1":"\u0627\u0644\u0634\u0631\u0642\u064a\u0629",
    "qs:name_adm2":"\u0627\u0644\u062f\u0645\u0627\u0645",
    "qs:name_en":"Northern Al Dohah",
    "qs:name_local":"\u0627\u0644\u062f\u0645\u0627\u0645",
    "qs:photo_max":9,
    "qs:photo_sum":15,
    "qs:placetype":"Suburb",
    "qs:quad_count":5,
    "qs:woe_adm0":23424938,
    "qs:woe_adm1":2346954,
    "qs:woe_adm2":56120200,
    "qs:woe_lau":0,
    "qs:woe_local":1939574,
    "qs:woe_ver":"7.10.0",
    "wof:lang":[
        "ara"
    ],
    "wof:name":"\u0627\u0644\u062f\u0648\u062d\u0629 \u0627\u0644\u0634\u0645\u0627\u0644\u064a\u0629",
    "wof:placetype":"neighbourhood"
},
  "geometry": {"coordinates":[50.170349,26.334611],"type":"Point"}
}