{
  "type": "Feature",
  "properties": {
    "gn:admin1_code":"0.0",
    "gn:asciiname":"Jash",
    "gn:country_code":"SA",
    "gn:dem":1167,
    "gn:feature_class":"P",
    "gn:feature_code":"PPL",
    "gn:name":"J\u0101sh",
    "gn:population":0,
    "gn:timezone":"Asia/Riyadh",
    "iso:country":"SA",
    "name:ara_x_preferred":[
        "J\u0101sh"
    ],
    "name:ara_x_variant":[
        "\u062c\u0627\u0634"
    ],
    "wof:name":"Jash",
    "wof:placetype":"locality"
},
  "geometry": {"coordinates":[43.45224,19.37323],"type":"Point"}
}