{
  "type": "Feature",
  "properties": {
    "gn:admin1_code":"10",
    "gn:asciiname":"Ash Sharafa",
    "gn:country_code":"SA",
    "gn:dem":661,
    "gn:feature_class":"P",
    "gn:feature_code":"PPL",
    "gn:name":"Ash Shar\u0101f\u00e1",
    "gn:population":0,
    "gn:timezone":"Asia/Riyadh",
    "iso:country":"SA",
    "name:und_x_variant":[
        "Sharafa",
        "Ash Shar\u0101f\u00e1"
    ],
    "wof:name":"Ash Sharafa",
    "wof:placetype":"locality"
},
  "geometry": {"coordinates":[44.90135,20.43473],"type":"Point"}
}