{
  "type": "Feature",
  "properties": {
    "gn:admin1_code":"17",
    "gn:asciiname":"Matariq",
    "gn:country_code":"SA",
    "gn:dem":275,
    "gn:feature_class":"P",
    "gn:feature_code":"PPL",
    "gn:name":"Ma\u0163\u0101riq",
    "gn:population":0,
    "gn:timezone":"Asia/Riyadh",
    "iso:country":"SA",
    "name:und_x_variant":[
        "Ma\u0163\u0101riq"
    ],
    "wof:name":"Matariq",
    "wof:placetype":"locality"
},
  "geometry": {"coordinates":[43.1231,16.90297],"type":"Point"}
}