{
  "type": "Feature",
  "properties": {
    "gn:admin1_code":"6.0",
    "gn:asciiname":"Jabal al Qawm",
    "gn:country_code":"SA",
    "gn:dem":10,
    "gn:feature_class":"P",
    "gn:feature_code":"PPL",
    "gn:name":"Jabal al Qawm",
    "gn:population":0,
    "gn:timezone":"Asia/Riyadh",
    "iso:country":"SA",
    "wof:name":"Jabal al Qawm",
    "wof:placetype":"neighbourhood"
},
  "geometry": {"coordinates":[49.97806,26.605],"type":"Point"}
}