{
  "type": "Feature",
  "properties": {
    "gn:admin1_code":"13",
    "gn:asciiname":"Turubah",
    "gn:country_code":"SA",
    "gn:dem":689,
    "gn:feature_class":"P",
    "gn:feature_code":"PPL",
    "gn:name":"Turubah",
    "gn:population":0,
    "gn:timezone":"Asia/Riyadh",
    "iso:country":"SA",
    "name:ara_x_preferred":[
        "\u062a\u0631\u0628\u0629"
    ],
    "name:fas_x_preferred":[
        "\u062a\u0631\u0628\u0629"
    ],
    "name:nno_x_preferred":[
        "Turubah"
    ],
    "name:urd_x_preferred":[
        "\u062a\u0631\u0628\u06c1"
    ],
    "wof:name":"Turubah",
    "wof:placetype":"locality"
},
  "geometry": {"coordinates":[42.92457,28.25849],"type":"Point"}
}