{
  "type": "Feature",
  "properties": {
    "gn:admin1_code":"10",
    "gn:asciiname":"Al `Abbasiyah",
    "gn:country_code":"SA",
    "gn:dem":725,
    "gn:feature_class":"P",
    "gn:feature_code":"PPL",
    "gn:name":"Al \u2018Abb\u0101s\u012byah",
    "gn:population":0,
    "gn:timezone":"Asia/Riyadh",
    "iso:country":"SA",
    "name:ara_x_preferred":[
        "\u0627\u0644\u0639\u0628\u0627\u0633\u064a\u0629"
    ],
    "name:und_x_variant":[
        "Al \u2018Abb\u0101s\u012byah"
    ],
    "wof:name":"Al `Abbasiyah",
    "wof:placetype":"locality"
},
  "geometry": {"coordinates":[45.48283,24.47449],"type":"Point"}
}