{
  "type": "Feature",
  "properties": {
    "gn:admin1_code":"0",
    "gn:asciiname":"Ahad Marrat",
    "gn:country_code":"SA",
    "gn:dem":2237,
    "gn:feature_class":"P",
    "gn:feature_code":"PPL",
    "gn:name":"A\u1e29ad Marr\u0101t",
    "gn:population":0,
    "gn:timezone":"Asia/Riyadh",
    "iso:country":"SA",
    "name:und_x_variant":[
        "A\u1e29ad Marr\u0101t"
    ],
    "wof:name":"Ahad Marrat",
    "wof:placetype":"locality"
},
  "geometry": {"coordinates":[42.56017,18.18453],"type":"Point"}
}