{
  "type": "Feature",
  "properties": {
    "gn:admin1_code":"10",
    "gn:asciiname":"Ruwayghib",
    "gn:country_code":"SA",
    "gn:dem":692,
    "gn:feature_class":"P",
    "gn:feature_code":"PPL",
    "gn:name":"Ruwayghib",
    "gn:population":0,
    "gn:timezone":"Asia/Riyadh",
    "iso:country":"SA",
    "name:ara_x_preferred":[
        "\u0631\u0648\u064a\u063a\u0628"
    ],
    "wof:name":"Ruwayghib",
    "wof:placetype":"locality"
},
  "geometry": {"coordinates":[46.36555,25.66138],"type":"Point"}
}