{
  "type": "Feature",
  "properties": {
    "gn:admin1_code":"0",
    "gn:asciiname":"Khasa",
    "gn:cc2":"SA",
    "gn:country_code":"SA",
    "gn:dem":-9999,
    "gn:feature_class":"P",
    "gn:feature_code":"PPL",
    "gn:name":"Khasa",
    "gn:population":0,
    "gn:timezone":"Asia/Riyadh",
    "iso:country":"SA",
    "name:swe_x_preferred":[
        "Khasa"
    ],
    "name:und_x_variant":[
        "Hasa",
        "Khisa",
        "Khasa"
    ],
    "wof:name":"Khasa",
    "wof:placetype":"locality"
},
  "geometry": {"coordinates":[41.63333,17.93332999999999],"type":"Point"}
}