{
  "type": "Feature",
  "properties": {
    "gn:admin1_code":"17",
    "gn:asciiname":"Suq al Layl",
    "gn:country_code":"SA",
    "gn:dem":89,
    "gn:feature_class":"P",
    "gn:feature_code":"PPL",
    "gn:name":"S\u016bq al Layl",
    "gn:population":0,
    "gn:timezone":"Asia/Riyadh",
    "iso:country":"SA",
    "name:und_x_variant":[
        "S\u016bq al Layl"
    ],
    "wof:name":"Suq al Layl",
    "wof:placetype":"locality"
},
  "geometry": {"coordinates":[42.99335,16.71757],"type":"Point"}
}