{
  "type": "Feature",
  "properties": {
    "gn:admin1_code":"10",
    "gn:asciiname":"Al Khatilah",
    "gn:country_code":"SA",
    "gn:dem":639,
    "gn:feature_class":"P",
    "gn:feature_code":"PPL",
    "gn:name":"Al Kh\u0101tilah",
    "gn:population":0,
    "gn:timezone":"Asia/Riyadh",
    "iso:country":"SA",
    "name:ara_x_preferred":[
        "\u0627\u0644\u062e\u0627\u062a\u0644\u0629"
    ],
    "name:und_x_variant":[
        "Al Kh\u0101tilah"
    ],
    "wof:name":"Al Khatilah",
    "wof:placetype":"locality"
},
  "geometry": {"coordinates":[46.1887,25.49147],"type":"Point"}
}