{
  "type": "Feature",
  "properties": {
    "gn:admin1_code":"17",
    "gn:asciiname":"Khumsiyah",
    "gn:country_code":"SA",
    "gn:dem":29,
    "gn:feature_class":"P",
    "gn:feature_code":"PPL",
    "gn:name":"Khums\u012byah",
    "gn:population":0,
    "gn:timezone":"Asia/Riyadh",
    "iso:country":"SA",
    "name:nno_x_preferred":[
        "Khumsiyah"
    ],
    "name:und_x_variant":[
        "Khums\u012byah"
    ],
    "wof:name":"Khumsiyah",
    "wof:placetype":"locality"
},
  "geometry": {"coordinates":[42.80194,16.77139],"type":"Point"}
}