{
  "type": "Feature",
  "properties": {
    "gn:admin1_code":"0",
    "gn:asciiname":"Zurayghit",
    "gn:country_code":"SA",
    "gn:dem":1037,
    "gn:feature_class":"P",
    "gn:feature_code":"PPL",
    "gn:name":"Zurayghi\u0163",
    "gn:population":0,
    "gn:timezone":"Asia/Riyadh",
    "iso:country":"SA",
    "name:und_x_variant":[
        "Zurayghi\u0163"
    ],
    "wof:name":"Zurayghit",
    "wof:placetype":"locality"
},
  "geometry": {"coordinates":[40.55,26.48333],"type":"Point"}
}