{
  "type": "Feature",
  "properties": {
    "gn:admin1_code":"10",
    "gn:asciiname":"Musiddah",
    "gn:country_code":"SA",
    "gn:dem":594,
    "gn:feature_class":"P",
    "gn:feature_code":"PPL",
    "gn:name":"Mu\u015fiddah",
    "gn:population":0,
    "gn:timezone":"Asia/Riyadh",
    "iso:country":"SA",
    "name:ara_x_preferred":[
        "\u0645\u0635\u062f\u0629"
    ],
    "name:und_x_variant":[
        "Mu\u015fiddah",
        "Ma\u015faddah"
    ],
    "wof:name":"Musiddah",
    "wof:placetype":"locality"
},
  "geometry": {"coordinates":[45.24483,26.64178],"type":"Point"}
}