{
  "type": "Feature",
  "properties": {
    "gn:admin1_code":"0",
    "gn:asciiname":"Hudayb",
    "gn:cc2":"SA",
    "gn:country_code":"SA",
    "gn:dem":1192,
    "gn:feature_class":"P",
    "gn:feature_code":"PPL",
    "gn:name":"Hu\u1e11ayb",
    "gn:population":0,
    "gn:timezone":"Asia/Riyadh",
    "iso:country":"SA",
    "name:und_x_variant":[
        "Hudhaib",
        "Hu\u1e11ayb"
    ],
    "wof:name":"Hudayb",
    "wof:placetype":"locality"
},
  "geometry": {"coordinates":[42.58333,19.95],"type":"Point"}
}