{
  "type": "Feature",
  "properties": {
    "gn:admin1_code":"14",
    "gn:asciiname":"Ad Dawh al Kabir",
    "gn:country_code":"SA",
    "gn:dem":171,
    "gn:feature_class":"P",
    "gn:feature_code":"PPL",
    "gn:name":"Ad Daw\u1e29 al Kab\u012br",
    "gn:population":0,
    "gn:timezone":"Asia/Riyadh",
    "iso:country":"SA",
    "name:und_x_variant":[
        "Ad Daw\u1e29 al Kab\u012br"
    ],
    "wof:name":"Ad Dawh al Kabir",
    "wof:placetype":"locality"
},
  "geometry": {"coordinates":[39.6579,21.55628],"type":"Point"}
}