{
  "type": "Feature",
  "properties": {
    "gn:admin1_code":"14",
    "gn:asciiname":"Ad Dawh al Kabir",
    "gn:country_code":"SA",
    "gn:dem":171,
    "gn:feature_class":"P",
    "gn:feature_code":"PPL",
    "gn:name":"Ad Daw\u1e29 al Kab\u012br",
    "gn:population":0,
    "gn:timezone":"Asia/Riyadh",
    "iso:country":"SA",
    "name:ara_x_preferred":[
        "\u0627\u0644\u062f\u0648\u062d \u0627\u0644\u0643\u0628\u064a\u0631"
    ],
    "name:fas_x_preferred":[
        "\u0627\u062f\u0627\u0648 \u0627\u0644\u06a9\u0628\u06cc\u0631"
    ],
    "name:nno_x_preferred":[
        "Ad Dawh al Kabir"
    ],
    "name:und_x_variant":[
        "Ad Daw\u1e29 al Kab\u012br"
    ],
    "name:urd_x_preferred":[
        "\u0627\u0644\u062f\u0648\u062d \u0627\u0644\u06a9\u0628\u06cc\u0631"
    ],
    "wof:name":"Ad Dawh al Kabir",
    "wof:placetype":"locality"
},
  "geometry": {"coordinates":[39.6579,21.55628],"type":"Point"}
}