{
  "type": "Feature",
  "properties": {
    "gn:admin1_code":"10",
    "gn:asciiname":"Al Muhawal",
    "gn:country_code":"SA",
    "gn:dem":928,
    "gn:feature_class":"P",
    "gn:feature_code":"PPL",
    "gn:name":"Al Mu\u1e29\u0101wal",
    "gn:population":0,
    "gn:timezone":"Asia/Riyadh",
    "iso:country":"SA",
    "name:und_x_variant":[
        "Al Mu\u1e29\u0101wal"
    ],
    "wof:name":"Al Muhawal",
    "wof:placetype":"locality"
},
  "geometry": {"coordinates":[43.63361,24.48333],"type":"Point"}
}