{
  "type": "Feature",
  "properties": {
    "gn:admin1_code":"10.0",
    "gn:asciiname":"Ar Rifa`",
    "gn:country_code":"SA",
    "gn:dem":454,
    "gn:feature_class":"P",
    "gn:feature_code":"PPL",
    "gn:name":"Ar Rif\u0101\u2018",
    "gn:population":0,
    "gn:timezone":"Asia/Riyadh",
    "iso:country":"SA",
    "name:ara_x_preferred":[
        "Ar Rif\u0101\u2018"
    ],
    "name:ara_x_variant":[
        "\u0627\u0644\u0631\u0641\u0627\u0639"
    ],
    "name:und_x_variant":[
        "Ar Ruf\u0101\u2018",
        "Ar Rufa\u2019"
    ],
    "wof:name":"Ar Rifa`",
    "wof:placetype":"locality"
},
  "geometry": {"coordinates":[47.17343,24.30246],"type":"Point"}
}