{
  "type": "Feature",
  "properties": {
    "gn:admin1_code":"13",
    "gn:asciiname":"Ibdah",
    "gn:country_code":"SA",
    "gn:dem":959,
    "gn:feature_class":"P",
    "gn:feature_code":"PPL",
    "gn:name":"Ib\u1e11ah",
    "gn:population":0,
    "gn:timezone":"Asia/Riyadh",
    "iso:country":"SA",
    "name:ara_x_preferred":[
        "\u0627\u0628\u0636\u0629"
    ],
    "name:und_x_variant":[
        "Ib\u1e11ah"
    ],
    "wof:name":"Ibdah",
    "wof:placetype":"locality"
},
  "geometry": {"coordinates":[42.34681,26.96596],"type":"Point"}
}