{
  "type": "Feature",
  "properties": {
    "gn:admin1_code":"10.0",
    "gn:asciiname":"Al Bad` al Qadim",
    "gn:country_code":"SA",
    "gn:dem":439,
    "gn:feature_class":"P",
    "gn:feature_code":"PPL",
    "gn:name":"Al Bad\u2018 al Qad\u012bm",
    "gn:population":0,
    "gn:timezone":"Asia/Riyadh",
    "iso:country":"SA",
    "name:und_x_variant":[
        "Al Bad\u2018 al Qad\u012bm"
    ],
    "wof:name":"Al Bad` al Qadim",
    "wof:placetype":"locality"
},
  "geometry": {"coordinates":[47.26708,24.18845],"type":"Point"}
}