{
  "type": "Feature",
  "properties": {
    "gn:admin1_code":"10",
    "gn:asciiname":"Al Ash`ariyah",
    "gn:country_code":"SA",
    "gn:dem":1045,
    "gn:feature_class":"P",
    "gn:feature_code":"PPL",
    "gn:name":"Al Ash\u2018ar\u012byah",
    "gn:population":0,
    "gn:timezone":"Asia/Riyadh",
    "iso:country":"SA",
    "name:und_x_variant":[
        "Al Ash\u2018ar\u012byah"
    ],
    "wof:name":"Al Ash`ariyah",
    "wof:placetype":"locality"
},
  "geometry": {"coordinates":[43.00134,24.35842],"type":"Point"}
}