{
  "type": "Feature",
  "properties": {
    "gn:admin1_code":"0",
    "gn:asciiname":"Salam",
    "gn:country_code":"SA",
    "gn:dem":964,
    "gn:feature_class":"P",
    "gn:feature_code":"PPL",
    "gn:name":"Sal\u0101m",
    "gn:population":0,
    "gn:timezone":"Asia/Riyadh",
    "iso:country":"SA",
    "name:und_x_variant":[
        "Sal\u0101m"
    ],
    "wof:name":"Salam",
    "wof:placetype":"locality"
},
  "geometry": {"coordinates":[43.11667,24.71667],"type":"Point"}
}