{
  "type": "Feature",
  "properties": {
    "gn:admin1_code":"14.0",
    "gn:asciiname":"Al Wudiyah",
    "gn:country_code":"SA",
    "gn:dem":1010,
    "gn:feature_class":"P",
    "gn:feature_code":"PPL",
    "gn:name":"Al Wudiyah",
    "gn:population":0,
    "gn:timezone":"Asia/Riyadh",
    "iso:country":"SA",
    "wof:name":"Al Wudiyah",
    "wof:placetype":"locality"
},
  "geometry": {"coordinates":[40.38917,22.49722],"type":"Point"}
}