{
  "type": "Feature",
  "properties": {
    "gn:admin1_code":"14",
    "gn:asciiname":"Tharwah",
    "gn:country_code":"SA",
    "gn:dem":148,
    "gn:feature_class":"P",
    "gn:feature_code":"PPL",
    "gn:name":"Tharwah",
    "gn:population":0,
    "gn:timezone":"Asia/Riyadh",
    "iso:country":"SA",
    "name:nno_x_preferred":[
        "Tharwah"
    ],
    "name:und_x_variant":[
        "Tharwa"
    ],
    "wof:name":"Tharwah",
    "wof:placetype":"locality"
},
  "geometry": {"coordinates":[39.6034,21.50329],"type":"Point"}
}