{
  "type": "Feature",
  "properties": {
    "gn:admin1_code":"0",
    "gn:asciiname":"Al Dalham",
    "gn:country_code":"SA",
    "gn:dem":2324,
    "gn:feature_class":"P",
    "gn:feature_code":"PPL",
    "gn:name":"\u0100l Dalham",
    "gn:population":0,
    "gn:timezone":"Asia/Riyadh",
    "iso:country":"SA",
    "name:und_x_variant":[
        "\u0100l Dalham"
    ],
    "wof:name":"Al Dalham",
    "wof:placetype":"locality"
},
  "geometry": {"coordinates":[42.95378,18.04684],"type":"Point"}
}