{
  "type": "Feature",
  "properties": {
    "gn:admin1_code":"8",
    "gn:asciiname":"Al Hajnawi",
    "gn:country_code":"SA",
    "gn:dem":654,
    "gn:feature_class":"P",
    "gn:feature_code":"PPL",
    "gn:name":"Al \u1e28ajn\u0101w\u012b",
    "gn:population":0,
    "gn:timezone":"Asia/Riyadh",
    "iso:country":"SA",
    "name:ara_x_preferred":[
        "\u0627\u0644\u062d\u062c\u0646\u0627\u0648\u064a"
    ],
    "name:und_x_variant":[
        "Al \u1e28ajn\u0101w\u012b",
        "Qusur Haqnawi",
        "Qu\u015f\u016br \u1e28ajn\u0101w\u012b",
        "\u1e28ajn\u0101w\u012b"
    ],
    "wof:name":"Al Hajnawi",
    "wof:placetype":"locality"
},
  "geometry": {"coordinates":[43.63652,25.93624],"type":"Point"}
}