{
  "type": "Feature",
  "properties": {
    "gn:admin1_code":"6",
    "gn:asciiname":"An Nazim",
    "gn:country_code":"SA",
    "gn:dem":403,
    "gn:feature_class":"P",
    "gn:feature_code":"PPLL",
    "gn:name":"An Naz\u0327\u012bm",
    "gn:population":0,
    "gn:timezone":"Asia/Riyadh",
    "iso:country":"SA",
    "name:und_x_variant":[
        "An Naz\u0327\u012bm"
    ],
    "wof:name":"An Nazim",
    "wof:placetype":"locality"
},
  "geometry": {"coordinates":[45.23081,28.65431],"type":"Point"}
}