{
  "type": "Feature",
  "properties": {
    "gn:admin1_code":"20",
    "gn:asciiname":"Mujamma` al Hadithah",
    "gn:country_code":"SA",
    "gn:dem":536,
    "gn:feature_class":"P",
    "gn:feature_code":"PPL",
    "gn:name":"Mujamma\u2018 al \u1e28ad\u012bthah",
    "gn:population":0,
    "gn:timezone":"Asia/Riyadh",
    "iso:country":"SA",
    "name:ara_x_preferred":[
        "\u0645\u062c\u0645\u0639 \u0627\u0644\u062d\u062f\u064a\u062b\u0629"
    ],
    "name:und_x_variant":[
        "Mujamma\u2018 al \u1e28ad\u012bthah"
    ],
    "wof:name":"Mujamma` al Hadithah",
    "wof:placetype":"locality"
},
  "geometry": {"coordinates":[37.11176,31.51344000000001],"type":"Point"}
}