{
  "type": "Feature",
  "properties": {
    "gn:admin1_code":"20",
    "gn:asciiname":"Al Laqayit",
    "gn:country_code":"SA",
    "gn:dem":553,
    "gn:feature_class":"P",
    "gn:feature_code":"PPL",
    "gn:name":"Al Laq\u0101yi\u0163",
    "gn:population":0,
    "gn:timezone":"Asia/Riyadh",
    "iso:country":"SA",
    "name:ara_x_preferred":[
        "\u0627\u0644\u0644\u0642\u0627\u064a\u0637"
    ],
    "name:und_x_variant":[
        "Al Laq\u0101yi\u0163"
    ],
    "wof:name":"Al Laqayit",
    "wof:placetype":"locality"
},
  "geometry": {"coordinates":[40.25404,29.98847],"type":"Point"}
}