{
  "type": "Feature",
  "properties": {
    "gn:admin1_code":"17",
    "gn:asciiname":"Al Haqw",
    "gn:country_code":"SA",
    "gn:dem":216,
    "gn:feature_class":"P",
    "gn:feature_code":"PPL",
    "gn:name":"Al \u1e28aqw",
    "gn:population":0,
    "gn:timezone":"Asia/Riyadh",
    "iso:country":"SA",
    "name:ara_x_preferred":[
        "\u0627\u0644\u062d\u0642\u0648"
    ],
    "name:und_x_variant":[
        "Haqu",
        "Al \u1e28aq\u016b",
        "Al \u1e28aqw"
    ],
    "wof:name":"Al Haqw",
    "wof:placetype":"locality"
},
  "geometry": {"coordinates":[42.7002,17.52495],"type":"Point"}
}