{
  "type": "Feature",
  "properties": {
    "gn:admin1_code":"10",
    "gn:asciiname":"Al Lughfiyah",
    "gn:country_code":"SA",
    "gn:dem":717,
    "gn:feature_class":"P",
    "gn:feature_code":"PPL",
    "gn:name":"Al Lughf\u012byah",
    "gn:population":0,
    "gn:timezone":"Asia/Riyadh",
    "iso:country":"SA",
    "name:ara_x_preferred":[
        "\u0627\u0644\u0644\u063a\u0641\u064a\u0629"
    ],
    "name:und_x_variant":[
        "Al Lughf\u012byah"
    ],
    "wof:name":"Al Lughfiyah",
    "wof:placetype":"locality"
},
  "geometry": {"coordinates":[46.22168,24.16153],"type":"Point"}
}