{
  "type": "Feature",
  "properties": {
    "gn:admin1_code":"0",
    "gn:asciiname":"Al Wasat",
    "gn:country_code":"SA",
    "gn:dem":2391,
    "gn:feature_class":"P",
    "gn:feature_code":"PPL",
    "gn:name":"Al Wasa\u0163",
    "gn:population":0,
    "gn:timezone":"Asia/Riyadh",
    "iso:country":"SA",
    "name:und_x_variant":[
        "Al Wasa\u0163"
    ],
    "wof:name":"Al Wasat",
    "wof:placetype":"locality"
},
  "geometry": {"coordinates":[43.13333,17.96667],"type":"Point"}
}