{
  "type": "Feature",
  "properties": {
    "gn:admin1_code":"0",
    "gn:asciiname":"Arbal Allah",
    "gn:country_code":"SA",
    "gn:dem":2283,
    "gn:feature_class":"P",
    "gn:feature_code":"PPL",
    "gn:name":"Arbal All\u0101h",
    "gn:population":0,
    "gn:timezone":"Asia/Riyadh",
    "iso:country":"SA",
    "name:und_x_variant":[
        "Arbal All\u0101h"
    ],
    "wof:name":"Arbal Allah",
    "wof:placetype":"locality"
},
  "geometry": {"coordinates":[41.45,20.05],"type":"Point"}
}