{
  "type": "Feature",
  "properties": {
    "gn:admin1_code":"10",
    "gn:asciiname":"Abarahee at Taybi",
    "gn:country_code":"SA",
    "gn:dem":939,
    "gn:feature_class":"P",
    "gn:feature_code":"PPL",
    "gn:name":"Abarahee a\u0163 \u0162ayb\u012b",
    "gn:population":0,
    "gn:timezone":"Asia/Riyadh",
    "iso:country":"SA",
    "name:und_x_variant":[
        "Abarahee a\u0163 \u0162ayb\u012b"
    ],
    "wof:name":"Abarahee at Taybi",
    "wof:placetype":"locality"
},
  "geometry": {"coordinates":[45.03333,23.96667],"type":"Point"}
}