{
  "type": "Feature",
  "properties": {
    "gn:admin1_code":"10",
    "gn:asciiname":"Khunayfsah",
    "gn:country_code":"SA",
    "gn:dem":981,
    "gn:feature_class":"P",
    "gn:feature_code":"PPL",
    "gn:name":"Khunayfsah",
    "gn:population":0,
    "gn:timezone":"Asia/Riyadh",
    "iso:country":"SA",
    "wof:name":"Khunayfsah",
    "wof:placetype":"locality"
},
  "geometry": {"coordinates":[44.78341,23.85348],"type":"Point"}
}