{
  "type": "Feature",
  "properties": {
    "gn:admin1_code":"0",
    "gn:asciiname":"Al Farshah",
    "gn:country_code":"SA",
    "gn:dem":61,
    "gn:feature_class":"P",
    "gn:feature_code":"PPL",
    "gn:name":"Al Farshah",
    "gn:population":0,
    "gn:timezone":"Asia/Riyadh",
    "iso:country":"SA",
    "name:und_x_variant":[
        "Farshah",
        "Al Farshah"
    ],
    "wof:name":"Al Farshah",
    "wof:placetype":"locality"
},
  "geometry": {"coordinates":[41.2467,19.24255],"type":"Point"}
}