{
  "type": "Feature",
  "properties": {
    "gn:admin1_code":"16.0",
    "gn:asciiname":"Aba al Rashash",
    "gn:country_code":"SA",
    "gn:dem":1290,
    "gn:feature_class":"P",
    "gn:feature_code":"PPLL",
    "gn:name":"Aba al Rashash",
    "gn:population":0,
    "gn:timezone":"Asia/Riyadh",
    "iso:country":"SA",
    "name:ara_x_preferred":[
        "\u0623\u0628\u0627 \u0627\u0644\u0631\u0634\u0627\u0634"
    ],
    "name:und_x_variant":[
        "Ab\u0101 ar Rash\u0101sh",
        "Aba al Rashash"
    ],
    "wof:name":"Aba al Rashash",
    "wof:placetype":"locality"
},
  "geometry": {"coordinates":[44.25078,17.59157],"type":"Point"}
}