{
  "type": "Feature",
  "properties": {
    "gn:admin1_code":"5.0",
    "gn:asciiname":"Al Fara`",
    "gn:country_code":"SA",
    "gn:dem":700,
    "gn:feature_class":"P",
    "gn:feature_code":"PPL",
    "gn:name":"Al Fara\u2018",
    "gn:population":0,
    "gn:timezone":"Asia/Riyadh",
    "iso:country":"SA",
    "name:und_x_variant":[
        "Al Fara\u2018"
    ],
    "wof:name":"Al Fara`",
    "wof:placetype":"locality"
},
  "geometry": {"coordinates":[38.0619,24.97436],"type":"Point"}
}