{
  "type": "Feature",
  "properties": {
    "gn:admin1_code":"0",
    "gn:asciiname":"Sabihi",
    "gn:country_code":"SA",
    "gn:dem":1148,
    "gn:feature_class":"P",
    "gn:feature_code":"PPL",
    "gn:name":"\u015eab\u012b\u1e29\u012b",
    "gn:population":0,
    "gn:timezone":"Asia/Riyadh",
    "iso:country":"SA",
    "name:und_x_variant":[
        "\u015eab\u012b\u1e29\u012b"
    ],
    "wof:name":"Sabihi",
    "wof:placetype":"locality"
},
  "geometry": {"coordinates":[42.59821,20.0767],"type":"Point"}
}