{
  "type": "Feature",
  "properties": {
    "gn:admin1_code":"20",
    "gn:asciiname":"Ithrah",
    "gn:country_code":"SA",
    "gn:dem":515,
    "gn:feature_class":"P",
    "gn:feature_code":"PPLL",
    "gn:name":"Ithrah",
    "gn:population":0,
    "gn:timezone":"Asia/Riyadh",
    "iso:country":"SA",
    "name:und_x_variant":[
        "Etra",
        "Ithr\u0101\u2019",
        "Ithrah"
    ],
    "wof:name":"Ithrah",
    "wof:placetype":"locality"
},
  "geometry": {"coordinates":[37.62392,31.38695],"type":"Point"}
}