{
  "type": "Feature",
  "properties": {
    "gn:admin1_code":"8",
    "gn:asciiname":"Qasr Ibn `Uqayyil",
    "gn:country_code":"SA",
    "gn:dem":672,
    "gn:feature_class":"P",
    "gn:feature_code":"PPL",
    "gn:name":"Qa\u015fr Ibn \u2018Uqayyil",
    "gn:population":0,
    "gn:timezone":"Asia/Riyadh",
    "iso:country":"SA",
    "name:ara_x_preferred":[
        "\u0642\u0635\u0631 \u0627\u0628\u0646 \u0639\u0642\u064a\u0651\u0650\u0644"
    ],
    "name:und_x_variant":[
        "Qa\u015fr Ibn \u2018Uqayyil",
        "Qa\u015fr Ibn \u2018Uqayl"
    ],
    "wof:name":"Qasr Ibn `Uqayyil",
    "wof:placetype":"locality"
},
  "geometry": {"coordinates":[43.37035,25.8433],"type":"Point"}
}