{
  "type": "Feature",
  "properties": {
    "gn:admin1_code":"14.0",
    "gn:asciiname":"Ar Rabwah al `Ulya",
    "gn:country_code":"SA",
    "gn:dem":117,
    "gn:feature_class":"P",
    "gn:feature_code":"PPL",
    "gn:name":"Ar Rabwah al \u2018Uly\u0101",
    "gn:population":0,
    "gn:timezone":"Asia/Riyadh",
    "iso:country":"SA",
    "name:nno_x_preferred":[
        "Ar Rabwah al `Ulya"
    ],
    "name:und_x_variant":[
        "Ar Rabwah al \u2018Uly\u0101"
    ],
    "wof:name":"Ar Rabwah al `Ulya",
    "wof:placetype":"locality"
},
  "geometry": {"coordinates":[39.41188,21.97958],"type":"Point"}
}