{
  "type": "Feature",
  "properties": {
    "gn:admin1_code":"0",
    "gn:asciiname":"Jadmah",
    "gn:cc2":"SA",
    "gn:country_code":"SA",
    "gn:dem":617,
    "gn:feature_class":"P",
    "gn:feature_code":"PPL",
    "gn:name":"Jadmah",
    "gn:population":0,
    "gn:timezone":"Asia/Riyadh",
    "iso:country":"SA",
    "name:und_x_variant":[
        "Ghadnah",
        "Jadmah"
    ],
    "wof:name":"Jadmah",
    "wof:placetype":"locality"
},
  "geometry": {"coordinates":[41.80944,19.47167],"type":"Point"}
}