{
  "type": "Feature",
  "properties": {
    "gn:admin1_code":"14.0",
    "gn:asciiname":"Al Mu`aysim",
    "gn:country_code":"SA",
    "gn:dem":403,
    "gn:feature_class":"P",
    "gn:feature_code":"PPL",
    "gn:name":"Al Mu\u2018ay\u015fim",
    "gn:population":0,
    "gn:timezone":"Asia/Riyadh",
    "iso:country":"SA",
    "name:ara_x_preferred":[
        "\u0627\u0644\u0645\u0639\u064a\u0635\u0645"
    ],
    "name:ara_x_variant":[
        "Al Mu`aysim"
    ],
    "name:eng_x_preferred":[
        "Al Muaysim"
    ],
    "name:und_x_variant":[
        "Al Mu\u2018ay\u015fim"
    ],
    "wof:name":"Al Muaysim",
    "wof:placetype":"neighbourhood"
},
  "geometry": {"coordinates":[39.90333,21.45083],"type":"Point"}
}