{
  "type": "Feature",
  "properties": {
    "gn:admin1_code":"14.0",
    "gn:asciiname":"Al Khadra'",
    "gn:country_code":"SA",
    "gn:dem":414,
    "gn:feature_class":"P",
    "gn:feature_code":"PPL",
    "gn:name":"Al Kha\u1e11r\u0101\u2019",
    "gn:population":0,
    "gn:timezone":"Asia/Riyadh",
    "iso:country":"SA",
    "name:fas_x_preferred":[
        "\u0627\u0644\u062e\u062f\u0631\u0627\u0639"
    ],
    "name:und_x_variant":[
        "Al Kha\u1e11r\u0101\u2019"
    ],
    "wof:name":"Al Khadra'",
    "wof:placetype":"neighbourhood"
},
  "geometry": {"coordinates":[39.90472000000001,21.46778],"type":"Point"}
}