{
  "type": "Feature",
  "properties": {
    "gn:admin1_code":"0",
    "gn:asciiname":"Fuqaha'",
    "gn:country_code":"SA",
    "gn:dem":11,
    "gn:feature_class":"P",
    "gn:feature_code":"PPL",
    "gn:name":"Fuqah\u0101\u2019",
    "gn:population":0,
    "gn:timezone":"Asia/Riyadh",
    "iso:country":"SA",
    "name:ara_x_preferred":[
        "\u0641\u0642\u0647\u0627\u0621"
    ],
    "name:ara_x_variant":[
        "Fuqaha'"
    ],
    "name:eng_x_preferred":[
        "Fuqaha"
    ],
    "name:und_x_variant":[
        "Fugana",
        "Fuqah\u0101\u2019"
    ],
    "wof:name":"Fuqaha",
    "wof:placetype":"locality"
},
  "geometry": {"coordinates":[42.61667,16.91667],"type":"Point"}
}