{
  "type": "Feature",
  "properties": {
    "gn:admin1_code":"10",
    "gn:asciiname":"Al Mudarra`ah",
    "gn:country_code":"SA",
    "gn:dem":932,
    "gn:feature_class":"P",
    "gn:feature_code":"PPL",
    "gn:name":"Al Mudarra\u2018ah",
    "gn:population":0,
    "gn:timezone":"Asia/Riyadh",
    "iso:country":"SA",
    "name:und_x_variant":[
        "Al Mudarra\u2018ah"
    ],
    "wof:name":"Al Mudarra`ah",
    "wof:placetype":"locality"
},
  "geometry": {"coordinates":[43.60611,24.48833],"type":"Point"}
}