{
  "type": "Feature",
  "properties": {
    "gn:admin1_code":"10",
    "gn:asciiname":"Munifat Jalwah",
    "gn:country_code":"SA",
    "gn:dem":969,
    "gn:feature_class":"P",
    "gn:feature_code":"PPL",
    "gn:name":"Mun\u012bfat Jalwah",
    "gn:population":0,
    "gn:timezone":"Asia/Riyadh",
    "iso:country":"SA",
    "name:und_x_variant":[
        "Mun\u012bfat Jalwah"
    ],
    "wof:name":"Munifat Jalwah",
    "wof:placetype":"locality"
},
  "geometry": {"coordinates":[43.55111,24.57917],"type":"Point"}
}