{
  "type": "Feature",
  "properties": {
    "gn:population":85371,
    "iso:country":"SA",
    "name:ara_x_preferred":[
        "\u062a\u0627\u0631\u0648\u062a"
    ],
    "name:ara_x_variant":[
        "T\u0101r\u016bt"
    ],
    "name:eng_x_colloquial":[
        "Taaroet",
        "Taaroet fort",
        "Tarot",
        "Tarot fort",
        "Tarut fort"
    ],
    "name:eng_x_preferred":[
        "Tarut"
    ],
    "name:eng_x_variant":[
        "Darin Fort",
        "T\u00e5r\u00f8t",
        "T\u00e5r\u00f8t fort"
    ],
    "qs:gn_fcode":"PPL",
    "qs:gn_local":0,
    "qs:gn_namadm1":"00",
    "qs:gn_name":"T\u0101r\u016bt",
    "qs:local_max":49,
    "qs:local_sum":102,
    "qs:localhoods":5,
    "qs:name":"Tarut",
    "qs:name_adm0":"\u0627\u0644\u0633\u0639\u0648\u062f\u064a\u0629",
    "qs:name_adm1":"\u0627\u0644\u0634\u0631\u0642\u064a\u0629",
    "qs:name_adm2":"\u0627\u0644\u0642\u0637\u064a\u0641",
    "qs:name_local":"\u0627\u0644\u0642\u0637\u064a\u0641",
    "qs:photo_max":4,
    "qs:photo_sum":5,
    "qs:placetype":"Suburb",
    "qs:quad_count":2,
    "qs:woe_adm0":23424938,
    "qs:woe_adm1":2346954,
    "qs:woe_adm2":56120202,
    "qs:woe_lau":0,
    "qs:woe_local":1939673,
    "qs:woe_ver":"7.10.0",
    "wof:lang":[
        "eng"
    ],
    "wof:name":"Tarut",
    "wof:placetype":"neighbourhood",
    "wof:population":85371
},
  "geometry": {"coordinates":[50.086121,26.577229],"type":"Point"}
}