{
  "type": "Feature",
  "properties": {
    "gn:gn_country":"SA",
    "gn:gn_fcode":"PPL",
    "gn:gn_pop":5247,
    "gn:population":5247,
    "iso:country":"SA",
    "name:unk_x_variant":[
        "Mulaija"
    ],
    "qs_pg:aaroncc":"SA",
    "qs_pg:gn_country":"SA",
    "qs_pg:gn_fcode":"PPL",
    "qs_pg:gn_pop":5247,
    "qs_pg:name":"Mulayjah",
    "qs_pg:photos_9r":0,
    "qs_pg:photos_sr":0,
    "qs_pg:pop_sr":5,
    "qs_pg:qs_pg_placetype":"locality",
    "wof:name":"Mulayjah",
    "wof:placetype":"locality",
    "wof:population":5247
},
  "geometry": {"coordinates":[48.42419,27.27103],"type":"Point"}
}