{
  "type": "Feature",
  "properties": {
    "gn:admin1_code":"13",
    "gn:asciiname":"Al Kihayfiyah",
    "gn:country_code":"SA",
    "gn:dem":736,
    "gn:feature_class":"P",
    "gn:feature_code":"PPL",
    "gn:name":"Al Kihayf\u012byah",
    "gn:population":0,
    "gn:timezone":"Asia/Riyadh",
    "iso:country":"SA",
    "name:ara_x_preferred":[
        "\u0627\u0644\u0643\u0650\u0647\u064e\u064a\u0641\u0650\u064a\u0651\u064e\u0629"
    ],
    "name:und_x_variant":[
        "Al Kuhayf\u012byah",
        "Al Kihayf\u012byah"
    ],
    "wof:name":"Al Kihayfiyah",
    "wof:placetype":"locality"
},
  "geometry": {"coordinates":[42.98739000000001,27.19923],"type":"Point"}
}