{
  "type": "Feature",
  "properties": {
    "gn:admin1_code":"17",
    "gn:asciiname":"Hamdah",
    "gn:country_code":"SA",
    "gn:dem":68,
    "gn:feature_class":"P",
    "gn:feature_code":"PPL",
    "gn:name":"\u1e28am\u1e11ah",
    "gn:population":0,
    "gn:timezone":"Asia/Riyadh",
    "iso:country":"SA",
    "name:nno_x_preferred":[
        "Hamdah"
    ],
    "name:und_x_variant":[
        "Al \u1e28\u0101midah",
        "\u1e28am\u1e11ah"
    ],
    "wof:name":"Hamdah",
    "wof:placetype":"locality"
},
  "geometry": {"coordinates":[42.92216,16.76195],"type":"Point"}
}