{
  "type": "Feature",
  "properties": {
    "gn:admin1_code":"0",
    "gn:asciiname":"Al Khalaf",
    "gn:country_code":"SA",
    "gn:dem":2416,
    "gn:feature_class":"P",
    "gn:feature_code":"PPL",
    "gn:name":"\u0100l Khalaf",
    "gn:population":0,
    "gn:timezone":"Asia/Riyadh",
    "iso:country":"SA",
    "name:und_x_variant":[
        "\u0100l Khalaf"
    ],
    "wof:name":"Al Khalaf",
    "wof:placetype":"locality"
},
  "geometry": {"coordinates":[43.12725,17.95237999999999],"type":"Point"}
}