{
  "type": "Feature",
  "properties": {
    "gn:country":"SA",
    "gn:fcode":"PPL",
    "gn:population":9218,
    "iso:country":"SA",
    "name:und_x_variant":[
        "Mendak"
    ],
    "qs_pg:aaroncc":"SA",
    "qs_pg:gn_country":"SA",
    "qs_pg:gn_fcode":"PPL",
    "qs_pg:gn_pop":9218,
    "qs_pg:name":"Al Mindak",
    "qs_pg:photos_9r":0,
    "qs_pg:photos_sr":0,
    "qs_pg:pop_sr":5,
    "qs_pg:qs_pg_placetype":"locality",
    "wof:name":"Al Mindak",
    "wof:placetype":"locality",
    "wof:population":9218
},
  "geometry": {"coordinates":[41.28337,20.1588],"type":"Point"}
}