{
  "type": "Feature",
  "properties": {
    "gn:admin1_code":"14",
    "gn:asciiname":"Al Waht",
    "gn:country_code":"SA",
    "gn:dem":1757,
    "gn:feature_class":"P",
    "gn:feature_code":"PPL",
    "gn:name":"Al Wah\u0163",
    "gn:population":0,
    "gn:timezone":"Asia/Riyadh",
    "iso:country":"SA",
    "name:ell_x_preferred":[
        "\u0391\u03bb \u039f\u03c5\u03ac\u03c7\u03c4"
    ],
    "name:fas_x_preferred":[
        "\u0627\u0644\u0648\u062d\u062a"
    ],
    "name:nno_x_preferred":[
        "Al Waht"
    ],
    "name:und_x_variant":[
        "Al Waha\u0163",
        "Al Wah\u0163"
    ],
    "wof:name":"Al Waht",
    "wof:placetype":"locality"
},
  "geometry": {"coordinates":[40.34247,21.23506],"type":"Point"}
}