{
  "type": "Feature",
  "properties": {
    "gn:admin1_code":"5.0",
    "gn:asciiname":"Diraybis",
    "gn:country_code":"SA",
    "gn:dem":198,
    "gn:feature_class":"P",
    "gn:feature_code":"PPL",
    "gn:name":"Diraybis",
    "gn:population":0,
    "gn:timezone":"Asia/Riyadh",
    "iso:country":"SA",
    "wof:name":"Diraybis",
    "wof:placetype":"locality"
},
  "geometry": {"coordinates":[39.22307,23.36498],"type":"Point"}
}