{
  "type": "Feature",
  "properties": {
    "gn:admin1_code":"8",
    "gn:asciiname":"Jadid",
    "gn:country_code":"SA",
    "gn:dem":822,
    "gn:feature_class":"P",
    "gn:feature_code":"PPL",
    "gn:name":"Jad\u012bd",
    "gn:population":0,
    "gn:timezone":"Asia/Riyadh",
    "iso:country":"SA",
    "name:ara_x_preferred":[
        "\u062c\u062f\u064a\u062f"
    ],
    "name:azb_x_preferred":[
        "\u062c\u062f\u06cc\u062f\u0686\u06cc\u0644\u06cc\u06a9"
    ],
    "name:aze_x_preferred":[
        "C\u0259didizm"
    ],
    "name:bak_x_preferred":[
        "\u0419\u04d9\u0434\u0438\u0442\u0441\u0435\u043b\u0435\u043a"
    ],
    "name:cat_x_preferred":[
        "Jadidisme"
    ],
    "name:crh_x_preferred":[
        "Usul-i Cedid"
    ],
    "name:deu_x_preferred":[
        "Dschadidismus"
    ],
    "name:fas_x_preferred":[
        "\u062c\u062f\u06cc\u062f\u06cc\u0632\u0645"
    ],
    "name:fra_x_preferred":[
        "Jadidisme"
    ],
    "name:hye_x_preferred":[
        "\u054b\u0561\u0564\u056b\u0564\u0561\u056f\u0561\u0576\u0578\u0582\u0569\u0575\u0578\u0582\u0576"
    ],
    "name:ita_x_preferred":[
        "Jadid"
    ],
    "name:jpn_x_preferred":[
        "\u30b8\u30e3\u30c7\u30a3\u30fc\u30c9\u904b\u52d5"
    ],
    "name:kaz_x_preferred":[
        "\u0416\u04d9\u0434\u0438\u0442\u0448\u0456\u043b\u0456\u043a"
    ],
    "name:kir_x_preferred":[
        "\u0416\u0430\u0434\u0438\u0434 \u043c\u0435\u043a\u0442\u0435\u043f\u0442\u0435\u0440\u0438"
    ],
    "name:nld_x_preferred":[
        "Jadid"
    ],
    "name:pol_x_preferred":[
        "D\u017cadidyzm"
    ],
    "name:rus_x_preferred":[
        "\u0414\u0436\u0430\u0434\u0438\u0434\u0438\u0437\u043c"
    ],
    "name:spa_x_preferred":[
        "Jadid"
    ],
    "name:swe_x_preferred":[
        "Jadid"
    ],
    "name:tat_x_preferred":[
        "C\u0259dit\u00e7elek"
    ],
    "name:tgk_x_preferred":[
        "\u04b6\u0430\u0434\u0438\u0434\u0438\u044f"
    ],
    "name:tur_x_preferred":[
        "Cedit\u00e7ilik"
    ],
    "name:ukr_x_preferred":[
        "\u0414\u0436\u0430\u0434\u0438\u0434\u0438\u0437\u043c"
    ],
    "name:und_x_variant":[
        "Jad\u012bd"
    ],
    "name:uzb_x_preferred":[
        "Jadidchilik"
    ],
    "name:zho_x_preferred":[
        "\u624e\u5409\u5fb7"
    ],
    "wof:name":"Jadid",
    "wof:placetype":"locality"
},
  "geometry": {"coordinates":[42.20233,25.99979],"type":"Point"}
}