{
  "type": "Feature",
  "properties": {
    "gn:admin1_code":"8",
    "gn:asciiname":"Jadid",
    "gn:country_code":"SA",
    "gn:dem":822,
    "gn:feature_class":"P",
    "gn:feature_code":"PPL",
    "gn:name":"Jad\u012bd",
    "gn:population":0,
    "gn:timezone":"Asia/Riyadh",
    "iso:country":"SA",
    "name:ara_x_preferred":[
        "\u062c\u062f\u064a\u062f"
    ],
    "name:und_x_variant":[
        "Jad\u012bd"
    ],
    "wof:name":"Jadid",
    "wof:placetype":"locality"
},
  "geometry": {"coordinates":[42.20233,25.99979],"type":"Point"}
}