{
  "type": "Feature",
  "properties": {
    "iso:country":"SA",
    "name:ara_x_preferred":[
        "\u0627\u0628\u0627 \u0627\u0644\u0633\u0639\u0648\u062f"
    ],
    "name:eng_x_preferred":[
        "Aba Al Saud"
    ],
    "qs:gn_pop":0,
    "qs:name":"\u0627\u0628\u0627 \u0627\u0644\u0633\u0639\u0648\u062f",
    "qs:name_adm0":"\u0627\u0644\u0633\u0639\u0648\u062f\u064a\u0629",
    "qs:name_adm1":"\u0646\u062c\u0631\u0627\u0646",
    "qs:photos":60,
    "qs:photos_1k":12,
    "qs:photos_9k":1,
    "qs:photos_9r":3,
    "qs:photos_all":147,
    "qs:photos_sr":2,
    "qs:placetype":"Town",
    "qs:pop_sr":"0",
    "qs:woe_adm0":23424938,
    "wof:name":"Aba Al Saud",
    "wof:placetype":"locality"
},
  "geometry": {"coordinates":[44.132659,17.490552],"type":"Point"}
}