{
  "type": "Feature",
  "properties": {
    "gn:admin1_code":"10.0",
    "gn:asciiname":"Al Quway`",
    "gn:country_code":"SA",
    "gn:dem":587,
    "gn:feature_class":"P",
    "gn:feature_code":"PPL",
    "gn:name":"Al Quway\u2018",
    "gn:population":0,
    "gn:timezone":"Asia/Riyadh",
    "iso:country":"SA",
    "name:und_x_variant":[
        "Al Quway\u2018"
    ],
    "wof:name":"Al Quway`",
    "wof:placetype":"locality"
},
  "geometry": {"coordinates":[46.81756,23.46257],"type":"Point"}
}