{
  "type": "Feature",
  "properties": {
    "gn:admin1_code":"13",
    "gn:asciiname":"Al Jithyathah",
    "gn:country_code":"SA",
    "gn:dem":734,
    "gn:feature_class":"P",
    "gn:feature_code":"PPL",
    "gn:name":"Al Jithy\u0101thah",
    "gn:population":0,
    "gn:timezone":"Asia/Riyadh",
    "iso:country":"SA",
    "name:ara_x_preferred":[
        "\u0627\u0644\u062c\u0650\u062b\u064a\u0627\u062b\u0629"
    ],
    "name:und_x_variant":[
        "Al Jithy\u0101thah"
    ],
    "wof:name":"Al Jithyathah",
    "wof:placetype":"locality"
},
  "geometry": {"coordinates":[42.62773,27.71423],"type":"Point"}
}