{
  "type": "Feature",
  "properties": {
    "gn:admin1_code":"14.0",
    "gn:asciiname":"Al Muqr",
    "gn:country_code":"SA",
    "gn:dem":104,
    "gn:feature_class":"P",
    "gn:feature_code":"PPL",
    "gn:name":"Al Muqr",
    "gn:population":0,
    "gn:timezone":"Asia/Riyadh",
    "iso:country":"SA",
    "wof:name":"Al Muqr",
    "wof:placetype":"locality"
},
  "geometry": {"coordinates":[39.37648,21.99858],"type":"Point"}
}