{
  "type": "Feature",
  "properties": {
    "gn:admin1_code":"0",
    "gn:asciiname":"Al Basam",
    "gn:country_code":"SA",
    "gn:dem":2451,
    "gn:feature_class":"P",
    "gn:feature_code":"PPL",
    "gn:name":"Al Bas\u0101m",
    "gn:population":0,
    "gn:timezone":"Asia/Riyadh",
    "iso:country":"SA",
    "name:und_x_variant":[
        "Al Bas\u0101m"
    ],
    "wof:name":"Al Basam",
    "wof:placetype":"locality"
},
  "geometry": {"coordinates":[43.1864,18.05678],"type":"Point"}
}