{
  "type": "Feature",
  "properties": {
    "gn:admin1_code":"0",
    "gn:asciiname":"Tindahah",
    "gn:country_code":"SA",
    "gn:dem":2027,
    "gn:feature_class":"P",
    "gn:feature_code":"PPL",
    "gn:name":"Tinda\u1e29ah",
    "gn:population":0,
    "gn:timezone":"Asia/Riyadh",
    "iso:country":"SA",
    "name:und_x_variant":[
        "Tindaha",
        "Tinda\u1e29ah"
    ],
    "wof:name":"Tindahah",
    "wof:placetype":"locality"
},
  "geometry": {"coordinates":[42.85983,18.31257],"type":"Point"}
}