{
  "type": "Feature",
  "properties": {
    "gn:admin1_code":"13",
    "gn:asciiname":"Al Jubb",
    "gn:country_code":"SA",
    "gn:dem":1027,
    "gn:feature_class":"P",
    "gn:feature_code":"PPL",
    "gn:name":"Al Jubb",
    "gn:population":0,
    "gn:timezone":"Asia/Riyadh",
    "iso:country":"SA",
    "name:und_x_variant":[
        "Jub",
        "Al Jubb"
    ],
    "wof:name":"Al Jubb",
    "wof:placetype":"locality"
},
  "geometry": {"coordinates":[42.28333,27.18333],"type":"Point"}
}