{
  "type": "Feature",
  "properties": {
    "gn:admin1_code":"0",
    "gn:asciiname":"Bani Malik",
    "gn:country_code":"SA",
    "gn:dem":2042,
    "gn:feature_class":"P",
    "gn:feature_code":"PPL",
    "gn:name":"Ban\u012b M\u0101lik",
    "gn:population":0,
    "gn:timezone":"Asia/Riyadh",
    "iso:country":"SA",
    "name:nno_x_preferred":[
        "Bani Malik"
    ],
    "name:und_x_variant":[
        "Ban\u012b M\u0101lik"
    ],
    "wof:name":"Bani Malik",
    "wof:placetype":"locality"
},
  "geometry": {"coordinates":[42.56316,18.38767],"type":"Point"}
}