{
  "type": "Feature",
  "properties": {
    "gn:admin1_code":"14.0",
    "gn:asciiname":"alabwa",
    "gn:country_code":"SA",
    "gn:dem":78,
    "gn:feature_class":"P",
    "gn:feature_code":"PPL",
    "gn:name":"alabwa",
    "gn:population":0,
    "gn:timezone":"Asia/Riyadh",
    "iso:country":"SA",
    "wof:name":"alabwa",
    "wof:placetype":"locality"
},
  "geometry": {"coordinates":[39.10378,23.11636],"type":"Point"}
}