{
  "type": "Feature",
  "properties": {
    "gn:admin1_code":"10",
    "gn:asciiname":"As Sumayrah",
    "gn:country_code":"SA",
    "gn:dem":1000,
    "gn:feature_class":"P",
    "gn:feature_code":"PPL",
    "gn:name":"As Sumayrah",
    "gn:population":0,
    "gn:timezone":"Asia/Riyadh",
    "iso:country":"SA",
    "wof:name":"As Sumayrah",
    "wof:placetype":"locality"
},
  "geometry": {"coordinates":[44.42444,24.38361],"type":"Point"}
}