{
  "type": "Feature",
  "properties": {
    "gn:admin1_code":"0",
    "gn:asciiname":"Bil Hasbil",
    "gn:country_code":"SA",
    "gn:dem":1854,
    "gn:feature_class":"P",
    "gn:feature_code":"PPL",
    "gn:name":"Bil Hasbil",
    "gn:population":0,
    "gn:timezone":"Asia/Riyadh",
    "iso:country":"SA",
    "wof:name":"Bil Hasbil",
    "wof:placetype":"locality"
},
  "geometry": {"coordinates":[42.72667,18.63083],"type":"Point"}
}