{
  "type": "Feature",
  "properties": {
    "gn:admin1_code":"5.0",
    "gn:asciiname":"As Sulhaniyah",
    "gn:country_code":"SA",
    "gn:dem":952,
    "gn:feature_class":"P",
    "gn:feature_code":"PPL",
    "gn:name":"A\u015f \u015eul\u1e29an\u012byah",
    "gn:population":0,
    "gn:timezone":"Asia/Riyadh",
    "iso:country":"SA",
    "name:und_x_variant":[
        "A\u015f \u015eul\u1e29an\u012byah"
    ],
    "wof:name":"As Sulhaniyah",
    "wof:placetype":"locality"
},
  "geometry": {"coordinates":[40.48596,22.8757],"type":"Point"}
}