{
  "type": "Feature",
  "properties": {
    "gn:admin1_code":"14",
    "gn:asciiname":"Anda",
    "gn:country_code":"SA",
    "gn:dem":-9999,
    "gn:feature_class":"P",
    "gn:feature_code":"PPL",
    "gn:name":"Anda",
    "gn:population":0,
    "gn:timezone":"Asia/Riyadh",
    "iso:country":"SA",
    "name:ceb_x_preferred":[
        "Anda"
    ],
    "name:dan_x_preferred":[
        "Anda"
    ],
    "name:deu_x_preferred":[
        "Anda"
    ],
    "name:eus_x_preferred":[
        "Anda"
    ],
    "name:fra_x_preferred":[
        "Anda"
    ],
    "name:heb_x_preferred":[
        "\u05d0\u05e0\u05d3\u05d4"
    ],
    "name:hun_x_preferred":[
        "Anda"
    ],
    "name:ita_x_preferred":[
        "Anda"
    ],
    "name:mlg_x_preferred":[
        "Anda"
    ],
    "name:nld_x_preferred":[
        "Anda"
    ],
    "name:nno_x_preferred":[
        "Anda"
    ],
    "name:nor_x_preferred":[
        "Anda"
    ],
    "name:slv_x_preferred":[
        "Anda"
    ],
    "name:spa_x_preferred":[
        "Anda"
    ],
    "name:swe_x_preferred":[
        "Anda"
    ],
    "name:und_x_variant":[
        "Andah"
    ],
    "name:war_x_preferred":[
        "Anda"
    ],
    "wof:name":"Anda",
    "wof:placetype":"locality"
},
  "geometry": {"coordinates":[41.23333,18.81667],"type":"Point"}
}