{
  "type": "Feature",
  "properties": {
    "gn:admin1_code":"14",
    "gn:asciiname":"Anda",
    "gn:country_code":"SA",
    "gn:dem":-9999,
    "gn:feature_class":"P",
    "gn:feature_code":"PPL",
    "gn:name":"Anda",
    "gn:population":0,
    "gn:timezone":"Asia/Riyadh",
    "iso:country":"SA",
    "name:und_x_variant":[
        "Andah",
        "Anda"
    ],
    "wof:name":"Anda",
    "wof:placetype":"locality"
},
  "geometry": {"coordinates":[41.23333,18.81667],"type":"Point"}
}