{
  "type": "Feature",
  "properties": {
    "gn:admin1_code":"10",
    "gn:asciiname":"Mushrifah",
    "gn:country_code":"SA",
    "gn:dem":723,
    "gn:feature_class":"P",
    "gn:feature_code":"PPL",
    "gn:name":"Mushrifah",
    "gn:population":0,
    "gn:timezone":"Asia/Riyadh",
    "iso:country":"SA",
    "name:ara_x_preferred":[
        "\u0645\u0634\u0631\u0641\u0629"
    ],
    "wof:name":"Mushrifah",
    "wof:placetype":"locality"
},
  "geometry": {"coordinates":[44.63708,25.15632],"type":"Point"}
}