{
  "type": "Feature",
  "properties": {
    "gn:admin1_code":"14.0",
    "gn:asciiname":"Al Kulakhiyah",
    "gn:country_code":"SA",
    "gn:dem":1384,
    "gn:feature_class":"P",
    "gn:feature_code":"PPL",
    "gn:name":"Al Kul\u0101kh\u012byah",
    "gn:population":0,
    "gn:timezone":"Asia/Riyadh",
    "iso:country":"SA",
    "name:und_x_variant":[
        "Al Kul\u0101kh\u012byah"
    ],
    "wof:name":"Al Kulakhiyah",
    "wof:placetype":"locality"
},
  "geometry": {"coordinates":[40.80444,21.31806],"type":"Point"}
}