{
  "type": "Feature",
  "properties": {
    "gn:admin1_code":"8",
    "gn:asciiname":"Ar Rudaymah",
    "gn:country_code":"SA",
    "gn:dem":694,
    "gn:feature_class":"P",
    "gn:feature_code":"PPL",
    "gn:name":"Ar Ru\u1e11aymah",
    "gn:population":0,
    "gn:timezone":"Asia/Riyadh",
    "iso:country":"SA",
    "name:ara_x_preferred":[
        "\u0627\u0644\u0631\u0651\u064f\u0636\u064a\u0645\u0629"
    ],
    "name:und_x_variant":[
        "Ar Ruway\u1e11\u0101t",
        "Ra\u1e11aymah",
        "Radhaima",
        "Ru\u1e11aymah",
        "Ar Ru\u1e11aymah"
    ],
    "wof:name":"Ar Rudaymah",
    "wof:placetype":"locality"
},
  "geometry": {"coordinates":[43.37505,25.77647],"type":"Point"}
}