{
  "type": "Feature",
  "properties": {
    "gn:admin1_code":"13",
    "gn:asciiname":"Al Waqid",
    "gn:country_code":"SA",
    "gn:dem":963,
    "gn:feature_class":"P",
    "gn:feature_code":"PPL",
    "gn:name":"Al Waq\u012bd",
    "gn:population":0,
    "gn:timezone":"Asia/Riyadh",
    "iso:country":"SA",
    "name:und_x_variant":[
        "Al Wuq\u012bd",
        "Al-Wu\u017e\u00eed",
        "Al Waq\u012bd"
    ],
    "wof:name":"Al Waqid",
    "wof:placetype":"neighbourhood"
},
  "geometry": {"coordinates":[41.68333,27.65],"type":"Point"}
}