{
  "type": "Feature",
  "properties": {
    "gn:admin1_code":"0",
    "gn:asciiname":"Al Athamah",
    "gn:country_code":"SA",
    "gn:dem":2279,
    "gn:feature_class":"P",
    "gn:feature_code":"PPL",
    "gn:name":"Al Athamah",
    "gn:population":0,
    "gn:timezone":"Asia/Riyadh",
    "iso:country":"SA",
    "wof:name":"Al Athamah",
    "wof:placetype":"locality"
},
  "geometry": {"coordinates":[41.45,20.06667],"type":"Point"}
}