{
  "type": "Feature",
  "properties": {
    "gn:admin1_code":"0",
    "gn:asciiname":"Bilad Bani `Amr",
    "gn:country_code":"SA",
    "gn:dem":2342,
    "gn:feature_class":"P",
    "gn:feature_code":"PPL",
    "gn:name":"Bil\u0101d Ban\u012b \u2018Amr",
    "gn:population":0,
    "gn:timezone":"Asia/Riyadh",
    "iso:country":"SA",
    "name:ara_x_preferred":[
        "\u0628\u0644\u0627\u062f \u0628\u0646\u064a \u0639\u0645\u0631\u0648"
    ],
    "name:und_x_variant":[
        "Bilad Beni \u2018Amr",
        "Bil\u0101d Ban\u012b \u2018Amr"
    ],
    "wof:name":"Bilad Bani `Amr",
    "wof:placetype":"locality"
},
  "geometry": {"coordinates":[42.13654,19.16256],"type":"Point"}
}