{
  "type": "Feature",
  "properties": {
    "gn:admin1_code":"20",
    "gn:asciiname":"Al Bayda'",
    "gn:country_code":"SA",
    "gn:dem":593,
    "gn:feature_class":"P",
    "gn:feature_code":"PPLL",
    "gn:name":"Al Bay\u1e11\u0101\u2019",
    "gn:population":0,
    "gn:timezone":"Asia/Riyadh",
    "iso:country":"SA",
    "name:ceb_x_preferred":[
        "Al Bayda'"
    ],
    "name:nld_x_preferred":[
        "Al Bayda'"
    ],
    "name:sco_x_preferred":[
        "Al Bayda'"
    ],
    "name:swe_x_preferred":[
        "Al Bayda'"
    ],
    "name:und_x_variant":[
        "Al Bay\u1e11\u0101\u2019"
    ],
    "wof:name":"Al Bayda'",
    "wof:placetype":"locality"
},
  "geometry": {"coordinates":[40.17111,30.02472],"type":"Point"}
}