{
  "type": "Feature",
  "properties": {
    "gn:admin1_code":"0",
    "gn:asciiname":"Hadram",
    "gn:country_code":"SA",
    "gn:dem":1954,
    "gn:feature_class":"P",
    "gn:feature_code":"PPL",
    "gn:name":"\u1e28a\u1e11ram",
    "gn:population":0,
    "gn:timezone":"Asia/Riyadh",
    "iso:country":"SA",
    "name:und_x_variant":[
        "\u1e28a\u1e11ram"
    ],
    "wof:name":"Hadram",
    "wof:placetype":"locality"
},
  "geometry": {"coordinates":[41.23333,20.21667],"type":"Point"}
}