{
  "type": "Feature",
  "properties": {
    "gn:admin1_code":"13",
    "gn:asciiname":"Al Jithamiyah",
    "gn:country_code":"SA",
    "gn:dem":925,
    "gn:feature_class":"P",
    "gn:feature_code":"PPL",
    "gn:name":"Al Jith\u0101m\u012byah",
    "gn:population":0,
    "gn:timezone":"Asia/Riyadh",
    "iso:country":"SA",
    "name:ara_x_preferred":[
        "\u0627\u0644\u062c\u062b\u0627\u0645\u064a\u0629"
    ],
    "name:und_x_variant":[
        "Judh\u0101m\u012byah",
        "Al-Ge\u1e6d\u00e2mijje",
        "Jirthamiya",
        "Al Judh\u0101m\u012byah",
        "Jadhamiyah",
        "Al Jith\u0101m\u012byah"
    ],
    "wof:name":"Al Jithamiyah",
    "wof:placetype":"neighbourhood"
},
  "geometry": {"coordinates":[41.72523,27.67816],"type":"Point"}
}