{
  "type": "Feature",
  "properties": {
    "gn:admin1_code":"6",
    "gn:asciiname":"`Uray`irah",
    "gn:country_code":"SA",
    "gn:dem":147,
    "gn:feature_class":"P",
    "gn:feature_code":"PPL",
    "gn:name":"\u2018Uray\u2018irah",
    "gn:population":0,
    "gn:timezone":"Asia/Riyadh",
    "iso:country":"SA",
    "name:ara_x_preferred":[
        "\u0639\u0631\u064a\u0639\u0631\u0629"
    ],
    "name:und_x_variant":[
        "Arai\u2018ra",
        "\u2018Uway\u2018irah",
        "\u2018Uray\u2018irah"
    ],
    "wof:name":"`Uray`irah",
    "wof:placetype":"locality"
},
  "geometry": {"coordinates":[48.87772,25.97323],"type":"Point"}
}