{
  "type": "Feature",
  "properties": {
    "gn:admin1_code":"17",
    "gn:asciiname":"Al `Ushwah",
    "gn:country_code":"SA",
    "gn:dem":26,
    "gn:feature_class":"P",
    "gn:feature_code":"PPL",
    "gn:name":"Al \u2018Ushwah",
    "gn:population":0,
    "gn:timezone":"Asia/Riyadh",
    "iso:country":"SA",
    "name:und_x_variant":[
        "\u2018Ushwah",
        "Ushwa",
        "Al \u2018Ushwah"
    ],
    "wof:name":"Al `Ushwah",
    "wof:placetype":"locality"
},
  "geometry": {"coordinates":[42.65444,16.96583],"type":"Point"}
}