{
  "type": "Feature",
  "properties": {
    "gn:admin1_code":"15",
    "gn:asciiname":"Ibn `A'ish",
    "gn:country_code":"SA",
    "gn:dem":429,
    "gn:feature_class":"P",
    "gn:feature_code":"PPLL",
    "gn:name":"Ibn \u2018\u0100\u2019ish",
    "gn:population":0,
    "gn:timezone":"Asia/Riyadh",
    "iso:country":"SA",
    "name:ara_x_preferred":[
        "Ibn \u2018\u0100\u2019ish"
    ],
    "name:ara_x_variant":[
        "\u0625\u0628\u0646 \u0639\u0627\u0626\u0634"
    ],
    "wof:name":"Ibn `A'ish",
    "wof:placetype":"locality"
},
  "geometry": {"coordinates":[42.35424,30.3072],"type":"Point"}
}