{
  "type": "Feature",
  "properties": {
    "gn:admin1_code":"13",
    "gn:asciiname":"Az Zuluzal",
    "gn:country_code":"SA",
    "gn:dem":1240,
    "gn:feature_class":"P",
    "gn:feature_code":"PPL",
    "gn:name":"Az\u0327 Z\u0327uluz\u0327al",
    "gn:population":0,
    "gn:timezone":"Asia/Riyadh",
    "iso:country":"SA",
    "name:ara_x_preferred":[
        "\u0627\u0644\u0638\u0644\u0638\u0644"
    ],
    "name:und_x_variant":[
        "Az\u0327 Z\u0327uluz\u0327al"
    ],
    "wof:name":"Az Zuluzal",
    "wof:placetype":"locality"
},
  "geometry": {"coordinates":[41.37633,27.33407],"type":"Point"}
}