{
  "type": "Feature",
  "properties": {
    "gn:admin1_code":"10",
    "gn:asciiname":"Bijadiyah",
    "gn:country_code":"SA",
    "gn:dem":913,
    "gn:feature_class":"P",
    "gn:feature_code":"PPL",
    "gn:name":"Bij\u0101d\u012byah",
    "gn:population":0,
    "gn:timezone":"Asia/Riyadh",
    "iso:country":"SA",
    "name:und_x_variant":[
        "Bij\u0101d\u012byah"
    ],
    "wof:name":"Bijadiyah",
    "wof:placetype":"locality"
},
  "geometry": {"coordinates":[43.74667,24.3025],"type":"Point"}
}