{
  "type": "Feature",
  "properties": {
    "gn:admin1_code":"0",
    "gn:asciiname":"Murabba'",
    "gn:country_code":"SA",
    "gn:dem":386,
    "gn:feature_class":"P",
    "gn:feature_code":"PPL",
    "gn:name":"Murabba\u2019",
    "gn:population":0,
    "gn:timezone":"Asia/Riyadh",
    "iso:country":"SA",
    "name:und_x_variant":[
        "Murabba\u2019"
    ],
    "wof:name":"Murabba'",
    "wof:placetype":"locality"
},
  "geometry": {"coordinates":[38.35416,25.38623],"type":"Point"}
}