{
  "type": "Feature",
  "properties": {
    "gn:admin1_code":"13",
    "gn:asciiname":"As Surayhah",
    "gn:country_code":"SA",
    "gn:dem":931,
    "gn:feature_class":"P",
    "gn:feature_code":"PPL",
    "gn:name":"As Suray\u1e29ah",
    "gn:population":0,
    "gn:timezone":"Asia/Riyadh",
    "iso:country":"SA",
    "name:ara_x_preferred":[
        "\u0627\u0644\u0633\u0631\u064a\u062d\u0629"
    ],
    "name:und_x_variant":[
        "As Suray\u1e29ah"
    ],
    "wof:name":"As Surayhah",
    "wof:placetype":"locality"
},
  "geometry": {"coordinates":[41.45175,27.73857000000001],"type":"Point"}
}