{
  "type": "Feature",
  "properties": {
    "gn:admin1_code":"10",
    "gn:asciiname":"Al Ghatghat",
    "gn:cc2":"SA",
    "gn:country_code":"SA",
    "gn:dem":627,
    "gn:feature_class":"P",
    "gn:feature_code":"PPLL",
    "gn:name":"Al Gha\u0163gha\u0163",
    "gn:population":0,
    "gn:timezone":"Asia/Riyadh",
    "iso:country":"SA",
    "name:und_x_variant":[
        "Ghat Ghat"
    ],
    "wof:name":"Al Ghatghat",
    "wof:placetype":"locality"
},
  "geometry": {"coordinates":[46.24991,24.47649],"type":"Point"}
}