{
  "type": "Feature",
  "properties": {
    "gn:admin1_code":"0",
    "gn:asciiname":"Al `Awsajiyah",
    "gn:country_code":"SA",
    "gn:dem":1023,
    "gn:feature_class":"P",
    "gn:feature_code":"PPL",
    "gn:name":"Al \u2018Awsaj\u012byah",
    "gn:population":0,
    "gn:timezone":"Asia/Riyadh",
    "iso:country":"SA",
    "name:und_x_variant":[
        "Aushaziya",
        "Al \u2018Awshaz\u012byah",
        "Al \u2018Awsaj\u012byah"
    ],
    "wof:name":"Al `Awsajiyah",
    "wof:placetype":"locality"
},
  "geometry": {"coordinates":[41.68333,26.81667],"type":"Point"}
}