{
  "type": "Feature",
  "properties": {
    "gn:admin1_code":"0",
    "gn:asciiname":"Al Dahrah",
    "gn:country_code":"SA",
    "gn:dem":2342,
    "gn:feature_class":"P",
    "gn:feature_code":"PPL",
    "gn:name":"\u0100l \u1e10ahrah",
    "gn:population":0,
    "gn:timezone":"Asia/Riyadh",
    "iso:country":"SA",
    "name:und_x_variant":[
        "\u0100l \u1e10ahrah"
    ],
    "wof:name":"Al Dahrah",
    "wof:placetype":"locality"
},
  "geometry": {"coordinates":[43.21637,17.94347999999999],"type":"Point"}
}