{
  "type": "Feature",
  "properties": {
    "gn:admin1_code":"8",
    "gn:asciiname":"Al Jardhawiyah",
    "gn:country_code":"SA",
    "gn:dem":834,
    "gn:feature_class":"P",
    "gn:feature_code":"PPL",
    "gn:name":"Al Jardh\u0101w\u012byah",
    "gn:population":0,
    "gn:timezone":"Asia/Riyadh",
    "iso:country":"SA",
    "name:ara_x_preferred":[
        "\u0627\u0644\u062c\u0631\u0630\u0627\u0648\u064a\u0651\u064e\u0629"
    ],
    "name:und_x_variant":[
        "Jird\u0101w\u012bjah",
        "Al Jurdh\u0101w\u012byah",
        "Jard\u0101w\u012byah",
        "Al Jardh\u0101w\u012byah"
    ],
    "wof:name":"Al Jardhawiyah",
    "wof:placetype":"locality"
},
  "geometry": {"coordinates":[42.73024,25.38666],"type":"Point"}
}