{
  "type": "Feature",
  "properties": {
    "gn:admin1_code":"0",
    "gn:asciiname":"Al Jafa",
    "gn:country_code":"SA",
    "gn:dem":1426,
    "gn:feature_class":"P",
    "gn:feature_code":"PPL",
    "gn:name":"Al Jaf\u0101",
    "gn:population":0,
    "gn:timezone":"Asia/Riyadh",
    "iso:country":"SA",
    "name:und_x_variant":[
        "Al Jaf\u0101"
    ],
    "wof:name":"Al Jafa",
    "wof:placetype":"locality"
},
  "geometry": {"coordinates":[43.917,17.76986],"type":"Point"}
}