{
  "type": "Feature",
  "properties": {
    "iso:country":"SA",
    "name:ara_x_preferred":[
        "\u0627\u0644\u0645\u0648\u064a\u0632\u0644\u0647"
    ],
    "name:eng_x_preferred":[
        "Al M'aizilah"
    ],
    "name:eng_x_variant":[
        "Al Muayzilah",
        "Al M'aizilah"
    ],
    "qs:gn_adm0_cc":"SA",
    "qs:gn_local":108410,
    "qs:gn_nam_loc":"\u0627\u0644\u0631\u064a\u0627\u0636, \u0627\u0644\u0631\u064a\u0627\u0636, \u0627\u0644\u0631\u064a\u0627\u0636, SA",
    "qs:gn_namadm1":"10",
    "qs:local_max":655,
    "qs:local_sum":5321,
    "qs:localhoods":54,
    "qs:name":"\u0627\u0644\u0645\u0648\u064a\u0632\u0644\u0647",
    "qs:name_adm0":"\u0627\u0644\u0633\u0639\u0648\u062f\u064a\u0629",
    "qs:name_adm1":"\u0627\u0644\u0631\u064a\u0627\u0636",
    "qs:name_adm2":"\u0627\u0644\u0631\u064a\u0627\u0636",
    "qs:name_en":"Al M'aizilah",
    "qs:name_local":"\u0627\u0644\u0631\u064a\u0627\u0636",
    "qs:photo_max":205,
    "qs:photo_sum":321,
    "qs:placetype":"Suburb",
    "qs:quad_count":8,
    "qs:woe_adm0":23424938,
    "qs:woe_adm1":2346951,
    "qs:woe_adm2":56120189,
    "qs:woe_lau":0,
    "qs:woe_local":1939753,
    "qs:woe_ver":"7.10.0",
    "wof:lang":[
        "ara"
    ],
    "wof:name":"\u0627\u0644\u0645\u0648\u064a\u0632\u0644\u0647",
    "wof:placetype":"neighbourhood"
},
  "geometry": {"coordinates":[46.833091,24.777024],"type":"Point"}
}