{
  "type": "Feature",
  "properties": {
    "gn:admin1_code":"0",
    "gn:asciiname":"Harf",
    "gn:country_code":"SA",
    "gn:dem":930,
    "gn:feature_class":"P",
    "gn:feature_code":"PPL",
    "gn:name":"\u1e28arf",
    "gn:population":0,
    "gn:timezone":"Asia/Riyadh",
    "iso:country":"SA",
    "name:und_x_variant":[
        "\u1e28arf"
    ],
    "wof:name":"Harf",
    "wof:placetype":"locality"
},
  "geometry": {"coordinates":[42.79634,21.25045],"type":"Point"}
}