{
  "type": "Feature",
  "properties": {
    "gn:admin1_code":"5.0",
    "gn:asciiname":"Al Hijriyah",
    "gn:country_code":"SA",
    "gn:dem":871,
    "gn:feature_class":"P",
    "gn:feature_code":"PPL",
    "gn:name":"Al Hijr\u012byah",
    "gn:population":0,
    "gn:timezone":"Asia/Riyadh",
    "iso:country":"SA",
    "name:und_x_variant":[
        "Al Hijr\u012byah"
    ],
    "wof:name":"Al Hijriyah",
    "wof:placetype":"locality"
},
  "geometry": {"coordinates":[40.29268,23.81072],"type":"Point"}
}