{
  "type": "Feature",
  "properties": {
    "gn:admin1_code":"5",
    "gn:asciiname":"Al Kharma'",
    "gn:country_code":"SA",
    "gn:dem":193,
    "gn:feature_class":"P",
    "gn:feature_code":"PPL",
    "gn:name":"Al Kharm\u0101\u2019",
    "gn:population":0,
    "gn:timezone":"Asia/Riyadh",
    "iso:country":"SA",
    "name:ara_x_preferred":[
        "\u0627\u0644\u062e\u0631\u0645\u0627\u0621"
    ],
    "name:fas_x_preferred":[
        "\u0627\u0644\u062e\u0631\u0645\u0639"
    ],
    "name:nno_x_preferred":[
        "Al Kharma'"
    ],
    "name:und_x_variant":[
        "Kharmah",
        "Kharma",
        "Al Kharm\u0101\u2019"
    ],
    "name:urd_x_preferred":[
        "\u0627\u0644\u062e\u0631\u0645\u0627\u0621"
    ],
    "wof:name":"Al Kharma'",
    "wof:placetype":"locality"
},
  "geometry": {"coordinates":[38.89527,23.89686],"type":"Point"}
}