{
  "type": "Feature",
  "properties": {
    "gn:admin1_code":"10",
    "gn:asciiname":"Ahl Hunaysh",
    "gn:country_code":"SA",
    "gn:dem":610,
    "gn:feature_class":"P",
    "gn:feature_code":"PPL",
    "gn:name":"Ahl \u1e28unaysh",
    "gn:population":0,
    "gn:timezone":"Asia/Riyadh",
    "iso:country":"SA",
    "name:ara_x_preferred":[
        "\u0623\u0647\u0644 \u062d\u0646\u064a\u0634"
    ],
    "name:eng_x_preferred":[
        "Ahl Hunaysh"
    ],
    "name:und_x_variant":[
        "Al Hanish",
        "Ahl Hanaish",
        "Ahl \u1e28unaysh"
    ],
    "wof:name":"Ahl Hunaysh",
    "wof:placetype":"locality"
},
  "geometry": {"coordinates":[45.58333,20.46667],"type":"Point"}
}