{
  "type": "Feature",
  "properties": {
    "gn:admin1_code":"8",
    "gn:asciiname":"Al Qaysumah",
    "gn:country_code":"SA",
    "gn:dem":686,
    "gn:feature_class":"P",
    "gn:feature_code":"PPL",
    "gn:name":"Al Qay\u015f\u016bmah",
    "gn:population":0,
    "gn:timezone":"Asia/Riyadh",
    "iso:country":"SA",
    "name:ara_x_preferred":[
        "\u0627\u0644\u0642\u064a\u0635\u0648\u0645\u0629"
    ],
    "name:und_x_variant":[
        "Al Qay\u015f\u016bmah"
    ],
    "wof:name":"Al Qaysumah",
    "wof:placetype":"locality"
},
  "geometry": {"coordinates":[43.1748,25.7423],"type":"Point"}
}