{
  "type": "Feature",
  "properties": {
    "gn:admin1_code":"6",
    "gn:asciiname":"Ma`raj as Suban",
    "gn:country_code":"SA",
    "gn:dem":282,
    "gn:feature_class":"P",
    "gn:feature_code":"PPL",
    "gn:name":"Ma\u2018raj a\u015f S\u016bb\u0101n",
    "gn:population":0,
    "gn:timezone":"Asia/Riyadh",
    "iso:country":"SA",
    "name:ara_x_preferred":[
        "\u0645\u0639\u0631\u062c \u0627\u0644\u0633\u0648\u0628\u0627\u0646"
    ],
    "name:und_x_variant":[
        "Ma\u2018raj a\u015f S\u016bb\u0101n"
    ],
    "wof:name":"Ma`raj as Suban",
    "wof:placetype":"locality"
},
  "geometry": {"coordinates":[47.02585,27.97362],"type":"Point"}
}