{
  "type": "Feature",
  "properties": {
    "gn:admin1_code":"6",
    "gn:asciiname":"Az Zughayn",
    "gn:country_code":"SA",
    "gn:dem":72,
    "gn:feature_class":"P",
    "gn:feature_code":"PPL",
    "gn:name":"Az Zughayn",
    "gn:population":0,
    "gn:timezone":"Asia/Riyadh",
    "iso:country":"SA",
    "name:ara_x_preferred":[
        "\u0627\u0644\u0632\u0651\u064f\u063a\u064e\u064a\u0646"
    ],
    "name:und_x_variant":[
        "Uzughain",
        "Az Zughayn"
    ],
    "wof:name":"Az Zughayn",
    "wof:placetype":"locality"
},
  "geometry": {"coordinates":[48.42431,26.98298],"type":"Point"}
}