{
  "type": "Feature",
  "properties": {
    "gn:admin1_code":"14",
    "gn:asciiname":"`Ayn Sha`tha'",
    "gn:country_code":"SA",
    "gn:dem":73,
    "gn:feature_class":"P",
    "gn:feature_code":"PPL",
    "gn:name":"\u2018Ayn Sha\u2018th\u0101\u2019",
    "gn:population":0,
    "gn:timezone":"Asia/Riyadh",
    "iso:country":"SA",
    "name:und_x_variant":[
        "\u2018Ayn Sha\u2018\u0101thah",
        "\u2018Ayn Sha\u2018th\u0101\u2019"
    ],
    "wof:name":"`Ayn Sha`tha'",
    "wof:placetype":"locality"
},
  "geometry": {"coordinates":[39.30971,21.93929],"type":"Point"}
}