{
  "type": "Feature",
  "properties": {
    "gn:gn_country":"SA",
    "gn:gn_fcode":"PPL",
    "gn:gn_pop":6117,
    "gn:population":6117,
    "iso:country":"SA",
    "name:ara_x_preferred":[
        "\u0645\u0633\u0644\u064a\u0629"
    ],
    "name:unk_x_variant":[
        "Masliya"
    ],
    "qs_pg:aaroncc":"SA",
    "qs_pg:gn_country":"SA",
    "qs_pg:gn_fcode":"PPL",
    "qs_pg:gn_pop":6117,
    "qs_pg:name":"Misl\u012byah",
    "qs_pg:photos_9r":0,
    "qs_pg:photos_sr":0,
    "qs_pg:pop_sr":5,
    "qs_pg:qs_pg_placetype":"locality",
    "wof:name":"Misl\u012byah",
    "wof:placetype":"locality",
    "wof:population":6117
},
  "geometry": {"coordinates":[42.5572,17.45988],"type":"Point"}
}