{
  "type": "Feature",
  "properties": {
    "gn:admin1_code":"10",
    "gn:asciiname":"Al Ghayl",
    "gn:country_code":"SA",
    "gn:dem":790,
    "gn:feature_class":"P",
    "gn:feature_code":"PPL",
    "gn:name":"Al Ghayl",
    "gn:population":0,
    "gn:timezone":"Asia/Riyadh",
    "iso:country":"SA",
    "name:und_x_variant":[
        "Ghayl",
        "Ghail",
        "Al Ghayl"
    ],
    "wof:name":"Al Ghayl",
    "wof:placetype":"locality"
},
  "geometry": {"coordinates":[46.32343,22.6076],"type":"Point"}
}