{
  "type": "Feature",
  "properties": {
    "gn:admin1_code":"17",
    "gn:asciiname":"Umm an Narb",
    "gn:country_code":"SA",
    "gn:dem":149,
    "gn:feature_class":"P",
    "gn:feature_code":"PPL",
    "gn:name":"Umm an Narb",
    "gn:population":0,
    "gn:timezone":"Asia/Riyadh",
    "iso:country":"SA",
    "wof:name":"Umm an Narb",
    "wof:placetype":"locality"
},
  "geometry": {"coordinates":[43.12792,16.59708],"type":"Point"}
}