{
  "type": "Feature",
  "properties": {
    "gn:admin1_code":"0",
    "gn:asciiname":"Ash Shaykh",
    "gn:country_code":"SA",
    "gn:dem":2122,
    "gn:feature_class":"P",
    "gn:feature_code":"PPL",
    "gn:name":"Ash Shaykh",
    "gn:population":0,
    "gn:timezone":"Asia/Riyadh",
    "iso:country":"SA",
    "name:und_x_variant":[
        "Esh Sheikh",
        "Ash Shaykh"
    ],
    "wof:name":"Ash Shaykh",
    "wof:placetype":"locality"
},
  "geometry": {"coordinates":[42.04944,19.38614],"type":"Point"}
}