{
  "type": "Feature",
  "properties": {
    "gn:admin1_code":"11",
    "gn:asciiname":"Kufayrah",
    "gn:country_code":"SA",
    "gn:dem":77,
    "gn:feature_class":"P",
    "gn:feature_code":"PPL",
    "gn:name":"Kufayrah",
    "gn:population":0,
    "gn:timezone":"Asia/Riyadh",
    "iso:country":"SA",
    "name:und_x_variant":[
        "Kefeirah",
        "Kefire",
        "Kufayrah"
    ],
    "wof:name":"Kufayrah",
    "wof:placetype":"locality"
},
  "geometry": {"coordinates":[41.53333,18.78333],"type":"Point"}
}