{
  "type": "Feature",
  "properties": {
    "gn:admin1_code":"10",
    "gn:asciiname":"Ar Ruwaydah",
    "gn:country_code":"SA",
    "gn:dem":783,
    "gn:feature_class":"P",
    "gn:feature_code":"PPL",
    "gn:name":"Ar Ruway\u1e11ah",
    "gn:population":0,
    "gn:timezone":"Asia/Riyadh",
    "iso:country":"SA",
    "name:ara_x_preferred":[
        "\u0627\u0644\u0631\u0648\u064a\u0636\u0629"
    ],
    "name:und_x_variant":[
        "Ruwaidha",
        "Ruwaidhah",
        "Ruway\u1e11ah",
        "Ar Ruway\u1e11ah"
    ],
    "wof:name":"Ar Ruwaydah",
    "wof:placetype":"locality"
},
  "geometry": {"coordinates":[45.14175,25.87457],"type":"Point"}
}