{
  "type": "Feature",
  "properties": {
    "gn:admin1_code":"14",
    "gn:asciiname":"As Suwadah",
    "gn:country_code":"SA",
    "gn:dem":1711,
    "gn:feature_class":"P",
    "gn:feature_code":"PPL",
    "gn:name":"As Suwadah",
    "gn:population":0,
    "gn:timezone":"Asia/Riyadh",
    "iso:country":"SA",
    "name:und_x_variant":[
        "Sawd\u0101\u2019",
        "Sawdah",
        "As Suwadah"
    ],
    "wof:name":"As Suwadah",
    "wof:placetype":"locality"
},
  "geometry": {"coordinates":[40.51124,21.13229],"type":"Point"}
}