{
  "type": "Feature",
  "properties": {
    "gn:admin1_code":"13",
    "gn:asciiname":"Al Huwaydi",
    "gn:country_code":"SA",
    "gn:dem":1168,
    "gn:feature_class":"P",
    "gn:feature_code":"PPL",
    "gn:name":"Al Huwayd\u012b",
    "gn:population":0,
    "gn:timezone":"Asia/Riyadh",
    "iso:country":"SA",
    "name:ara_x_preferred":[
        "\u0627\u0644\u0647\u0648\u064a\u062f\u064a"
    ],
    "name:und_x_variant":[
        "Al Huwayd\u012b"
    ],
    "wof:name":"Al Huwaydi",
    "wof:placetype":"locality"
},
  "geometry": {"coordinates":[41.31981,27.02366],"type":"Point"}
}