{
  "type": "Feature",
  "properties": {
    "gn:admin1_code":"5",
    "gn:asciiname":"Al Jabriyah",
    "gn:country_code":"SA",
    "gn:dem":188,
    "gn:feature_class":"P",
    "gn:feature_code":"PPL",
    "gn:name":"Al Jabr\u012byah",
    "gn:population":0,
    "gn:timezone":"Asia/Riyadh",
    "iso:country":"SA",
    "name:ara_x_preferred":[
        "\u0627\u0644\u062c\u0627\u0628\u0631\u064a\u0629"
    ],
    "name:ell_x_preferred":[
        "\u0391\u03bb \u03a4\u03b6\u03b1\u03bc\u03c0\u03c1\u03af\u03b3\u03b9\u03b1"
    ],
    "name:fas_x_preferred":[
        "\u0627\u0644\u062c\u0628\u0631\u06cc\u0627\u0647"
    ],
    "name:nno_x_preferred":[
        "Al Jabriyah"
    ],
    "name:und_x_variant":[
        "Jabraya",
        "Al Jabr\u012byah"
    ],
    "name:urd_x_preferred":[
        "\u0627\u0644\u062c\u0627\u0628\u0631\u06cc\u06c1"
    ],
    "wof:name":"Al Jabriyah",
    "wof:placetype":"locality"
},
  "geometry": {"coordinates":[38.52,24.25235],"type":"Point"}
}