{
  "type": "Feature",
  "properties": {
    "gn:admin1_code":"5",
    "gn:asciiname":"Al Jabriyah",
    "gn:country_code":"SA",
    "gn:dem":188,
    "gn:feature_class":"P",
    "gn:feature_code":"PPL",
    "gn:name":"Al Jabr\u012byah",
    "gn:population":0,
    "gn:timezone":"Asia/Riyadh",
    "iso:country":"SA",
    "name:und_x_variant":[
        "Jabraya",
        "Al Jabr\u012byah"
    ],
    "wof:name":"Al Jabriyah",
    "wof:placetype":"locality"
},
  "geometry": {"coordinates":[38.52,24.25235],"type":"Point"}
}