{
  "type": "Feature",
  "properties": {
    "gn:admin1_code":"6.0",
    "gn:asciiname":"Al Qudayh",
    "gn:country_code":"SA",
    "gn:dem":10,
    "gn:feature_class":"P",
    "gn:feature_code":"PPL",
    "gn:name":"Al Quday\u1e29",
    "gn:population":0,
    "gn:timezone":"Asia/Riyadh",
    "iso:country":"SA",
    "name:und_x_variant":[
        "Al Quday\u1e29"
    ],
    "wof:name":"Al Qudayh",
    "wof:placetype":"neighbourhood"
},
  "geometry": {"coordinates":[49.98944,26.56889],"type":"Point"}
}