{
  "type": "Feature",
  "properties": {
    "gn:admin1_code":"17",
    "gn:asciiname":"Umm `Araj",
    "gn:country_code":"SA",
    "gn:dem":110,
    "gn:feature_class":"P",
    "gn:feature_code":"PPL",
    "gn:name":"Umm \u2018Araj",
    "gn:population":0,
    "gn:timezone":"Asia/Riyadh",
    "iso:country":"SA",
    "name:und_x_variant":[
        "Umm \u2018Araj"
    ],
    "wof:name":"Umm `Araj",
    "wof:placetype":"locality"
},
  "geometry": {"coordinates":[43.03121,16.73863],"type":"Point"}
}