{
  "type": "Feature",
  "properties": {
    "gn:admin1_code":"13",
    "gn:asciiname":"Ad Darah",
    "gn:country_code":"SA",
    "gn:dem":1125,
    "gn:feature_class":"P",
    "gn:feature_code":"PPL",
    "gn:name":"Ad D\u0101rah",
    "gn:population":0,
    "gn:timezone":"Asia/Riyadh",
    "iso:country":"SA",
    "name:ara_x_preferred":[
        "\u0627\u0644\u062f\u0627\u0631\u0629"
    ],
    "name:und_x_variant":[
        "Ad D\u0101rah"
    ],
    "wof:name":"Ad Darah",
    "wof:placetype":"locality"
},
  "geometry": {"coordinates":[41.46276,27.00527],"type":"Point"}
}