{
  "type": "Feature",
  "properties": {
    "gn:admin1_code":"10",
    "gn:asciiname":"Al Bu`aythiyah",
    "gn:country_code":"SA",
    "gn:dem":851,
    "gn:feature_class":"P",
    "gn:feature_code":"PPL",
    "gn:name":"Al Bu\u2018ayth\u012byah",
    "gn:population":0,
    "gn:timezone":"Asia/Riyadh",
    "iso:country":"SA",
    "name:ara_x_preferred":[
        "\u0627\u0644\u0628\u0639\u064a\u062b\u064a\u0629"
    ],
    "name:und_x_variant":[
        "Al Bu\u2018ayth\u012byah"
    ],
    "wof:name":"Al Bu`aythiyah",
    "wof:placetype":"locality"
},
  "geometry": {"coordinates":[45.08954,24.11723],"type":"Point"}
}