{
  "type": "Feature",
  "properties": {
    "gn:admin1_code":"17.0",
    "gn:asciiname":"Al Kadarah",
    "gn:country_code":"SA",
    "gn:dem":176,
    "gn:feature_class":"P",
    "gn:feature_code":"PPL",
    "gn:name":"Al Kad\u0101rah",
    "gn:population":0,
    "gn:timezone":"Asia/Riyadh",
    "iso:country":"SA",
    "name:ara_x_preferred":[
        "\u0627\u0644\u0643\u062f\u0627\u0631\u0629"
    ],
    "name:und_x_variant":[
        "Al Kad\u0101rah"
    ],
    "wof:name":"Al Kadarah",
    "wof:placetype":"locality"
},
  "geometry": {"coordinates":[42.33605,17.78678],"type":"Point"}
}