{
  "type": "Feature",
  "properties": {
    "gn:admin1_code":"13",
    "gn:asciiname":"Al `Uqlah",
    "gn:country_code":"SA",
    "gn:dem":1179,
    "gn:feature_class":"P",
    "gn:feature_code":"PPL",
    "gn:name":"Al \u2018Uqlah",
    "gn:population":0,
    "gn:timezone":"Asia/Riyadh",
    "iso:country":"SA",
    "name:ara_x_preferred":[
        "\u0627\u0644\u0639\u0642\u0644\u0629"
    ],
    "name:und_x_variant":[
        "Al \u2018Uqlah"
    ],
    "wof:name":"Al `Uqlah",
    "wof:placetype":"locality"
},
  "geometry": {"coordinates":[41.27944,27.10213],"type":"Point"}
}