{
  "type": "Feature",
  "properties": {
    "gn:admin1_code":"6.0",
    "gn:asciiname":"`Ayn ash Shaqab",
    "gn:country_code":"SA",
    "gn:dem":4,
    "gn:feature_class":"P",
    "gn:feature_code":"PPL",
    "gn:name":"\u2018Ayn ash Shaqab",
    "gn:population":0,
    "gn:timezone":"Asia/Riyadh",
    "iso:country":"SA",
    "name:und_x_variant":[
        "\u2018Ayn ash Shaqab"
    ],
    "wof:name":"`Ayn ash Shaqab",
    "wof:placetype":"locality"
},
  "geometry": {"coordinates":[49.955,26.68361],"type":"Point"}
}