{
  "type": "Feature",
  "properties": {
    "gn:admin1_code":"10",
    "gn:asciiname":"Al Jadidah",
    "gn:country_code":"SA",
    "gn:dem":697,
    "gn:feature_class":"P",
    "gn:feature_code":"PPL",
    "gn:name":"Al Jad\u012bdah",
    "gn:population":0,
    "gn:timezone":"Asia/Riyadh",
    "iso:country":"SA",
    "name:ara_x_preferred":[
        "\u0627\u0644\u062c\u062f\u064a\u062f\u0629"
    ],
    "name:fas_x_preferred":[
        "\u0627\u0644\u062c\u062f\u06cc\u062f\u0627\u0647"
    ],
    "name:nno_x_preferred":[
        "Al Jadidah"
    ],
    "name:und_x_variant":[
        "Al Jad\u012bdah"
    ],
    "wof:name":"Al Jadidah",
    "wof:placetype":"locality"
},
  "geometry": {"coordinates":[45.81583,24.41385],"type":"Point"}
}