{
  "type": "Feature",
  "properties": {
    "gn:admin1_code":"14",
    "gn:asciiname":"Al Ashraf",
    "gn:country_code":"SA",
    "gn:dem":153,
    "gn:feature_class":"P",
    "gn:feature_code":"PPL",
    "gn:name":"Al Ashr\u0101f",
    "gn:population":0,
    "gn:timezone":"Asia/Riyadh",
    "iso:country":"SA",
    "name:ara_x_preferred":[
        "Al Ashr\u0101f"
    ],
    "wof:name":"Al Ashraf",
    "wof:placetype":"locality"
},
  "geometry": {"coordinates":[39.62042,21.51356],"type":"Point"}
}