{
  "type": "Feature",
  "properties": {
    "gn:admin1_code":"13",
    "gn:asciiname":"Ash Shinan",
    "gn:country_code":"SA",
    "gn:dem":903,
    "gn:feature_class":"P",
    "gn:feature_code":"PPL",
    "gn:name":"Ash Shin\u0101n",
    "gn:population":0,
    "gn:timezone":"Asia/Riyadh",
    "iso:country":"SA",
    "name:ara_x_preferred":[
        "Ash Shin\u0101n"
    ],
    "name:ara_x_variant":[
        "\u0627\u0644\u0634\u0651\u0650\u0646\u0627\u0646"
    ],
    "wof:name":"Ash Shinan",
    "wof:placetype":"locality"
},
  "geometry": {"coordinates":[42.4449,27.17478],"type":"Point"}
}