{
  "type": "Feature",
  "properties": {
    "gn:admin1_code":"0",
    "gn:asciiname":"Hulayfa'",
    "gn:country_code":"SA",
    "gn:dem":966,
    "gn:feature_class":"P",
    "gn:feature_code":"PPL",
    "gn:name":"\u1e28ulayf\u0101\u2019",
    "gn:population":0,
    "gn:timezone":"Asia/Riyadh",
    "iso:country":"SA",
    "name:und_x_variant":[
        "\u1e28ulayfah",
        "Hulaifa",
        "\u1e28ulayf\u0101\u2019"
    ],
    "wof:name":"Hulayfa'",
    "wof:placetype":"locality"
},
  "geometry": {"coordinates":[40.81391,25.99343],"type":"Point"}
}