{
  "type": "Feature",
  "properties": {
    "gn:admin1_code":"5.0",
    "gn:asciiname":"Al Gharid",
    "gn:country_code":"SA",
    "gn:dem":798,
    "gn:feature_class":"P",
    "gn:feature_code":"PPL",
    "gn:name":"Al Gharid",
    "gn:population":0,
    "gn:timezone":"Asia/Riyadh",
    "iso:country":"SA",
    "name:ara_x_preferred":[
        "\u0627\u0644\u063a\u0631\u064a\u0636"
    ],
    "name:und_x_variant":[
        "Al Ghar\u012b\u1e11",
        "Al Gharid"
    ],
    "wof:name":"Al Gharid",
    "wof:placetype":"locality"
},
  "geometry": {"coordinates":[39.38621,24.31368],"type":"Point"}
}