{
  "type": "Feature",
  "properties": {
    "gn:admin1_code":"10",
    "gn:asciiname":"At Tasrir",
    "gn:country_code":"SA",
    "gn:dem":794,
    "gn:feature_class":"P",
    "gn:feature_code":"PPL",
    "gn:name":"At Tasr\u012br",
    "gn:population":0,
    "gn:timezone":"Asia/Riyadh",
    "iso:country":"SA",
    "name:ara_x_preferred":[
        "\u0627\u0644\u062a\u0651\u064e\u0633\u0631\u0650\u064a\u0631"
    ],
    "name:und_x_variant":[
        "At Tasr\u012br"
    ],
    "wof:name":"At Tasrir",
    "wof:placetype":"locality"
},
  "geometry": {"coordinates":[44.28411,25.08309],"type":"Point"}
}