{
  "type": "Feature",
  "properties": {
    "gn:admin1_code":"20",
    "gn:asciiname":"`Alaqan",
    "gn:country_code":"SA",
    "gn:dem":1197,
    "gn:feature_class":"P",
    "gn:feature_code":"PPL",
    "gn:name":"\u2018Al\u0101q\u0101n",
    "gn:population":0,
    "gn:timezone":"Asia/Riyadh",
    "iso:country":"SA",
    "name:ara_x_preferred":[
        "\u2018Al\u0101q\u0101n"
    ],
    "wof:name":"`Alaqan",
    "wof:placetype":"locality"
},
  "geometry": {"coordinates":[35.40215999999999,29.15027000000001],"type":"Point"}
}