{
  "type": "Feature",
  "properties": {
    "gn:admin1_code":"20",
    "gn:asciiname":"Mazra`at Sultanah",
    "gn:country_code":"SA",
    "gn:dem":650,
    "gn:feature_class":"P",
    "gn:feature_code":"PPL",
    "gn:name":"Mazra\u2018at Sul\u0163\u0101nah",
    "gn:population":0,
    "gn:timezone":"Asia/Riyadh",
    "iso:country":"SA",
    "name:und_x_variant":[
        "Mazra\u2018at Sul\u0163\u0101nah"
    ],
    "wof:name":"Mazra`at Sultanah",
    "wof:placetype":"locality"
},
  "geometry": {"coordinates":[40.21833,30.24444],"type":"Point"}
}