{
  "type": "Feature",
  "properties": {
    "gn:admin1_code":"0",
    "gn:asciiname":"Al Farhaniyah",
    "gn:country_code":"SA",
    "gn:dem":948,
    "gn:feature_class":"P",
    "gn:feature_code":"PPL",
    "gn:name":"Al Far\u1e29\u0101n\u012byah",
    "gn:population":0,
    "gn:timezone":"Asia/Riyadh",
    "iso:country":"SA",
    "name:ara_x_preferred":[
        "\u0627\u0644\u0641\u0631\u062d\u0627\u0646\u064a\u0629"
    ],
    "name:und_x_variant":[
        "Al Far\u1e29\u0101n\u012byah"
    ],
    "wof:name":"Al Farhaniyah",
    "wof:placetype":"locality"
},
  "geometry": {"coordinates":[40.93876,27.31137],"type":"Point"}
}