{
  "type": "Feature",
  "properties": {
    "gn:admin1_code":"0",
    "gn:asciiname":"Harrat al Azahirah",
    "gn:country_code":"SA",
    "gn:dem":1890,
    "gn:feature_class":"P",
    "gn:feature_code":"PPL",
    "gn:name":"\u1e28arrat al Az\u0101hirah",
    "gn:population":0,
    "gn:timezone":"Asia/Riyadh",
    "iso:country":"SA",
    "name:und_x_variant":[
        "\u1e28arrat al Az\u0101hirah"
    ],
    "wof:name":"Harrat al Azahirah",
    "wof:placetype":"locality"
},
  "geometry": {"coordinates":[41.73333,19.81667],"type":"Point"}
}