{
  "type": "Feature",
  "properties": {
    "gn:country":"SA",
    "gn:fcode":"PPL",
    "gn:population":1000,
    "iso:country":"SA",
    "name:fas_x_preferred":[
        "\u0634\u06cc\u0628\u0629"
    ],
    "name:rus_x_preferred":[
        "\u0428\u0435\u0439\u0431\u0430"
    ],
    "name:urd_x_preferred":[
        "\u0634\u06cc\u0628\u06c1"
    ],
    "qs_pg:aaroncc":"SA",
    "qs_pg:gn_country":"SA",
    "qs_pg:gn_fcode":"PPL",
    "qs_pg:gn_pop":1000,
    "qs_pg:name":"Shaybah",
    "qs_pg:photos_9r":0,
    "qs_pg:photos_sr":0,
    "qs_pg:pop_sr":2,
    "qs_pg:qs_pg_placetype":"locality",
    "wof:name":"Shaybah",
    "wof:placetype":"locality",
    "wof:population":1000
},
  "geometry": {"coordinates":[54.09599,22.59246],"type":"Point"}
}