{
  "type": "Feature",
  "properties": {
    "gn:admin1_code":"17.0",
    "gn:asciiname":"Ar Ramadah",
    "gn:country_code":"SA",
    "gn:dem":91,
    "gn:feature_class":"P",
    "gn:feature_code":"PPL",
    "gn:name":"Ar Ram\u0101dah",
    "gn:population":0,
    "gn:timezone":"Asia/Riyadh",
    "iso:country":"SA",
    "name:und_x_variant":[
        "Ar Ram\u0101dah"
    ],
    "wof:name":"Ar Ramadah",
    "wof:placetype":"locality"
},
  "geometry": {"coordinates":[42.99301,16.69146],"type":"Point"}
}