{
  "type": "Feature",
  "properties": {
    "gn:admin1_code":"5",
    "gn:asciiname":"As Safra'",
    "gn:country_code":"SA",
    "gn:dem":277,
    "gn:feature_class":"P",
    "gn:feature_code":"PPL",
    "gn:name":"A\u015f \u015eafr\u0101\u2019",
    "gn:population":0,
    "gn:timezone":"Asia/Riyadh",
    "iso:country":"SA",
    "name:ara_x_preferred":[
        "\u0648\u0627\u062f\u064a \u0627\u0644\u0635\u0641\u0631\u0627\u0621"
    ],
    "name:fas_x_preferred":[
        "\u0627\u0644\u0635\u0641\u0631\u0627"
    ],
    "name:nno_x_preferred":[
        "As Safra'"
    ],
    "name:und_x_variant":[
        "Khayf al \u1e28iz\u0101m",
        "A\u015f \u015eafr\u0101\u2019"
    ],
    "name:urd_x_preferred":[
        "\u0648\u0627\u062f\u06cc \u0635\u0641\u0631\u0627\u0621"
    ],
    "wof:name":"As Safra'",
    "wof:placetype":"locality"
},
  "geometry": {"coordinates":[38.92278,24.01278],"type":"Point"}
}