{
  "type": "Feature",
  "properties": {
    "gn:admin1_code":"10",
    "gn:asciiname":"Ar Rawdah",
    "gn:country_code":"SA",
    "gn:dem":539,
    "gn:feature_class":"P",
    "gn:feature_code":"PPL",
    "gn:name":"Ar Raw\u1e11ah",
    "gn:population":0,
    "gn:timezone":"Asia/Riyadh",
    "iso:country":"SA",
    "name:und_x_variant":[
        "Al-Raw\u1e0da",
        "Raw\u1e11ah",
        "Raudha",
        "Raudhah",
        "Ar Raw\u1e11ah"
    ],
    "wof:name":"Ar Rawdah",
    "wof:placetype":"locality"
},
  "geometry": {"coordinates":[46.68649,22.20609],"type":"Point"}
}