{
  "type": "Feature",
  "properties": {
    "gn:admin1_code":"10",
    "gn:asciiname":"Al Hayathim",
    "gn:country_code":"SA",
    "gn:dem":442,
    "gn:feature_class":"P",
    "gn:feature_code":"PPL",
    "gn:name":"Al Hay\u0101thim",
    "gn:population":0,
    "gn:timezone":"Asia/Riyadh",
    "iso:country":"SA",
    "name:ara_x_preferred":[
        "\u0627\u0644\u0647\u064a\u0627\u062b\u0645"
    ],
    "name:und_x_variant":[
        "Al Hay\u0101thim",
        "Al Hayathim"
    ],
    "wof:name":"Al Hayathim",
    "wof:placetype":"locality"
},
  "geometry": {"coordinates":[47.23764,24.16555],"type":"Point"}
}