{
  "type": "Feature",
  "properties": {
    "gn:admin1_code":"10",
    "gn:asciiname":"Mudaysis",
    "gn:country_code":"SA",
    "gn:dem":940,
    "gn:feature_class":"P",
    "gn:feature_code":"PPL",
    "gn:name":"Mudays\u012bs",
    "gn:population":0,
    "gn:timezone":"Asia/Riyadh",
    "iso:country":"SA",
    "name:ara_x_preferred":[
        "\u0645\u062f\u064a\u0633\u064a\u0633"
    ],
    "name:und_x_variant":[
        "Mudays\u012bs"
    ],
    "wof:name":"Mudaysis",
    "wof:placetype":"locality"
},
  "geometry": {"coordinates":[43.4315,25.2357],"type":"Point"}
}