{
  "type": "Feature",
  "properties": {
    "gn:admin1_code":"0",
    "gn:asciiname":"Haqqaq",
    "gn:country_code":"SA",
    "gn:dem":47,
    "gn:feature_class":"P",
    "gn:feature_code":"PPL",
    "gn:name":"\u1e28aqqaq",
    "gn:population":0,
    "gn:timezone":"Asia/Riyadh",
    "iso:country":"SA",
    "name:und_x_variant":[
        "\u1e28aqqaq"
    ],
    "wof:name":"Haqqaq",
    "wof:placetype":"locality"
},
  "geometry": {"coordinates":[39.26667,22.81667],"type":"Point"}
}