{
  "type": "Feature",
  "properties": {
    "gn:admin1_code":"13",
    "gn:asciiname":"Fayd",
    "gn:country_code":"SA",
    "gn:dem":884,
    "gn:feature_class":"P",
    "gn:feature_code":"PPL",
    "gn:name":"Fayd",
    "gn:population":0,
    "gn:timezone":"Asia/Riyadh",
    "iso:country":"SA",
    "name:ara_x_preferred":[
        "\u0641\u064e\u064a\u062f"
    ],
    "name:und_x_variant":[
        "Fejd",
        "Faid",
        "Fayd"
    ],
    "wof:name":"Fayd",
    "wof:placetype":"locality"
},
  "geometry": {"coordinates":[42.51814,27.11368],"type":"Point"}
}