{
  "type": "Feature",
  "properties": {
    "gn:admin1_code":"0",
    "gn:asciiname":"Umm Qanburah",
    "gn:country_code":"SA",
    "gn:dem":70,
    "gn:feature_class":"P",
    "gn:feature_code":"PPL",
    "gn:name":"Umm Qanb\u016brah",
    "gn:population":0,
    "gn:timezone":"Asia/Riyadh",
    "iso:country":"SA",
    "name:ara_x_preferred":[
        "\u0623\u0645 \u0642\u0646\u0628\u0648\u0631\u0629"
    ],
    "name:eng_x_preferred":[
        "Umm Qanburah"
    ],
    "name:und_x_variant":[
        "Umm Qanb\u016brah"
    ],
    "wof:name":"Umm Qanburah",
    "wof:placetype":"locality"
},
  "geometry": {"coordinates":[42.85,16.98333],"type":"Point"}
}