{
  "type": "Feature",
  "properties": {
    "gn:admin1_code":"10",
    "gn:asciiname":"Al Maghrafiyah",
    "gn:country_code":"SA",
    "gn:dem":706,
    "gn:feature_class":"P",
    "gn:feature_code":"PPL",
    "gn:name":"Al Maghraf\u012byah",
    "gn:population":0,
    "gn:timezone":"Asia/Riyadh",
    "iso:country":"SA",
    "name:ara_x_preferred":[
        "\u0627\u0644\u0645\u063a\u0631\u0641\u064a\u0629"
    ],
    "name:und_x_variant":[
        "Al Maghraf\u012byah",
        "Al Maghrafiyah"
    ],
    "wof:name":"Al Maghrafiyah",
    "wof:placetype":"locality"
},
  "geometry": {"coordinates":[46.44417,24.44084],"type":"Point"}
}